{
  "type": "Feature",
  "properties": {
    "gn:admin1_code":"2.0",
    "gn:admin2_code":"9143474.0",
    "gn:asciiname":"Kongbo",
    "gn:cc2":"CF",
    "gn:country_code":"CF",
    "gn:dem":478,
    "gn:feature_class":"P",
    "gn:feature_code":"PPL",
    "gn:name":"Kongbo",
    "gn:population":0,
    "gn:timezone":"Africa/Bangui",
    "iso:country":"CF",
    "name:und_x_variant":[
        "B\u00e9pa",
        "Kongbo"
    ],
    "wof:name":"Kongbo",
    "wof:placetype":"locality"
},
  "geometry": {"coordinates":[21.38333,4.73333],"type":"Point"}
}