{
  "type": "Feature",
  "properties": {
    "gn:admin1_code":"12.0",
    "gn:admin2_code":"9143477.0",
    "gn:asciiname":"Bobadouna",
    "gn:country_code":"CF",
    "gn:dem":534,
    "gn:feature_class":"P",
    "gn:feature_code":"PPL",
    "gn:name":"Bobadouna",
    "gn:population":0,
    "gn:timezone":"Africa/Bangui",
    "iso:country":"CF",
    "wof:name":"Bobadouna",
    "wof:placetype":"locality"
},
  "geometry": {"coordinates":[18.43333,6.01667],"type":"Point"}
}