{
  "type": "Feature",
  "properties": {
    "gn:admin1_code":"7.0",
    "gn:admin2_code":"7732068.0",
    "gn:asciiname":"Mbale",
    "gn:cc2":"CF",
    "gn:country_code":"CF",
    "gn:dem":449,
    "gn:feature_class":"P",
    "gn:feature_code":"PPL",
    "gn:name":"Mbal\u00e9",
    "gn:population":0,
    "gn:timezone":"Africa/Bangui",
    "iso:country":"CF",
    "name:ceb_x_preferred":[
        "Mbale"
    ],
    "name:dan_x_preferred":[
        "Mbale"
    ],
    "name:deu_x_preferred":[
        "Mbale"
    ],
    "name:fra_x_preferred":[
        "Mbale"
    ],
    "name:heb_x_preferred":[
        "\u05de\u05d1\u05d0\u05dd"
    ],
    "name:heb_x_variant":[
        "\u05de\u05d1\u05d0\u05dc\u05d4"
    ],
    "name:hrv_x_preferred":[
        "Mbale"
    ],
    "name:hun_x_preferred":[
        "Mbale"
    ],
    "name:ita_x_preferred":[
        "Mbale"
    ],
    "name:kal_x_preferred":[
        "Mbale"
    ],
    "name:lit_x_preferred":[
        "Mbal\u0117"
    ],
    "name:mri_x_preferred":[
        "Mbale"
    ],
    "name:nld_x_preferred":[
        "Mbale"
    ],
    "name:pol_x_preferred":[
        "Mbale"
    ],
    "name:ron_x_preferred":[
        "Mbale"
    ],
    "name:rus_x_preferred":[
        "\u041c\u0431\u0430\u043b\u0435"
    ],
    "name:swa_x_preferred":[
        "Mbale"
    ],
    "name:swe_x_preferred":[
        "Mbale"
    ],
    "name:tur_x_preferred":[
        "Mbale"
    ],
    "name:und_x_variant":[
        "M\u2019Ba",
        "Mbal\u00e9"
    ],
    "name:urd_x_preferred":[
        "\u0645\u0628\u0627\u0644\u06d2"
    ],
    "name:zho_x_preferred":[
        "\u59c6\u5df4\u840a"
    ],
    "wof:name":"Mbale",
    "wof:placetype":"locality"
},
  "geometry": {"coordinates":[17.78333,4.41667],"type":"Point"}
}