{
  "type": "Feature",
  "properties": {
    "gn:admin1_code":"7.0",
    "gn:admin2_code":"7732068.0",
    "gn:asciiname":"Mbale",
    "gn:cc2":"CF",
    "gn:country_code":"CF",
    "gn:dem":449,
    "gn:feature_class":"P",
    "gn:feature_code":"PPL",
    "gn:name":"Mbal\u00e9",
    "gn:population":0,
    "gn:timezone":"Africa/Bangui",
    "iso:country":"CF",
    "name:und_x_variant":[
        "M\u2019Ba",
        "Mbal\u00e9"
    ],
    "wof:name":"Mbale",
    "wof:placetype":"locality"
},
  "geometry": {"coordinates":[17.78333,4.41667],"type":"Point"}
}