{
  "type": "Feature",
  "properties": {
    "gn:admin1_code":"7.0",
    "gn:admin2_code":"9143487.0",
    "gn:asciiname":"Pokoli",
    "gn:country_code":"CF",
    "gn:dem":498,
    "gn:feature_class":"P",
    "gn:feature_code":"PPL",
    "gn:name":"Pokoli",
    "gn:population":0,
    "gn:timezone":"Africa/Bangui",
    "iso:country":"CF",
    "wof:name":"Pokoli",
    "wof:placetype":"locality"
},
  "geometry": {"coordinates":[17.55,4.45],"type":"Point"}
}