{
  "type": "Feature",
  "properties": {
    "gn:admin1_code":"7.0",
    "gn:admin2_code":"9143486.0",
    "gn:asciiname":"Borongue",
    "gn:country_code":"CF",
    "gn:dem":683,
    "gn:feature_class":"P",
    "gn:feature_code":"PPL",
    "gn:name":"Borongu\u00e9",
    "gn:population":0,
    "gn:timezone":"Africa/Bangui",
    "iso:country":"CF",
    "wof:name":"Borongue",
    "wof:placetype":"locality"
},
  "geometry": {"coordinates":[17.36667000000001,4.75],"type":"Point"}
}