{
  "type": "Feature",
  "properties": {
    "gn:admin1_code":"4.0",
    "gn:admin2_code":"7732917.0",
    "gn:asciiname":"Pondo",
    "gn:country_code":"CF",
    "gn:dem":709,
    "gn:feature_class":"P",
    "gn:feature_code":"PPL",
    "gn:name":"Pondo",
    "gn:population":0,
    "gn:timezone":"Africa/Bangui",
    "iso:country":"CF",
    "name:swe_x_preferred":[
        "Pondo"
    ],
    "wof:name":"Pondo",
    "wof:placetype":"locality"
},
  "geometry": {"coordinates":[16.69645,5.21172],"type":"Point"}
}