{
  "type": "Feature",
  "properties": {
    "gn:country":"CF",
    "gn:fcode":"PPL",
    "gn:pop":13459,
    "iso:country":"CF",
    "name:dut_x_preferred":[
        "Rafa\u00ef"
    ],
    "name:eng_x_preferred":[
        "Rafa\u00ef"
    ],
    "name:fre_x_preferred":[
        "Rafa\u00ef"
    ],
    "name:ita_x_preferred":[
        "Rafa\u00ef"
    ],
    "name:jpn_x_preferred":[
        "\u30e9\u30d5\u30a1\u30a4"
    ],
    "name:pol_x_preferred":[
        "Rafa\u00ef"
    ],
    "name:rum_x_preferred":[
        "Rafa\u00ef"
    ],
    "name:rus_x_preferred":[
        "\u0420\u0430\u0444\u0430\u0438"
    ],
    "name:swe_x_preferred":[
        "Rafai"
    ],
    "qs:name":"Rafa\u00ef",
    "qs:photos_9r":0,
    "qs:photos_sr":0,
    "qs:pop_sr":"6",
    "wd:wordcount":90,
    "wof:name":"Rafa\u00ef",
    "wof:placetype":"locality",
    "wof:population":13459
},
  "geometry": {"coordinates":[23.91667,4.95],"type":"Point"}
}