{
  "type": "Feature",
  "properties": {
    "gn:admin1_code":"17.0",
    "gn:admin2_code":"8299285.0",
    "gn:asciiname":"Boubadoule",
    "gn:country_code":"CF",
    "gn:dem":480,
    "gn:feature_class":"P",
    "gn:feature_code":"PPL",
    "gn:name":"Boubadoul\u00e9",
    "gn:population":0,
    "gn:timezone":"Africa/Bangui",
    "iso:country":"CF",
    "wof:name":"Boubadoule",
    "wof:placetype":"locality"
},
  "geometry": {"coordinates":[17.68807,4.57496],"type":"Point"}
}