{
  "type": "Feature",
  "properties": {
    "gn:admin1_code":"17",
    "gn:admin2_code":"7732723.0",
    "gn:asciiname":"Boziboro",
    "gn:country_code":"CF",
    "gn:dem":662,
    "gn:feature_class":"P",
    "gn:feature_code":"PPL",
    "gn:name":"Boziboro",
    "gn:population":0,
    "gn:timezone":"Africa/Bangui",
    "iso:country":"CF",
    "wof:name":"Boziboro",
    "wof:placetype":"locality"
},
  "geometry": {"coordinates":[17.52031,5.04028],"type":"Point"}
}