{
  "type": "Feature",
  "properties": {
    "gn:admin1_code":"4.0",
    "gn:admin2_code":"9143488.0",
    "gn:asciiname":"Kambayeke",
    "gn:country_code":"CF",
    "gn:dem":557,
    "gn:feature_class":"P",
    "gn:feature_code":"PPL",
    "gn:name":"Kambay\u00e9k\u00e9",
    "gn:population":0,
    "gn:timezone":"Africa/Bangui",
    "iso:country":"CF",
    "wof:name":"Kambayeke",
    "wof:placetype":"locality"
},
  "geometry": {"coordinates":[15.32835,3.891],"type":"Point"}
}