{
  "type": "Feature",
  "properties": {
    "gn:admin1_code":"6.0",
    "gn:admin2_code":"7731894.0",
    "gn:asciiname":"Doumounou",
    "gn:country_code":"CF",
    "gn:dem":418,
    "gn:feature_class":"P",
    "gn:feature_code":"PPL",
    "gn:name":"Doumounou",
    "gn:population":0,
    "gn:timezone":"Africa/Bangui",
    "iso:country":"CF",
    "name:und_x_variant":[
        "Doumonou"
    ],
    "wof:name":"Doumounou",
    "wof:placetype":"locality"
},
  "geometry": {"coordinates":[19.10939,5.56434],"type":"Point"}
}