{
  "type": "Feature",
  "properties": {
    "gn:admin1_code":"17.0",
    "gn:admin2_code":"7732372.0",
    "gn:asciiname":"Seyango",
    "gn:country_code":"CF",
    "gn:dem":677,
    "gn:feature_class":"P",
    "gn:feature_code":"PPL",
    "gn:name":"Seyango",
    "gn:population":0,
    "gn:timezone":"Africa/Bangui",
    "iso:country":"CF",
    "name:und_x_variant":[
        "S\u00e9angou",
        "Siango",
        "Seyango"
    ],
    "wof:name":"Seyango",
    "wof:placetype":"locality"
},
  "geometry": {"coordinates":[17.15384,5.13592],"type":"Point"}
}