{
  "type": "Feature",
  "properties": {
    "gn:admin1_code":"2.0",
    "gn:admin2_code":"7731891.0",
    "gn:asciiname":"Langande",
    "gn:cc2":"CF",
    "gn:country_code":"CF",
    "gn:dem":595,
    "gn:feature_class":"P",
    "gn:feature_code":"PPL",
    "gn:name":"Langand\u00e9",
    "gn:population":0,
    "gn:timezone":"Africa/Bangui",
    "iso:country":"CF",
    "name:und_x_variant":[
        "Ima",
        "Langand\u00e9"
    ],
    "wof:name":"Langande",
    "wof:placetype":"locality"
},
  "geometry": {"coordinates":[21.26667,4.45],"type":"Point"}
}