{
  "type": "Feature",
  "properties": {
    "gn:admin1_code":"12.0",
    "gn:admin2_code":"7732115.0",
    "gn:asciiname":"Bofill",
    "gn:country_code":"CF",
    "gn:dem":509,
    "gn:feature_class":"P",
    "gn:feature_code":"PPL",
    "gn:name":"Bofill",
    "gn:population":0,
    "gn:timezone":"Africa/Bangui",
    "iso:country":"CF",
    "name:cat_x_preferred":[
        "Bofill"
    ],
    "name:deu_x_preferred":[
        "Bofill"
    ],
    "name:fra_x_preferred":[
        "Bofill"
    ],
    "name:spa_x_preferred":[
        "Bofill"
    ],
    "name:und_x_variant":[
        "Bofil\u00e9",
        "Bofill"
    ],
    "wof:name":"Bofill",
    "wof:placetype":"locality"
},
  "geometry": {"coordinates":[17.38187000000001,6.60252],"type":"Point"}
}