{
  "type": "Feature",
  "properties": {
    "gn:admin1_code":"17.0",
    "gn:admin2_code":"7732723.0",
    "gn:asciiname":"Boese",
    "gn:country_code":"CF",
    "gn:dem":678,
    "gn:feature_class":"P",
    "gn:feature_code":"PPL",
    "gn:name":"Bo\u00e9s\u00e9",
    "gn:population":0,
    "gn:timezone":"Africa/Bangui",
    "iso:country":"CF",
    "name:und_x_variant":[
        "Bo\u00e9s\u00e9",
        "Bo\u00e9ss\u00e9"
    ],
    "wof:name":"Boese",
    "wof:placetype":"locality"
},
  "geometry": {"coordinates":[17.58564,5.14209],"type":"Point"}
}