{
  "type": "Feature",
  "properties": {
    "gn:admin1_code":"18.0",
    "gn:admin2_code":"7731897.0",
    "gn:asciiname":"Potopoto",
    "gn:country_code":"CF",
    "gn:dem":395,
    "gn:feature_class":"P",
    "gn:feature_code":"PPL",
    "gn:name":"Potopoto",
    "gn:population":0,
    "gn:timezone":"Africa/Bangui",
    "iso:country":"CF",
    "wof:name":"Potopoto",
    "wof:placetype":"locality"
},
  "geometry": {"coordinates":[18.55,4.41667],"type":"Point"}
}