{
  "type": "Feature",
  "properties": {
    "gn:admin1_code":"1.0",
    "gn:admin2_code":"9143460.0",
    "gn:asciiname":"Boul-Kinia",
    "gn:country_code":"CF",
    "gn:dem":491,
    "gn:feature_class":"P",
    "gn:feature_code":"PPL",
    "gn:name":"Boul-Kinia",
    "gn:population":0,
    "gn:timezone":"Africa/Bangui",
    "iso:country":"CF",
    "name:und_x_variant":[
        "Bril\u2019Kinia",
        "Boul-Kinia"
    ],
    "wof:name":"Boul-Kinia",
    "wof:placetype":"locality"
},
  "geometry": {"coordinates":[20.58341,8.98207],"type":"Point"}
}