{
  "type": "Feature",
  "properties": {
    "gn:admin1_code":"12.0",
    "gn:admin2_code":"9143478.0",
    "gn:asciiname":"Lito",
    "gn:country_code":"CF",
    "gn:dem":418,
    "gn:feature_class":"P",
    "gn:feature_code":"PPL",
    "gn:name":"Lito",
    "gn:population":0,
    "gn:timezone":"Africa/Bangui",
    "iso:country":"CF",
    "name:ceb_x_preferred":[
        "Lito"
    ],
    "name:fra_x_preferred":[
        "Lito"
    ],
    "name:spa_x_preferred":[
        "Lito"
    ],
    "name:swe_x_preferred":[
        "Lito"
    ],
    "wof:name":"Lito",
    "wof:placetype":"locality"
},
  "geometry": {"coordinates":[18.63333,7.56667],"type":"Point"}
}