{
  "type": "Feature",
  "properties": {
    "gn:admin1_code":"12.0",
    "gn:admin2_code":"9143480.0",
    "gn:asciiname":"Karangara",
    "gn:country_code":"CF",
    "gn:dem":469,
    "gn:feature_class":"P",
    "gn:feature_code":"PPL",
    "gn:name":"Karangara",
    "gn:population":0,
    "gn:timezone":"Africa/Bangui",
    "iso:country":"CF",
    "name:und_x_variant":[
        "Carangara",
        "Karangara"
    ],
    "wof:name":"Karangara",
    "wof:placetype":"locality"
},
  "geometry": {"coordinates":[17.43062,7.03841],"type":"Point"}
}