{
  "type": "Feature",
  "properties": {
    "gn:admin1_code":"2.0",
    "gn:admin2_code":"9143474.0",
    "gn:asciiname":"Oroko",
    "gn:country_code":"CF",
    "gn:dem":545,
    "gn:feature_class":"P",
    "gn:feature_code":"PPL",
    "gn:name":"Oroko",
    "gn:population":0,
    "gn:timezone":"Africa/Bangui",
    "iso:country":"CF",
    "name:ceb_x_preferred":[
        "Oroko"
    ],
    "name:fra_x_preferred":[
        "Oroko"
    ],
    "name:swe_x_preferred":[
        "Oroko"
    ],
    "wof:name":"Oroko",
    "wof:placetype":"locality"
},
  "geometry": {"coordinates":[21.25,5.53333],"type":"Point"}
}