{
  "type": "Feature",
  "properties": {
    "gn:admin1_code":"11.0",
    "gn:asciiname":"Mouka",
    "gn:country_code":"CF",
    "gn:dem":638,
    "gn:feature_class":"P",
    "gn:feature_code":"PPL",
    "gn:name":"Mouka",
    "gn:population":0,
    "gn:timezone":"Africa/Bangui",
    "iso:country":"CF",
    "name:und_x_variant":[
        "Muka",
        "Mouka"
    ],
    "wof:name":"Mouka",
    "wof:placetype":"locality"
},
  "geometry": {"coordinates":[21.88856,7.28757],"type":"Point"}
}