{
  "type": "Feature",
  "properties": {
    "gn:admin1_code":"3.0",
    "gn:admin2_code":"9143465.0",
    "gn:asciiname":"Ayaba",
    "gn:country_code":"CF",
    "gn:dem":593,
    "gn:feature_class":"P",
    "gn:feature_code":"PPL",
    "gn:name":"Ayaba",
    "gn:population":0,
    "gn:timezone":"Africa/Bangui",
    "iso:country":"CF",
    "wof:name":"Ayaba",
    "wof:placetype":"locality"
},
  "geometry": {"coordinates":[22.01083,6.72094],"type":"Point"}
}