{
  "type": "Feature",
  "properties": {
    "gn:admin1_code":"17.0",
    "gn:admin2_code":"7731895.0",
    "gn:asciiname":"Boula",
    "gn:country_code":"CF",
    "gn:dem":438,
    "gn:feature_class":"P",
    "gn:feature_code":"PPL",
    "gn:name":"Boula",
    "gn:population":0,
    "gn:timezone":"Africa/Bangui",
    "iso:country":"CF",
    "wof:name":"Boula",
    "wof:placetype":"locality"
},
  "geometry": {"coordinates":[18.81667,4.76667],"type":"Point"}
}