{
  "type": "Feature",
  "properties": {
    "gn:admin1_code":"4.0",
    "gn:admin2_code":"7732917.0",
    "gn:asciiname":"Talim",
    "gn:country_code":"CF",
    "gn:dem":672,
    "gn:feature_class":"P",
    "gn:feature_code":"PPL",
    "gn:name":"Talim",
    "gn:population":0,
    "gn:timezone":"Africa/Bangui",
    "iso:country":"CF",
    "name:fra_x_preferred":[
        "Talim"
    ],
    "wof:name":"Talim",
    "wof:placetype":"locality"
},
  "geometry": {"coordinates":[16.75,4.88333],"type":"Point"}
}