{
  "type": "Feature",
  "properties": {
    "gn:admin1_code":"7.0",
    "gn:admin2_code":"7732068.0",
    "gn:asciiname":"Bouboua II",
    "gn:country_code":"CF",
    "gn:dem":598,
    "gn:feature_class":"P",
    "gn:feature_code":"PPL",
    "gn:name":"Bouboua II",
    "gn:population":0,
    "gn:timezone":"Africa/Bangui",
    "iso:country":"CF",
    "wof:name":"Bouboua II",
    "wof:placetype":"locality"
},
  "geometry": {"coordinates":[17.7264,4.13442],"type":"Point"}
}