{
  "type": "Feature",
  "properties": {
    "gn:admin1_code":"12",
    "gn:admin2_code":"9143478.0",
    "gn:asciiname":"Maitama",
    "gn:country_code":"CF",
    "gn:dem":410,
    "gn:feature_class":"P",
    "gn:feature_code":"PPL",
    "gn:name":"Ma\u00eftama",
    "gn:population":0,
    "gn:timezone":"Africa/Bangui",
    "iso:country":"CF",
    "name:und_x_variant":[
        "Ma\u00eftam",
        "Ma\u00eftama"
    ],
    "wof:name":"Maitama",
    "wof:placetype":"locality"
},
  "geometry": {"coordinates":[18.72294,8.17452],"type":"Point"}
}