{
  "type": "Feature",
  "properties": {
    "gn:admin1_code":"07",
    "gn:admin2_code":"9143467.0",
    "gn:asciiname":"Badane",
    "gn:country_code":"CF",
    "gn:dem":444,
    "gn:feature_class":"P",
    "gn:feature_code":"PPL",
    "gn:name":"Badane",
    "gn:population":0,
    "gn:timezone":"Africa/Bangui",
    "iso:country":"CF",
    "wof:name":"Badane",
    "wof:placetype":"locality"
},
  "geometry": {"coordinates":[17.03237,3.95705],"type":"Point"}
}