{
  "type": "Feature",
  "properties": {
    "gn:admin1_code":"4.0",
    "gn:admin2_code":"7732917.0",
    "gn:asciiname":"Chen-Boupane",
    "gn:cc2":"CF",
    "gn:country_code":"CF",
    "gn:dem":580,
    "gn:feature_class":"P",
    "gn:feature_code":"PPL",
    "gn:name":"Chen-Boupan\u00e9",
    "gn:population":0,
    "gn:timezone":"Africa/Bangui",
    "iso:country":"CF",
    "name:und_x_variant":[
        "Ghen-Boupane",
        "Chen-Boupan\u00e9"
    ],
    "wof:name":"Chen-Boupane",
    "wof:placetype":"locality"
},
  "geometry": {"coordinates":[16.61667000000001,4.78333],"type":"Point"}
}