{
  "type": "Feature",
  "properties": {
    "gn:admin1_code":"12.0",
    "gn:admin2_code":"9143479.0",
    "gn:asciiname":"Bekinga",
    "gn:country_code":"CF",
    "gn:dem":427,
    "gn:feature_class":"P",
    "gn:feature_code":"PPL",
    "gn:name":"B\u00e9kinga",
    "gn:population":0,
    "gn:timezone":"Africa/Bangui",
    "iso:country":"CF",
    "wof:name":"Bekinga",
    "wof:placetype":"locality"
},
  "geometry": {"coordinates":[17.09086,7.65372],"type":"Point"}
}