{
  "type": "Feature",
  "properties": {
    "gn:admin1_code":"9.0",
    "gn:admin2_code":"7732085.0",
    "gn:asciiname":"Dika",
    "gn:country_code":"CF",
    "gn:dem":714,
    "gn:feature_class":"P",
    "gn:feature_code":"PPL",
    "gn:name":"Dika",
    "gn:population":0,
    "gn:timezone":"Africa/Bangui",
    "iso:country":"CF",
    "name:und_x_variant":[
        "Dika-Boda",
        "Dika"
    ],
    "wof:name":"Dika",
    "wof:placetype":"locality"
},
  "geometry": {"coordinates":[15.19225,5.98534],"type":"Point"}
}