{
  "type": "Feature",
  "properties": {
    "gn:admin1_code":"16.0",
    "gn:admin2_code":"9143473.0",
    "gn:asciiname":"Kopou",
    "gn:country_code":"CF",
    "gn:dem":567,
    "gn:feature_class":"P",
    "gn:feature_code":"PPL",
    "gn:name":"Kopou",
    "gn:population":0,
    "gn:timezone":"Africa/Bangui",
    "iso:country":"CF",
    "wof:name":"Kopou",
    "wof:placetype":"locality"
},
  "geometry": {"coordinates":[16.75511,3.6914],"type":"Point"}
}