{
  "type": "Feature",
  "properties": {
    "gn:admin1_code":"11.0",
    "gn:admin2_code":"7732062.0",
    "gn:asciiname":"Sarabanda",
    "gn:country_code":"CF",
    "gn:dem":456,
    "gn:feature_class":"P",
    "gn:feature_code":"PPL",
    "gn:name":"Sarabanda",
    "gn:population":0,
    "gn:timezone":"Africa/Bangui",
    "iso:country":"CF",
    "name:ita_x_preferred":[
        "Sarabanda"
    ],
    "wof:name":"Sarabanda",
    "wof:placetype":"locality"
},
  "geometry": {"coordinates":[20.62551,5.75423],"type":"Point"}
}