{
  "type": "Feature",
  "properties": {
    "gn:admin1_code":"3.0",
    "gn:admin2_code":"9143465.0",
    "gn:asciiname":"Mboutou",
    "gn:country_code":"CF",
    "gn:dem":528,
    "gn:feature_class":"P",
    "gn:feature_code":"PPL",
    "gn:name":"Mboutou",
    "gn:population":0,
    "gn:timezone":"Africa/Bangui",
    "iso:country":"CF",
    "name:und_x_variant":[
        "Mboutou 2",
        "Mboutou"
    ],
    "wof:name":"Mboutou",
    "wof:placetype":"locality"
},
  "geometry": {"coordinates":[21.97216,5.55391],"type":"Point"}
}