{
  "type": "Feature",
  "properties": {
    "gn:admin1_code":"17.0",
    "gn:admin2_code":"9143490.0",
    "gn:asciiname":"Boutounou",
    "gn:country_code":"CF",
    "gn:dem":604,
    "gn:feature_class":"P",
    "gn:feature_code":"PPL",
    "gn:name":"Boutounou",
    "gn:population":0,
    "gn:timezone":"Africa/Bangui",
    "iso:country":"CF",
    "wof:name":"Boutounou",
    "wof:placetype":"locality"
},
  "geometry": {"coordinates":[18.30264,5.72802],"type":"Point"}
}