{
  "type": "Feature",
  "properties": {
    "gn:admin1_code":"3.0",
    "gn:admin2_code":"9143466.0",
    "gn:asciiname":"Birini",
    "gn:country_code":"CF",
    "gn:dem":743,
    "gn:feature_class":"P",
    "gn:feature_code":"PPL",
    "gn:name":"Birini",
    "gn:population":0,
    "gn:timezone":"Africa/Bangui",
    "iso:country":"CF",
    "name:und_x_variant":[
        "Ouakoutbi",
        "Brini",
        "Birini"
    ],
    "wof:name":"Birini",
    "wof:placetype":"locality"
},
  "geometry": {"coordinates":[22.39743,7.86233],"type":"Point"}
}