{
  "type": "Feature",
  "properties": {
    "gn:admin1_code":"1.0",
    "gn:admin2_code":"9143459.0",
    "gn:asciiname":"Vata",
    "gn:country_code":"CF",
    "gn:dem":437,
    "gn:feature_class":"P",
    "gn:feature_code":"PPL",
    "gn:name":"Vata",
    "gn:population":0,
    "gn:timezone":"Africa/Bangui",
    "iso:country":"CF",
    "name:bul_x_preferred":[
        "\u0412\u0430\u0442\u0430"
    ],
    "name:ceb_x_preferred":[
        "Vata"
    ],
    "name:ces_x_preferred":[
        "Vata"
    ],
    "name:deu_x_preferred":[
        "Vata"
    ],
    "name:fra_x_preferred":[
        "Vata"
    ],
    "name:hun_x_preferred":[
        "Vata"
    ],
    "name:ita_x_preferred":[
        "Vata"
    ],
    "name:jpn_x_preferred":[
        "\u30d9\u30f3\u30c4"
    ],
    "name:rus_x_preferred":[
        "\u0412\u0430\u0442\u0430"
    ],
    "name:slk_x_preferred":[
        "Vata"
    ],
    "name:spa_x_preferred":[
        "Vata"
    ],
    "name:swe_x_preferred":[
        "Vata"
    ],
    "wof:name":"Vata",
    "wof:placetype":"locality"
},
  "geometry": {"coordinates":[20.19766,7.70047],"type":"Point"}
}