{
  "type": "Feature",
  "properties": {
    "gn:admin1_code":"13.0",
    "gn:admin2_code":"9143493.0",
    "gn:asciiname":"Ngouboy",
    "gn:country_code":"CF",
    "gn:dem":635,
    "gn:feature_class":"P",
    "gn:feature_code":"PPL",
    "gn:name":"Ngouboy",
    "gn:population":0,
    "gn:timezone":"Africa/Bangui",
    "iso:country":"CF",
    "wof:name":"Ngouboy",
    "wof:placetype":"locality"
},
  "geometry": {"coordinates":[15.58333,7.45],"type":"Point"}
}