{
  "type": "Feature",
  "properties": {
    "gn:admin1_code":"16.0",
    "gn:admin2_code":"7731904.0",
    "gn:asciiname":"Bakobo",
    "gn:country_code":"CF",
    "gn:dem":583,
    "gn:feature_class":"P",
    "gn:feature_code":"PPL",
    "gn:name":"Bakobo",
    "gn:population":0,
    "gn:timezone":"Africa/Bangui",
    "iso:country":"CF",
    "wof:name":"Bakobo",
    "wof:placetype":"locality"
},
  "geometry": {"coordinates":[15.69501,3.40353],"type":"Point"}
}