{
  "type": "Feature",
  "properties": {
    "gn:admin1_code":"1.0",
    "gn:admin2_code":"9143460.0",
    "gn:asciiname":"Doum",
    "gn:country_code":"CF",
    "gn:dem":436,
    "gn:feature_class":"P",
    "gn:feature_code":"PPL",
    "gn:name":"Doum",
    "gn:population":0,
    "gn:timezone":"Africa/Bangui",
    "iso:country":"CF",
    "name:ceb_x_preferred":[
        "Doum"
    ],
    "name:fra_x_preferred":[
        "Doum"
    ],
    "name:swe_x_preferred":[
        "Doum"
    ],
    "wof:name":"Doum",
    "wof:placetype":"locality"
},
  "geometry": {"coordinates":[20.74401,9.01861],"type":"Point"}
}