{
  "type": "Feature",
  "properties": {
    "gn:admin1_code":"2.0",
    "gn:admin2_code":"7731892.0",
    "gn:asciiname":"Bokoro",
    "gn:country_code":"CF",
    "gn:dem":448,
    "gn:feature_class":"P",
    "gn:feature_code":"PPL",
    "gn:name":"Bokoro",
    "gn:population":0,
    "gn:timezone":"Africa/Bangui",
    "iso:country":"CF",
    "name:ceb_x_preferred":[
        "Bokoro"
    ],
    "name:fra_x_preferred":[
        "Bokoro"
    ],
    "name:ita_x_preferred":[
        "Bokoro"
    ],
    "name:pol_x_preferred":[
        "Bokoro"
    ],
    "name:ron_x_preferred":[
        "Bokoro"
    ],
    "name:rus_x_preferred":[
        "\u0411\u043e\u043a\u043e\u0440\u043e"
    ],
    "name:urd_x_preferred":[
        "\u0628\u0648\u06a9\u0648\u0631\u0648"
    ],
    "wof:name":"Bokoro",
    "wof:placetype":"locality"
},
  "geometry": {"coordinates":[20.59065,4.56671],"type":"Point"}
}