{
  "type": "Feature",
  "properties": {
    "gn:admin1_code":"2.0",
    "gn:admin2_code":"7731892.0",
    "gn:asciiname":"Bokoro",
    "gn:country_code":"CF",
    "gn:dem":448,
    "gn:feature_class":"P",
    "gn:feature_code":"PPL",
    "gn:name":"Bokoro",
    "gn:population":0,
    "gn:timezone":"Africa/Bangui",
    "iso:country":"CF",
    "wof:name":"Bokoro",
    "wof:placetype":"locality"
},
  "geometry": {"coordinates":[20.59065,4.56671],"type":"Point"}
}