{
  "type": "Feature",
  "properties": {
    "gn:admin1_code":"8.0",
    "gn:admin2_code":"7732690.0",
    "gn:asciiname":"Bagoso",
    "gn:country_code":"CF",
    "gn:dem":597,
    "gn:feature_class":"P",
    "gn:feature_code":"PPL",
    "gn:name":"Bagoso",
    "gn:population":0,
    "gn:timezone":"Africa/Bangui",
    "iso:country":"CF",
    "wof:name":"Bagoso",
    "wof:placetype":"locality"
},
  "geometry": {"coordinates":[22.75494,5.62032],"type":"Point"}
}