{
  "type": "Feature",
  "properties": {
    "gn:admin1_code":"2.0",
    "gn:admin2_code":"7731891.0",
    "gn:asciiname":"Ouye",
    "gn:country_code":"CF",
    "gn:dem":563,
    "gn:feature_class":"P",
    "gn:feature_code":"PPL",
    "gn:name":"Ouy\u00e9",
    "gn:population":0,
    "gn:timezone":"Africa/Bangui",
    "iso:country":"CF",
    "name:und_x_variant":[
        "Serengua",
        "Ouy\u00e9"
    ],
    "wof:name":"Ouye",
    "wof:placetype":"locality"
},
  "geometry": {"coordinates":[21.28588,4.55414],"type":"Point"}
}