{
  "type": "Feature",
  "properties": {
    "gn:admin1_code":"9.0",
    "gn:admin2_code":"2390511.0",
    "gn:asciiname":"Ndiba Bouassa",
    "gn:country_code":"CF",
    "gn:dem":1037,
    "gn:feature_class":"P",
    "gn:feature_code":"PPL",
    "gn:name":"Ndiba Bouassa",
    "gn:population":0,
    "gn:timezone":"Africa/Bangui",
    "iso:country":"CF",
    "name:und_x_variant":[
        "Diba-Bouessa",
        "Diba",
        "Ndiba Bouassa"
    ],
    "wof:name":"Ndiba Bouassa",
    "wof:placetype":"locality"
},
  "geometry": {"coordinates":[14.95418,5.82424],"type":"Point"}
}