{
  "type": "Feature",
  "properties": {
    "gn:admin1_code":"9.0",
    "gn:admin2_code":"7732085.0",
    "gn:asciiname":"Nagbenang",
    "gn:country_code":"CF",
    "gn:dem":609,
    "gn:feature_class":"P",
    "gn:feature_code":"PPL",
    "gn:name":"Nagbenang",
    "gn:population":0,
    "gn:timezone":"Africa/Bangui",
    "iso:country":"CF",
    "wof:name":"Nagbenang",
    "wof:placetype":"locality"
},
  "geometry": {"coordinates":[15.53333,5.55],"type":"Point"}
}