{
  "type": "Feature",
  "properties": {
    "gn:admin1_code":"1.0",
    "gn:admin2_code":"9143460.0",
    "gn:asciiname":"Bakolekpa",
    "gn:cc2":"CF",
    "gn:country_code":"CF",
    "gn:dem":638,
    "gn:feature_class":"P",
    "gn:feature_code":"PPL",
    "gn:name":"Bakolekpa",
    "gn:population":0,
    "gn:timezone":"Africa/Bangui",
    "iso:country":"CF",
    "name:und_x_variant":[
        "Bakolecpa",
        "Bakolekpa"
    ],
    "wof:name":"Bakolekpa",
    "wof:placetype":"locality"
},
  "geometry": {"coordinates":[20.93333,8.15],"type":"Point"}
}