{
  "type": "Feature",
  "properties": {
    "gn:admin1_code":"13.0",
    "gn:admin2_code":"9143494.0",
    "gn:asciiname":"Zara",
    "gn:country_code":"CF",
    "gn:dem":643,
    "gn:feature_class":"P",
    "gn:feature_code":"PPL",
    "gn:name":"Zara",
    "gn:population":0,
    "gn:timezone":"Africa/Bangui",
    "iso:country":"CF",
    "name:aze_x_preferred":[
        "Zara"
    ],
    "name:bel_x_preferred":[
        "\u0417\u0430\u0440\u0430"
    ],
    "name:bul_x_preferred":[
        "\u0417\u0430\u0440\u0430"
    ],
    "name:cat_x_preferred":[
        "Zara"
    ],
    "name:ceb_x_preferred":[
        "Zara"
    ],
    "name:ces_x_preferred":[
        "Zara"
    ],
    "name:deu_x_preferred":[
        "Zara"
    ],
    "name:ell_x_preferred":[
        "\u0396\u03ac\u03c1\u03b1"
    ],
    "name:est_x_preferred":[
        "Zara"
    ],
    "name:fin_x_preferred":[
        "Zara"
    ],
    "name:fra_x_preferred":[
        "Zara"
    ],
    "name:glg_x_preferred":[
        "Zara"
    ],
    "name:hun_x_preferred":[
        "Zara"
    ],
    "name:ind_x_preferred":[
        "Zara"
    ],
    "name:ita_x_preferred":[
        "Zara"
    ],
    "name:kor_x_preferred":[
        "\uc790\ub77c"
    ],
    "name:kur_x_preferred":[
        "Zara"
    ],
    "name:nld_x_preferred":[
        "Zara"
    ],
    "name:nno_x_preferred":[
        "Zara"
    ],
    "name:pol_x_preferred":[
        "Zara"
    ],
    "name:ron_x_preferred":[
        "Zara"
    ],
    "name:rus_x_preferred":[
        "\u0417\u0430\u0440\u0430"
    ],
    "name:spa_x_preferred":[
        "Zara"
    ],
    "name:srp_x_preferred":[
        "\u0417\u0430\u0440\u0430"
    ],
    "name:swe_x_preferred":[
        "Zara"
    ],
    "name:tur_x_preferred":[
        "Zara"
    ],
    "name:ukr_x_preferred":[
        "\u0417\u0430\u0440\u0430"
    ],
    "name:vie_x_preferred":[
        "Zara"
    ],
    "wof:name":"Zara",
    "wof:placetype":"locality"
},
  "geometry": {"coordinates":[16.32797,7.12275],"type":"Point"}
}