{
  "type": "Feature",
  "properties": {
    "gn:admin1_code":"12",
    "gn:admin2_code":"9143477.0",
    "gn:asciiname":"Ngoungou II",
    "gn:country_code":"CF",
    "gn:dem":538,
    "gn:feature_class":"P",
    "gn:feature_code":"PPL",
    "gn:name":"Ngoungou II",
    "gn:population":0,
    "gn:timezone":"Africa/Bangui",
    "iso:country":"CF",
    "wof:name":"Ngoungou II",
    "wof:placetype":"locality"
},
  "geometry": {"coordinates":[18.35456,5.88274],"type":"Point"}
}