{
  "type": "Feature",
  "properties": {
    "gn:admin1_code":"2.0",
    "gn:admin2_code":"7731890.0",
    "gn:asciiname":"Aoundaye",
    "gn:country_code":"CF",
    "gn:dem":407,
    "gn:feature_class":"P",
    "gn:feature_code":"PPL",
    "gn:name":"Aounday\u00e9",
    "gn:population":0,
    "gn:timezone":"Africa/Bangui",
    "iso:country":"CF",
    "wof:name":"Aoundaye",
    "wof:placetype":"locality"
},
  "geometry": {"coordinates":[21.86667000000001,4.31667],"type":"Point"}
}