{
  "type": "Feature",
  "properties": {
    "gn:admin1_code":"8.0",
    "gn:admin2_code":"9143468.0",
    "gn:asciiname":"Koulondji",
    "gn:country_code":"CF",
    "gn:dem":568,
    "gn:feature_class":"P",
    "gn:feature_code":"PPL",
    "gn:name":"Koulondji",
    "gn:population":0,
    "gn:timezone":"Africa/Bangui",
    "iso:country":"CF",
    "wof:name":"Koulondji",
    "wof:placetype":"locality"
},
  "geometry": {"coordinates":[23.78452,4.98149],"type":"Point"}
}