{
  "type": "Feature",
  "properties": {
    "gn:admin1_code":"7.0",
    "gn:admin2_code":"9143487.0",
    "gn:asciiname":"Bougoin",
    "gn:country_code":"CF",
    "gn:dem":620,
    "gn:feature_class":"P",
    "gn:feature_code":"PPL",
    "gn:name":"Bougoin",
    "gn:population":0,
    "gn:timezone":"Africa/Bangui",
    "iso:country":"CF",
    "wof:name":"Bougoin",
    "wof:placetype":"locality"
},
  "geometry": {"coordinates":[17.36667000000001,4.48333],"type":"Point"}
}