{
  "type": "Feature",
  "properties": {
    "gn:admin1_code":"5.0",
    "gn:admin2_code":"9143464.0",
    "gn:asciiname":"Kounboli",
    "gn:country_code":"CF",
    "gn:dem":637,
    "gn:feature_class":"P",
    "gn:feature_code":"PPL",
    "gn:name":"Kounboli",
    "gn:population":0,
    "gn:timezone":"Africa/Bangui",
    "iso:country":"CF",
    "wof:name":"Kounboli",
    "wof:placetype":"locality"
},
  "geometry": {"coordinates":[25.15365,5.06112],"type":"Point"}
}