{
  "type": "Feature",
  "properties": {
    "gn:admin1_code":"12.0",
    "gn:admin2_code":"9143472.0",
    "gn:asciiname":"Maimoudou",
    "gn:country_code":"CF",
    "gn:dem":392,
    "gn:feature_class":"P",
    "gn:feature_code":"PPL",
    "gn:name":"Ma\u00efmoudou",
    "gn:population":0,
    "gn:timezone":"Africa/Bangui",
    "iso:country":"CF",
    "wof:name":"Maimoudou",
    "wof:placetype":"locality"
},
  "geometry": {"coordinates":[17.77012999999999,7.80571],"type":"Point"}
}