{
  "type": "Feature",
  "properties": {
    "gn:admin1_code":"13.0",
    "gn:admin2_code":"9143491.0",
    "gn:asciiname":"Diaoke",
    "gn:country_code":"CF",
    "gn:dem":1024,
    "gn:feature_class":"P",
    "gn:feature_code":"PPL",
    "gn:name":"Diaok\u00e9",
    "gn:population":0,
    "gn:timezone":"Africa/Bangui",
    "iso:country":"CF",
    "wof:name":"Diaoke",
    "wof:placetype":"locality"
},
  "geometry": {"coordinates":[15.65,6.96667],"type":"Point"}
}