{
  "type": "Feature",
  "properties": {
    "gn:admin1_code":"4.0",
    "gn:admin2_code":"7732916.0",
    "gn:asciiname":"Mbiale",
    "gn:country_code":"CF",
    "gn:dem":648,
    "gn:feature_class":"P",
    "gn:feature_code":"PPL",
    "gn:name":"Mbial\u00e9",
    "gn:population":0,
    "gn:timezone":"Africa/Bangui",
    "iso:country":"CF",
    "wof:name":"Mbiale",
    "wof:placetype":"locality"
},
  "geometry": {"coordinates":[14.83352,4.53677],"type":"Point"}
}