{
  "type": "Feature",
  "properties": {
    "gn:admin1_code":"11.0",
    "gn:admin2_code":"9143471.0",
    "gn:asciiname":"Djoho",
    "gn:cc2":"CF",
    "gn:country_code":"CF",
    "gn:dem":524,
    "gn:feature_class":"P",
    "gn:feature_code":"PPL",
    "gn:name":"Djoho",
    "gn:population":0,
    "gn:timezone":"Africa/Bangui",
    "iso:country":"CF",
    "name:und_x_variant":[
        "Djoko",
        "Djoho"
    ],
    "wof:name":"Djoho",
    "wof:placetype":"locality"
},
  "geometry": {"coordinates":[20.66667,6.61667],"type":"Point"}
}