{
  "type": "Feature",
  "properties": {
    "gn:admin1_code":"11.0",
    "gn:admin2_code":"7732067.0",
    "gn:asciiname":"Atongoeye",
    "gn:country_code":"CF",
    "gn:dem":599,
    "gn:feature_class":"P",
    "gn:feature_code":"PPL",
    "gn:name":"Atongoey\u00e9",
    "gn:population":0,
    "gn:timezone":"Africa/Bangui",
    "iso:country":"CF",
    "wof:name":"Atongoeye",
    "wof:placetype":"locality"
},
  "geometry": {"coordinates":[21.18531,6.22308],"type":"Point"}
}