{
  "type": "Feature",
  "properties": {
    "gn:admin1_code":"13.0",
    "gn:admin2_code":"9143494.0",
    "gn:asciiname":"Benamkor Mali",
    "gn:country_code":"CF",
    "gn:dem":478,
    "gn:feature_class":"P",
    "gn:feature_code":"PPL",
    "gn:name":"B\u00e9namkor Mali",
    "gn:population":0,
    "gn:timezone":"Africa/Bangui",
    "iso:country":"CF",
    "name:und_x_variant":[
        "Benamkor",
        "B\u00e9namkor Mali"
    ],
    "wof:name":"Benamkor Mali",
    "wof:placetype":"locality"
},
  "geometry": {"coordinates":[16.272,7.4373],"type":"Point"}
}