{
  "type": "Feature",
  "properties": {
    "gn:admin1_code":"8.0",
    "gn:admin2_code":"7731888.0",
    "gn:asciiname":"Kemba",
    "gn:country_code":"CF",
    "gn:dem":406,
    "gn:feature_class":"P",
    "gn:feature_code":"PPL",
    "gn:name":"Kemba",
    "gn:population":0,
    "gn:timezone":"Africa/Bangui",
    "iso:country":"CF",
    "wof:name":"Kemba",
    "wof:placetype":"locality"
},
  "geometry": {"coordinates":[22.43568,4.1372],"type":"Point"}
}