{
  "type": "Feature",
  "properties": {
    "gn:admin1_code":"17.0",
    "gn:admin2_code":"7731895.0",
    "gn:asciiname":"Ingouade",
    "gn:country_code":"CF",
    "gn:dem":378,
    "gn:feature_class":"P",
    "gn:feature_code":"PPL",
    "gn:name":"Ingouad\u00e9",
    "gn:population":0,
    "gn:timezone":"Africa/Bangui",
    "iso:country":"CF",
    "wof:name":"Ingouade",
    "wof:placetype":"locality"
},
  "geometry": {"coordinates":[18.94844,4.89984],"type":"Point"}
}