{
  "type": "Feature",
  "properties": {
    "gn:admin1_code":"2.0",
    "gn:admin2_code":"7731891.0",
    "gn:asciiname":"Doussi",
    "gn:country_code":"CF",
    "gn:dem":397,
    "gn:feature_class":"P",
    "gn:feature_code":"PPL",
    "gn:name":"Doussi",
    "gn:population":0,
    "gn:timezone":"Africa/Bangui",
    "iso:country":"CF",
    "name:azb_x_preferred":[
        "\u062f\u0648\u0633\u06cc"
    ],
    "name:ceb_x_preferred":[
        "Doussi"
    ],
    "name:fas_x_preferred":[
        "\u062f\u0648\u0633\u06cc"
    ],
    "name:fra_x_preferred":[
        "Doussi"
    ],
    "name:swe_x_preferred":[
        "Doussi"
    ],
    "wof:name":"Doussi",
    "wof:placetype":"locality"
},
  "geometry": {"coordinates":[21.12539,4.39338],"type":"Point"}
}