{
  "type": "Feature",
  "properties": {
    "gn:admin1_code":"9.0",
    "gn:admin2_code":"7732085.0",
    "gn:asciiname":"Foro",
    "gn:country_code":"CF",
    "gn:dem":718,
    "gn:feature_class":"P",
    "gn:feature_code":"PPL",
    "gn:name":"Foro",
    "gn:population":0,
    "gn:timezone":"Africa/Bangui",
    "iso:country":"CF",
    "name:ast_x_preferred":[
        "Foru"
    ],
    "name:jpn_x_preferred":[
        "\u30d5\u30a9\u30ed"
    ],
    "name:por_x_preferred":[
        "Foro"
    ],
    "name:rus_x_preferred":[
        "\u0424\u043e\u0440\u043e"
    ],
    "name:spa_x_preferred":[
        "Foro"
    ],
    "wof:name":"Foro",
    "wof:placetype":"locality"
},
  "geometry": {"coordinates":[15.4961,5.86234],"type":"Point"}
}