{
  "type": "Feature",
  "properties": {
    "gn:admin1_code":"13.0",
    "gn:admin2_code":"9143493.0",
    "gn:asciiname":"Bang",
    "gn:country_code":"CF",
    "gn:dem":617,
    "gn:feature_class":"P",
    "gn:feature_code":"PPL",
    "gn:name":"Bang",
    "gn:population":0,
    "gn:timezone":"Africa/Bangui",
    "iso:country":"CF",
    "name:und_x_variant":[
        "Bang I",
        "Bang"
    ],
    "wof:name":"Bang",
    "wof:placetype":"locality"
},
  "geometry": {"coordinates":[15.53994,7.47752],"type":"Point"}
}