{
  "type": "Feature",
  "properties": {
    "gn:admin1_code":"13.0",
    "gn:admin2_code":"9143493.0",
    "gn:asciiname":"Bang",
    "gn:country_code":"CF",
    "gn:dem":617,
    "gn:feature_class":"P",
    "gn:feature_code":"PPL",
    "gn:name":"Bang",
    "gn:population":0,
    "gn:timezone":"Africa/Bangui",
    "iso:country":"CF",
    "name:ces_x_preferred":[
        "Bang"
    ],
    "name:deu_x_preferred":[
        "Bang"
    ],
    "name:est_x_preferred":[
        "Bang"
    ],
    "name:fra_x_preferred":[
        "Bang"
    ],
    "name:ita_x_preferred":[
        "Bang"
    ],
    "name:nld_x_preferred":[
        "Bang"
    ],
    "name:por_x_preferred":[
        "Bang"
    ],
    "name:rus_x_preferred":[
        "\u0411\u044d\u043d\u0433"
    ],
    "name:slv_x_preferred":[
        "Bang"
    ],
    "name:spa_x_preferred":[
        "Bang"
    ],
    "name:swe_x_preferred":[
        "Bang"
    ],
    "name:ukr_x_preferred":[
        "\u0411\u0430\u043d\u0433"
    ],
    "name:und_x_variant":[
        "Bang I"
    ],
    "wof:name":"Bang",
    "wof:placetype":"locality"
},
  "geometry": {"coordinates":[15.53994,7.47752],"type":"Point"}
}