{
  "type": "Feature",
  "properties": {
    "gn:admin1_code":"12.0",
    "gn:admin2_code":"9143478.0",
    "gn:asciiname":"Moyenne-Sido",
    "gn:country_code":"CF",
    "gn:dem":390,
    "gn:feature_class":"P",
    "gn:feature_code":"PPL",
    "gn:name":"Moyenne-Sido",
    "gn:population":0,
    "gn:timezone":"Africa/Bangui",
    "iso:country":"CF",
    "name:und_x_variant":[
        "Sido",
        "Moyenne-Sido"
    ],
    "wof:name":"Moyenne-Sido",
    "wof:placetype":"locality"
},
  "geometry": {"coordinates":[18.71545,8.22525],"type":"Point"}
}