{
  "type": "Feature",
  "properties": {
    "gn:admin1_code":"13.0",
    "gn:admin2_code":"9143493.0",
    "gn:asciiname":"Boudjara",
    "gn:country_code":"CF",
    "gn:dem":972,
    "gn:feature_class":"P",
    "gn:feature_code":"PPL",
    "gn:name":"Boudjara",
    "gn:population":0,
    "gn:timezone":"Africa/Bangui",
    "iso:country":"CF",
    "name:und_x_variant":[
        "Boundjara",
        "Boudjara"
    ],
    "wof:name":"Boudjara",
    "wof:placetype":"locality"
},
  "geometry": {"coordinates":[15.732,7.16431],"type":"Point"}
}