{
  "type": "Feature",
  "properties": {
    "gn:admin1_code":"8.0",
    "gn:admin2_code":"7732064.0",
    "gn:asciiname":"Bombo",
    "gn:country_code":"CF",
    "gn:dem":556,
    "gn:feature_class":"P",
    "gn:feature_code":"PPL",
    "gn:name":"Bombo",
    "gn:population":0,
    "gn:timezone":"Africa/Bangui",
    "iso:country":"CF",
    "name:ceb_x_preferred":[
        "Bombo"
    ],
    "name:fra_x_preferred":[
        "Bombo"
    ],
    "name:ita_x_preferred":[
        "Bombo"
    ],
    "name:lug_x_preferred":[
        "Bombo"
    ],
    "name:nld_x_preferred":[
        "Bombo"
    ],
    "name:pol_x_preferred":[
        "Bombo"
    ],
    "name:spa_x_preferred":[
        "Bombo"
    ],
    "name:swe_x_preferred":[
        "Bombo"
    ],
    "name:und_x_variant":[
        "Bambo",
        "Bombo"
    ],
    "wof:name":"Bombo",
    "wof:placetype":"locality"
},
  "geometry": {"coordinates":[23.51614,4.89408],"type":"Point"}
}