{
  "type": "Feature",
  "properties": {
    "gn:admin1_code":"16.0",
    "gn:admin2_code":"9143473.0",
    "gn:asciiname":"Mambelle",
    "gn:country_code":"CF",
    "gn:dem":632,
    "gn:feature_class":"P",
    "gn:feature_code":"PPL",
    "gn:name":"Mamb\u00e9ll\u00e9",
    "gn:population":0,
    "gn:timezone":"Africa/Bangui",
    "iso:country":"CF",
    "wof:name":"Mambelle",
    "wof:placetype":"locality"
},
  "geometry": {"coordinates":[16.64964,3.93038],"type":"Point"}
}