{
  "type": "Feature",
  "properties": {
    "gn:admin1_code":"2.0",
    "gn:admin2_code":"7731892.0",
    "gn:asciiname":"Ngoyi",
    "gn:country_code":"CF",
    "gn:dem":402,
    "gn:feature_class":"P",
    "gn:feature_code":"PPL",
    "gn:name":"Ngoyi",
    "gn:population":0,
    "gn:timezone":"Africa/Bangui",
    "iso:country":"CF",
    "wof:name":"Ngoyi",
    "wof:placetype":"locality"
},
  "geometry": {"coordinates":[20.83415,4.54099],"type":"Point"}
}