{
  "type": "Feature",
  "properties": {
    "gn:admin1_code":"17.0",
    "gn:admin2_code":"8299285.0",
    "gn:asciiname":"Bodoupa",
    "gn:country_code":"CF",
    "gn:dem":618,
    "gn:feature_class":"P",
    "gn:feature_code":"PPL",
    "gn:name":"Bodoupa",
    "gn:population":0,
    "gn:timezone":"Africa/Bangui",
    "iso:country":"CF",
    "wof:name":"Bodoupa",
    "wof:placetype":"locality"
},
  "geometry": {"coordinates":[17.91185,4.99507],"type":"Point"}
}