{
  "type": "Feature",
  "properties": {
    "gn:admin1_code":"17.0",
    "gn:admin2_code":"7731896.0",
    "gn:asciiname":"Bogbade",
    "gn:country_code":"CF",
    "gn:dem":374,
    "gn:feature_class":"P",
    "gn:feature_code":"PPL",
    "gn:name":"Bogbad\u00e9",
    "gn:population":0,
    "gn:timezone":"Africa/Bangui",
    "iso:country":"CF",
    "wof:name":"Bogbade",
    "wof:placetype":"locality"
},
  "geometry": {"coordinates":[18.25393,4.44922],"type":"Point"}
}