{
  "type": "Feature",
  "properties": {
    "gn:admin1_code":"17.0",
    "gn:admin2_code":"7732372.0",
    "gn:asciiname":"Bekamoule",
    "gn:country_code":"CF",
    "gn:dem":731,
    "gn:feature_class":"P",
    "gn:feature_code":"PPL",
    "gn:name":"B\u00e9kamoul\u00e9",
    "gn:population":0,
    "gn:timezone":"Africa/Bangui",
    "iso:country":"CF",
    "wof:name":"Bekamoule",
    "wof:placetype":"locality"
},
  "geometry": {"coordinates":[16.7642,5.52112],"type":"Point"}
}