{
  "type": "Feature",
  "properties": {
    "gn:admin1_code":"4.0",
    "gn:admin2_code":"7732917.0",
    "gn:asciiname":"Sazele",
    "gn:country_code":"CF",
    "gn:dem":608,
    "gn:feature_class":"P",
    "gn:feature_code":"PPL",
    "gn:name":"Saz\u00e9l\u00e9",
    "gn:population":0,
    "gn:timezone":"Africa/Bangui",
    "iso:country":"CF",
    "wof:name":"Sazele",
    "wof:placetype":"locality"
},
  "geometry": {"coordinates":[16.83718,4.52001],"type":"Point"}
}