{
  "type": "Feature",
  "properties": {
    "gn:admin1_code":"17.0",
    "gn:admin2_code":"7732372.0",
    "gn:asciiname":"Bodanga Koukoukele",
    "gn:country_code":"CF",
    "gn:dem":744,
    "gn:feature_class":"P",
    "gn:feature_code":"PPL",
    "gn:name":"Bodanga Koukouk\u00e9l\u00e9",
    "gn:population":0,
    "gn:timezone":"Africa/Bangui",
    "iso:country":"CF",
    "name:und_x_variant":[
        "Bodanga Koukouk\u00e9l\u00e9",
        "Koulouk\u00e9l\u00e9 Bodanga"
    ],
    "wof:name":"Bodanga Koukoukele",
    "wof:placetype":"locality"
},
  "geometry": {"coordinates":[17.10266,5.2332],"type":"Point"}
}