{
  "type": "Feature",
  "properties": {
    "gn:admin1_code":"12.0",
    "gn:admin2_code":"9143472.0",
    "gn:asciiname":"Gouin",
    "gn:country_code":"CF",
    "gn:dem":444,
    "gn:feature_class":"P",
    "gn:feature_code":"PPL",
    "gn:name":"Gouin",
    "gn:population":0,
    "gn:timezone":"Africa/Bangui",
    "iso:country":"CF",
    "name:ceb_x_preferred":[
        "Gouin"
    ],
    "name:deu_x_preferred":[
        "Gouin"
    ],
    "name:fra_x_preferred":[
        "Gouin"
    ],
    "name:rus_x_preferred":[
        "\u0413\u0443\u044d\u043d"
    ],
    "name:swe_x_preferred":[
        "Gouin"
    ],
    "wof:name":"Gouin",
    "wof:placetype":"locality"
},
  "geometry": {"coordinates":[17.43309,7.16706],"type":"Point"}
}