{
  "type": "Feature",
  "properties": {
    "gn:admin1_code":"11",
    "gn:admin2_code":"7732377.0",
    "gn:asciiname":"Makobo",
    "gn:country_code":"CF",
    "gn:dem":432,
    "gn:feature_class":"P",
    "gn:feature_code":"PPL",
    "gn:name":"Makobo",
    "gn:population":0,
    "gn:timezone":"Africa/Bangui",
    "iso:country":"CF",
    "wof:name":"Makobo",
    "wof:placetype":"locality"
},
  "geometry": {"coordinates":[19.97135,5.713],"type":"Point"}
}