{
  "type": "Feature",
  "properties": {
    "gn:admin1_code":"13.0",
    "gn:admin2_code":"9143494.0",
    "gn:asciiname":"Bedaia",
    "gn:country_code":"CF",
    "gn:dem":491,
    "gn:feature_class":"P",
    "gn:feature_code":"PPL",
    "gn:name":"B\u00e9da\u00efa",
    "gn:population":0,
    "gn:timezone":"Africa/Bangui",
    "iso:country":"CF",
    "name:und_x_variant":[
        "B\u00e9da\u00efa II",
        "B\u00e9da\u00efa"
    ],
    "wof:name":"Bedaia",
    "wof:placetype":"locality"
},
  "geometry": {"coordinates":[16.50176,7.46489],"type":"Point"}
}