{
  "type": "Feature",
  "properties": {
    "gn:admin1_code":"11.0",
    "gn:admin2_code":"9143471.0",
    "gn:asciiname":"Dakadjia",
    "gn:country_code":"CF",
    "gn:dem":509,
    "gn:feature_class":"P",
    "gn:feature_code":"PPL",
    "gn:name":"Dakadjia",
    "gn:population":0,
    "gn:timezone":"Africa/Bangui",
    "iso:country":"CF",
    "wof:name":"Dakadjia",
    "wof:placetype":"locality"
},
  "geometry": {"coordinates":[20.52112,6.20086],"type":"Point"}
}