{
  "type": "Feature",
  "properties": {
    "gn:admin1_code":"13.0",
    "gn:admin2_code":"8299286.0",
    "gn:asciiname":"Bolom",
    "gn:country_code":"CF",
    "gn:dem":970,
    "gn:feature_class":"P",
    "gn:feature_code":"PPL",
    "gn:name":"Bolom",
    "gn:population":0,
    "gn:timezone":"Africa/Bangui",
    "iso:country":"CF",
    "wof:name":"Bolom",
    "wof:placetype":"locality"
},
  "geometry": {"coordinates":[16.06683,6.46391],"type":"Point"}
}