{
  "type": "Feature",
  "properties": {
    "gn:admin1_code":"8.0",
    "gn:admin2_code":"7732690.0",
    "gn:asciiname":"Ouara",
    "gn:country_code":"CF",
    "gn:dem":523,
    "gn:feature_class":"P",
    "gn:feature_code":"PPL",
    "gn:name":"Ouara",
    "gn:population":0,
    "gn:timezone":"Africa/Bangui",
    "iso:country":"CF",
    "name:deu_x_preferred":[
        "Ouara"
    ],
    "name:eus_x_preferred":[
        "Ouara"
    ],
    "name:nld_x_preferred":[
        "Ouara"
    ],
    "name:pol_x_preferred":[
        "Ouara"
    ],
    "name:ron_x_preferred":[
        "Ouara"
    ],
    "name:rus_x_preferred":[
        "\u0423\u0430\u0440\u0430"
    ],
    "name:swe_x_preferred":[
        "Ouara"
    ],
    "name:urd_x_preferred":[
        "\u0627\u0648\u0627\u0631\u0627"
    ],
    "wof:name":"Ouara",
    "wof:placetype":"locality"
},
  "geometry": {"coordinates":[23.31667,5.53333],"type":"Point"}
}