{
  "type": "Feature",
  "properties": {
    "gn:admin1_code":"16.0",
    "gn:admin2_code":"7731904.0",
    "gn:asciiname":"Domisili",
    "gn:country_code":"CF",
    "gn:dem":630,
    "gn:feature_class":"P",
    "gn:feature_code":"PPL",
    "gn:name":"Domisili",
    "gn:population":0,
    "gn:timezone":"Africa/Bangui",
    "iso:country":"CF",
    "wof:name":"Domisili",
    "wof:placetype":"locality"
},
  "geometry": {"coordinates":[15.71132,3.39323],"type":"Point"}
}