{
  "type": "Feature",
  "properties": {
    "gn:admin1_code":"13.0",
    "gn:admin2_code":"9143494.0",
    "gn:asciiname":"Poumbe",
    "gn:country_code":"CF",
    "gn:dem":611,
    "gn:feature_class":"P",
    "gn:feature_code":"PPL",
    "gn:name":"Poumb\u00e9",
    "gn:population":0,
    "gn:timezone":"Africa/Bangui",
    "iso:country":"CF",
    "wof:name":"Poumbe",
    "wof:placetype":"locality"
},
  "geometry": {"coordinates":[16.38915,7.1087],"type":"Point"}
}