{
  "type": "Feature",
  "properties": {
    "gn:admin1_code":"16.0",
    "gn:admin2_code":"9143473.0",
    "gn:asciiname":"Bolondo",
    "gn:country_code":"CF",
    "gn:dem":550,
    "gn:feature_class":"P",
    "gn:feature_code":"PPL",
    "gn:name":"Bolondo",
    "gn:population":0,
    "gn:timezone":"Africa/Bangui",
    "iso:country":"CF",
    "name:cat_x_preferred":[
        "Bolondo"
    ],
    "name:ita_x_preferred":[
        "Bolondo"
    ],
    "name:nld_x_preferred":[
        "Bolondo"
    ],
    "name:spa_x_preferred":[
        "Bolondo"
    ],
    "wof:name":"Bolondo",
    "wof:placetype":"locality"
},
  "geometry": {"coordinates":[16.76176,3.97694],"type":"Point"}
}