{
  "type": "Feature",
  "properties": {
    "gn:admin1_code":"15.0",
    "gn:admin2_code":"9143470.0",
    "gn:asciiname":"Bozou",
    "gn:country_code":"CF",
    "gn:dem":585,
    "gn:feature_class":"P",
    "gn:feature_code":"PPL",
    "gn:name":"Bozou",
    "gn:population":0,
    "gn:timezone":"Africa/Bangui",
    "iso:country":"CF",
    "wof:name":"Bozou",
    "wof:placetype":"locality"
},
  "geometry": {"coordinates":[19.86765,6.8246],"type":"Point"}
}