{
  "type": "Feature",
  "properties": {
    "gn:admin1_code":"4.0",
    "gn:admin2_code":"7732685.0",
    "gn:asciiname":"Bayanga",
    "gn:country_code":"CF",
    "gn:dem":473,
    "gn:feature_class":"P",
    "gn:feature_code":"PPL",
    "gn:name":"Bayanga",
    "gn:population":0,
    "gn:timezone":"Africa/Bangui",
    "iso:country":"CF",
    "name:fra_x_preferred":[
        "Bayanga"
    ],
    "name:und_x_variant":[
        "Rayanga",
        "Bayanga"
    ],
    "wof:name":"Bayanga",
    "wof:placetype":"locality"
},
  "geometry": {"coordinates":[16.19179,4.386],"type":"Point"}
}