{
  "type": "Feature",
  "properties": {
    "gn:admin1_code":"01",
    "gn:admin2_code":"9143460.0",
    "gn:asciiname":"Manyibo",
    "gn:country_code":"CF",
    "gn:dem":405,
    "gn:feature_class":"P",
    "gn:feature_code":"PPL",
    "gn:name":"Manyibo",
    "gn:population":0,
    "gn:timezone":"Africa/Bangui",
    "iso:country":"CF",
    "name:fra_x_preferred":[
        "Manyibo"
    ],
    "wof:name":"Manyibo",
    "wof:placetype":"locality"
},
  "geometry": {"coordinates":[20.51128,9.18856],"type":"Point"}
}