{
  "type": "Feature",
  "properties": {
    "gn:admin1_code":"9.0",
    "gn:admin2_code":"2390511.0",
    "gn:asciiname":"Lokoti Yelewene",
    "gn:country_code":"CF",
    "gn:dem":1033,
    "gn:feature_class":"P",
    "gn:feature_code":"PPL",
    "gn:name":"Lokoti Y\u00e9l\u00e9w\u00e9n\u00e9",
    "gn:population":0,
    "gn:timezone":"Africa/Bangui",
    "iso:country":"CF",
    "wof:name":"Lokoti Yelewene",
    "wof:placetype":"locality"
},
  "geometry": {"coordinates":[14.93046,5.81286],"type":"Point"}
}