{
  "type": "Feature",
  "properties": {
    "gn:admin1_code":"7.0",
    "gn:admin2_code":"9143486.0",
    "gn:asciiname":"Bogoto",
    "gn:country_code":"CF",
    "gn:dem":697,
    "gn:feature_class":"P",
    "gn:feature_code":"PPL",
    "gn:name":"Bogoto",
    "gn:population":0,
    "gn:timezone":"Africa/Bangui",
    "iso:country":"CF",
    "wof:name":"Bogoto",
    "wof:placetype":"locality"
},
  "geometry": {"coordinates":[17.1764,4.8509],"type":"Point"}
}