{
  "type": "Feature",
  "properties": {
    "gn:admin1_code":"9.0",
    "gn:admin2_code":"2390511.0",
    "gn:asciiname":"Yagbe",
    "gn:country_code":"CF",
    "gn:dem":994,
    "gn:feature_class":"P",
    "gn:feature_code":"PPL",
    "gn:name":"Yagb\u00e9",
    "gn:population":0,
    "gn:timezone":"Africa/Bangui",
    "iso:country":"CF",
    "wof:name":"Yagbe",
    "wof:placetype":"locality"
},
  "geometry": {"coordinates":[14.90375,5.81536],"type":"Point"}
}