{
  "type": "Feature",
  "properties": {
    "gn:admin1_code":"8.0",
    "gn:admin2_code":"7731888.0",
    "gn:asciiname":"Gaigne",
    "gn:country_code":"CF",
    "gn:dem":557,
    "gn:feature_class":"P",
    "gn:feature_code":"PPL",
    "gn:name":"Gaign\u00e9",
    "gn:population":0,
    "gn:timezone":"Africa/Bangui",
    "iso:country":"CF",
    "wof:name":"Gaigne",
    "wof:placetype":"locality"
},
  "geometry": {"coordinates":[22.55,4.38333],"type":"Point"}
}