{
  "type": "Feature",
  "properties": {
    "gn:admin1_code":"14",
    "gn:admin2_code":"9143458.0",
    "gn:asciiname":"Amdafok",
    "gn:country_code":"CF",
    "gn:dem":486,
    "gn:feature_class":"P",
    "gn:feature_code":"PPL",
    "gn:name":"Amdafok",
    "gn:population":0,
    "gn:timezone":"Africa/Bangui",
    "iso:country":"CF",
    "wof:name":"Amdafok",
    "wof:placetype":"locality"
},
  "geometry": {"coordinates":[23.289,10.463],"type":"Point"}
}