{
  "type": "Feature",
  "properties": {
    "gn:admin1_code":"4.0",
    "gn:admin2_code":"2387494.0",
    "gn:asciiname":"Madoukou",
    "gn:country_code":"CF",
    "gn:dem":659,
    "gn:feature_class":"P",
    "gn:feature_code":"PPL",
    "gn:name":"Madoukou",
    "gn:population":0,
    "gn:timezone":"Africa/Bangui",
    "iso:country":"CF",
    "wof:name":"Madoukou",
    "wof:placetype":"locality"
},
  "geometry": {"coordinates":[16.5269,4.44344],"type":"Point"}
}