{
  "type": "Feature",
  "properties": {
    "gn:admin1_code":"2.0",
    "gn:admin2_code":"7732066.0",
    "gn:asciiname":"Bango",
    "gn:country_code":"CF",
    "gn:dem":604,
    "gn:feature_class":"P",
    "gn:feature_code":"PPL",
    "gn:name":"Bango",
    "gn:population":0,
    "gn:timezone":"Africa/Bangui",
    "iso:country":"CF",
    "name:ceb_x_preferred":[
        "Bango"
    ],
    "name:deu_x_preferred":[
        "Bango"
    ],
    "name:swe_x_preferred":[
        "Bango"
    ],
    "wof:name":"Bango",
    "wof:placetype":"locality"
},
  "geometry": {"coordinates":[21.76387,5.31808],"type":"Point"}
}