{
  "type": "Feature",
  "properties": {
    "gn:admin1_code":"8.0",
    "gn:admin2_code":"7732064.0",
    "gn:asciiname":"Demba",
    "gn:country_code":"CF",
    "gn:dem":588,
    "gn:feature_class":"P",
    "gn:feature_code":"PPL",
    "gn:name":"Demba",
    "gn:population":0,
    "gn:timezone":"Africa/Bangui",
    "iso:country":"CF",
    "name:ceb_x_preferred":[
        "Demba"
    ],
    "name:deu_x_preferred":[
        "Demba"
    ],
    "name:ron_x_preferred":[
        "Demba"
    ],
    "name:swe_x_preferred":[
        "Demba"
    ],
    "wof:name":"Demba",
    "wof:placetype":"locality"
},
  "geometry": {"coordinates":[23.57751,4.93877],"type":"Point"}
}