{
  "type": "Feature",
  "properties": {
    "gn:admin1_code":"5.0",
    "gn:admin2_code":"9143462.0",
    "gn:asciiname":"Sourmane",
    "gn:country_code":"CF",
    "gn:dem":634,
    "gn:feature_class":"P",
    "gn:feature_code":"PPL",
    "gn:name":"Sourmane",
    "gn:population":0,
    "gn:timezone":"Africa/Bangui",
    "iso:country":"CF",
    "wof:name":"Sourmane",
    "wof:placetype":"locality"
},
  "geometry": {"coordinates":[24.81667,6.65],"type":"Point"}
}