{
  "type": "Feature",
  "properties": {
    "gn:admin1_code":"11.0",
    "gn:admin2_code":"7732377.0",
    "gn:asciiname":"Yangbeu",
    "gn:country_code":"CF",
    "gn:dem":562,
    "gn:feature_class":"P",
    "gn:feature_code":"PPL",
    "gn:name":"Yangbeu",
    "gn:population":0,
    "gn:timezone":"Africa/Bangui",
    "iso:country":"CF",
    "wof:name":"Yangbeu",
    "wof:placetype":"locality"
},
  "geometry": {"coordinates":[19.77114,5.98484],"type":"Point"}
}