{
  "type": "Feature",
  "properties": {
    "gn:admin1_code":"7.0",
    "gn:admin2_code":"7732068.0",
    "gn:asciiname":"Boussemba",
    "gn:country_code":"CF",
    "gn:dem":405,
    "gn:feature_class":"P",
    "gn:feature_code":"PPL",
    "gn:name":"Boussemba",
    "gn:population":0,
    "gn:timezone":"Africa/Bangui",
    "iso:country":"CF",
    "wof:name":"Boussemba",
    "wof:placetype":"locality"
},
  "geometry": {"coordinates":[18.15327000000001,3.7265],"type":"Point"}
}