{
  "type": "Feature",
  "properties": {
    "gn:admin1_code":"11.0",
    "gn:admin2_code":"9143471.0",
    "gn:asciiname":"Roandji",
    "gn:country_code":"CF",
    "gn:dem":572,
    "gn:feature_class":"P",
    "gn:feature_code":"PPL",
    "gn:name":"Roandji",
    "gn:population":0,
    "gn:timezone":"Africa/Bangui",
    "iso:country":"CF",
    "wof:name":"Roandji",
    "wof:placetype":"locality"
},
  "geometry": {"coordinates":[20.70246,6.18259],"type":"Point"}
}