{
  "type": "Feature",
  "properties": {
    "gn:admin1_code":"17.0",
    "gn:admin2_code":"7732372.0",
    "gn:asciiname":"Bokanga",
    "gn:cc2":"CF",
    "gn:country_code":"CF",
    "gn:dem":681,
    "gn:feature_class":"P",
    "gn:feature_code":"PPL",
    "gn:name":"Bokanga",
    "gn:population":0,
    "gn:timezone":"Africa/Bangui",
    "iso:country":"CF",
    "name:und_x_variant":[
        "Bokengu\u00e9",
        "Bokanga"
    ],
    "wof:name":"Bokanga",
    "wof:placetype":"locality"
},
  "geometry": {"coordinates":[17.31667,5.25],"type":"Point"}
}