{
  "type": "Feature",
  "properties": {
    "gn:admin1_code":"1.0",
    "gn:admin2_code":"9143460.0",
    "gn:asciiname":"Aliou",
    "gn:country_code":"CF",
    "gn:dem":584,
    "gn:feature_class":"P",
    "gn:feature_code":"PPL",
    "gn:name":"Aliou",
    "gn:population":0,
    "gn:timezone":"Africa/Bangui",
    "iso:country":"CF",
    "name:und_x_variant":[
        "Alihoui",
        "Aliou"
    ],
    "wof:name":"Aliou",
    "wof:placetype":"locality"
},
  "geometry": {"coordinates":[20.6956,8.45467],"type":"Point"}
}