{
  "type": "Feature",
  "properties": {
    "iso:country":"CF",
    "name:azb_x_preferred":[
        "\u0628\u0627\u062a\u0627\u0646\u0642\u0627\u0641\u0648"
    ],
    "name:ceb_x_preferred":[
        "Batangafo"
    ],
    "name:deu_x_preferred":[
        "Batangafo"
    ],
    "name:eng_x_preferred":[
        "Batangafo"
    ],
    "name:fas_x_preferred":[
        "\u0628\u0627\u062a\u0627\u0646\u06af\u0627\u0641\u0648"
    ],
    "name:fra_x_preferred":[
        "Batangafo"
    ],
    "name:ita_x_preferred":[
        "Batangafo"
    ],
    "name:jpn_x_preferred":[
        "\u30d0\u30bf\u30f3\u30ac\u30d5\u30a9"
    ],
    "name:ltz_x_preferred":[
        "Batangafo"
    ],
    "name:nld_x_preferred":[
        "Batangafo"
    ],
    "name:pol_x_preferred":[
        "Batangafo"
    ],
    "name:ron_x_preferred":[
        "Batangafo"
    ],
    "name:rus_x_preferred":[
        "\u0411\u0430\u0442\u0430\u043d\u0433\u0430\u0444\u043e"
    ],
    "name:sag_x_preferred":[
        "Batangafo"
    ],
    "name:swe_x_preferred":[
        "Batangafo"
    ],
    "name:tur_x_preferred":[
        "Batangafo"
    ],
    "name:ukr_x_preferred":[
        "\u0411\u0430\u0442\u0430\u043d\u0491\u0430\u0444\u043e"
    ],
    "name:und_x_variant":[
        "D\u00e9vo"
    ],
    "qs:gn_country":"CF",
    "qs:gn_fcode":"PPL",
    "qs:gn_pop":15310,
    "qs:name":"Batangafo",
    "qs:name_adm0":"R\u00e9publique Centrafricaine",
    "qs:name_adm1":"Ouham",
    "qs:photos":0,
    "qs:photos_1k":0,
    "qs:photos_9k":0,
    "qs:photos_9r":0,
    "qs:photos_all":0,
    "qs:photos_sr":0,
    "qs:placetype":"Town",
    "qs:pop_sr":"6",
    "qs:woe_adm0":23424792,
    "wd:wordcount":46,
    "wof:name":"Batangafo",
    "wof:placetype":"locality",
    "wof:population":15310
},
  "geometry": {"coordinates":[18.2833,7.30082],"type":"Point"}
}