{
  "type": "Feature",
  "properties": {
    "gn:admin1_code":"13",
    "gn:admin2_code":"9143493.0",
    "gn:asciiname":"Bezaoueten",
    "gn:country_code":"CF",
    "gn:dem":1015,
    "gn:feature_class":"P",
    "gn:feature_code":"PPL",
    "gn:name":"B\u00e9zaoueten",
    "gn:population":0,
    "gn:timezone":"Africa/Bangui",
    "iso:country":"CF",
    "wof:name":"Bezaoueten",
    "wof:placetype":"locality"
},
  "geometry": {"coordinates":[15.22386,7.08119],"type":"Point"}
}