{
  "type": "Feature",
  "properties": {
    "gn:admin1_code":"6.0",
    "gn:admin2_code":"7732483.0",
    "gn:asciiname":"Bamassa",
    "gn:country_code":"CF",
    "gn:dem":549,
    "gn:feature_class":"P",
    "gn:feature_code":"PPL",
    "gn:name":"Bamassa",
    "gn:population":0,
    "gn:timezone":"Africa/Bangui",
    "iso:country":"CF",
    "name:und_x_variant":[
        "Bamasa"
    ],
    "wof:name":"Bamassa",
    "wof:placetype":"locality"
},
  "geometry": {"coordinates":[19.52826,5.79441],"type":"Point"}
}