{
  "type": "Feature",
  "properties": {
    "gn:admin1_code":"12",
    "gn:admin2_code":"9143472.0",
    "gn:asciiname":"Bomanda",
    "gn:country_code":"CF",
    "gn:dem":416,
    "gn:feature_class":"P",
    "gn:feature_code":"PPL",
    "gn:name":"Bomanda",
    "gn:population":0,
    "gn:timezone":"Africa/Bangui",
    "iso:country":"CF",
    "wof:name":"Bomanda",
    "wof:placetype":"locality"
},
  "geometry": {"coordinates":[18.19418,7.29625],"type":"Point"}
}