{
  "type": "Feature",
  "properties": {
    "gn:admin1_code":"11.0",
    "gn:admin2_code":"7732377.0",
    "gn:asciiname":"Kongue",
    "gn:country_code":"CF",
    "gn:dem":571,
    "gn:feature_class":"P",
    "gn:feature_code":"PPL",
    "gn:name":"Kongu\u00e9",
    "gn:population":0,
    "gn:timezone":"Africa/Bangui",
    "iso:country":"CF",
    "wof:name":"Kongue",
    "wof:placetype":"locality"
},
  "geometry": {"coordinates":[20.3348,5.82236],"type":"Point"}
}