{
  "type": "Feature",
  "properties": {
    "gn:admin1_code":"2.0",
    "gn:admin2_code":"7731892.0",
    "gn:asciiname":"Yere",
    "gn:country_code":"CF",
    "gn:dem":458,
    "gn:feature_class":"P",
    "gn:feature_code":"PPL",
    "gn:name":"Yer\u00e9",
    "gn:population":0,
    "gn:timezone":"Africa/Bangui",
    "iso:country":"CF",
    "wof:name":"Yere",
    "wof:placetype":"locality"
},
  "geometry": {"coordinates":[20.60004,4.55333],"type":"Point"}
}