{
  "type": "Feature",
  "properties": {
    "gn:admin1_code":"2.0",
    "gn:admin2_code":"7731892.0",
    "gn:asciiname":"Togbo",
    "gn:country_code":"CF",
    "gn:dem":427,
    "gn:feature_class":"P",
    "gn:feature_code":"PPL",
    "gn:name":"Togbo",
    "gn:population":0,
    "gn:timezone":"Africa/Bangui",
    "iso:country":"CF",
    "wof:name":"Togbo",
    "wof:placetype":"locality"
},
  "geometry": {"coordinates":[20.93345,4.5357],"type":"Point"}
}