{
  "type": "Feature",
  "properties": {
    "gn:admin1_code":"11.0",
    "gn:admin2_code":"7732067.0",
    "gn:asciiname":"Dekamba",
    "gn:country_code":"CF",
    "gn:dem":661,
    "gn:feature_class":"P",
    "gn:feature_code":"PPL",
    "gn:name":"Dekamba",
    "gn:population":0,
    "gn:timezone":"Africa/Bangui",
    "iso:country":"CF",
    "wof:name":"Dekamba",
    "wof:placetype":"locality"
},
  "geometry": {"coordinates":[21.13333,6.51667],"type":"Point"}
}