{
  "type": "Feature",
  "properties": {
    "gn:admin1_code":"17.0",
    "gn:admin2_code":"7731895.0",
    "gn:asciiname":"Binima",
    "gn:country_code":"CF",
    "gn:dem":441,
    "gn:feature_class":"P",
    "gn:feature_code":"PPL",
    "gn:name":"Binima",
    "gn:population":0,
    "gn:timezone":"Africa/Bangui",
    "iso:country":"CF",
    "wof:name":"Binima",
    "wof:placetype":"locality"
},
  "geometry": {"coordinates":[18.66087000000001,5.00185],"type":"Point"}
}