{
  "type": "Feature",
  "properties": {
    "gn:admin1_code":"13.0",
    "gn:admin2_code":"9143494.0",
    "gn:asciiname":"Bowe",
    "gn:country_code":"CF",
    "gn:dem":669,
    "gn:feature_class":"P",
    "gn:feature_code":"PPL",
    "gn:name":"Bow\u00e9",
    "gn:population":0,
    "gn:timezone":"Africa/Bangui",
    "iso:country":"CF",
    "wof:name":"Bowe",
    "wof:placetype":"locality"
},
  "geometry": {"coordinates":[16.70676,6.71279],"type":"Point"}
}