{
  "type": "Feature",
  "properties": {
    "gn:admin1_code":"3.0",
    "gn:admin2_code":"9143466.0",
    "gn:asciiname":"Boungou",
    "gn:country_code":"CF",
    "gn:dem":695,
    "gn:feature_class":"P",
    "gn:feature_code":"PPL",
    "gn:name":"Boungou",
    "gn:population":0,
    "gn:timezone":"Africa/Bangui",
    "iso:country":"CF",
    "wof:name":"Boungou",
    "wof:placetype":"locality"
},
  "geometry": {"coordinates":[22.05595,7.97362],"type":"Point"}
}