{
  "type": "Feature",
  "properties": {
    "gn:admin1_code":"13.0",
    "gn:admin2_code":"8299286.0",
    "gn:asciiname":"Pinongo",
    "gn:country_code":"CF",
    "gn:dem":717,
    "gn:feature_class":"P",
    "gn:feature_code":"PPL",
    "gn:name":"Pinongo",
    "gn:population":0,
    "gn:timezone":"Africa/Bangui",
    "iso:country":"CF",
    "wof:name":"Pinongo",
    "wof:placetype":"locality"
},
  "geometry": {"coordinates":[16.28463,6.3468],"type":"Point"}
}