{
  "type": "Feature",
  "properties": {
    "gn:admin1_code":"17.0",
    "gn:admin2_code":"7731895.0",
    "gn:asciiname":"Bogoin",
    "gn:country_code":"CF",
    "gn:dem":567,
    "gn:feature_class":"P",
    "gn:feature_code":"PPL",
    "gn:name":"Bogoin",
    "gn:population":0,
    "gn:timezone":"Africa/Bangui",
    "iso:country":"CF",
    "wof:name":"Bogoin",
    "wof:placetype":"locality"
},
  "geometry": {"coordinates":[18.43442000000001,5.18408],"type":"Point"}
}