{
  "type": "Feature",
  "properties": {
    "gn:admin1_code":"15.0",
    "gn:admin2_code":"9143469.0",
    "gn:asciiname":"Ngouvota",
    "gn:country_code":"CF",
    "gn:dem":491,
    "gn:feature_class":"P",
    "gn:feature_code":"PPL",
    "gn:name":"Ngouvota",
    "gn:population":0,
    "gn:timezone":"Africa/Bangui",
    "iso:country":"CF",
    "wof:name":"Ngouvota",
    "wof:placetype":"locality"
},
  "geometry": {"coordinates":[19.1303,6.76321],"type":"Point"}
}