{
  "type": "Feature",
  "properties": {
    "gn:admin1_code":"4.0",
    "gn:admin2_code":"7732685.0",
    "gn:asciiname":"Camp Bato",
    "gn:cc2":"CF",
    "gn:country_code":"CF",
    "gn:dem":515,
    "gn:feature_class":"P",
    "gn:feature_code":"PPL",
    "gn:name":"Camp Bato",
    "gn:population":0,
    "gn:timezone":"Africa/Bangui",
    "iso:country":"CF",
    "name:und_x_variant":[
        "Bato",
        "Camp Bato"
    ],
    "wof:name":"Camp Bato",
    "wof:placetype":"locality"
},
  "geometry": {"coordinates":[16.06667,4.36667],"type":"Point"}
}