{
  "type": "Feature",
  "properties": {
    "gn:admin1_code":"15",
    "gn:admin2_code":"9143469.0",
    "gn:asciiname":"Kodo I",
    "gn:country_code":"CF",
    "gn:dem":422,
    "gn:feature_class":"P",
    "gn:feature_code":"PPL",
    "gn:name":"Kodo I",
    "gn:population":0,
    "gn:timezone":"Africa/Bangui",
    "iso:country":"CF",
    "wof:name":"Kodo I",
    "wof:placetype":"locality"
},
  "geometry": {"coordinates":[19.18927,7.06653],"type":"Point"}
}