{
  "type": "Feature",
  "properties": {
    "gn:admin1_code":"1.0",
    "gn:admin2_code":"9143459.0",
    "gn:asciiname":"Bangoran",
    "gn:country_code":"CF",
    "gn:dem":413,
    "gn:feature_class":"P",
    "gn:feature_code":"PPL",
    "gn:name":"Bangoran",
    "gn:population":0,
    "gn:timezone":"Africa/Bangui",
    "iso:country":"CF",
    "wof:name":"Bangoran",
    "wof:placetype":"locality"
},
  "geometry": {"coordinates":[20.34539,8.08074],"type":"Point"}
}