{
  "type": "Feature",
  "properties": {
    "gn:admin1_code":"4.0",
    "gn:admin2_code":"7732916.0",
    "gn:asciiname":"Nouffou",
    "gn:country_code":"CF",
    "gn:dem":620,
    "gn:feature_class":"P",
    "gn:feature_code":"PPL",
    "gn:name":"Nouffou",
    "gn:population":0,
    "gn:timezone":"Africa/Bangui",
    "iso:country":"CF",
    "wof:name":"Nouffou",
    "wof:placetype":"locality"
},
  "geometry": {"coordinates":[15.15,4.45],"type":"Point"}
}