{
  "type": "Feature",
  "properties": {
    "gn:admin1_code":"17.0",
    "gn:admin2_code":"7732723.0",
    "gn:asciiname":"Boese I",
    "gn:country_code":"CF",
    "gn:dem":611,
    "gn:feature_class":"P",
    "gn:feature_code":"PPL",
    "gn:name":"Bo\u00e9s\u00e9 I",
    "gn:population":0,
    "gn:timezone":"Africa/Bangui",
    "iso:country":"CF",
    "name:und_x_variant":[
        "Booss\u00e9",
        "Bosui",
        "Bosoui",
        "Bouss\u00e9",
        "Bo\u00e9s\u00e9 I"
    ],
    "wof:name":"Boese I",
    "wof:placetype":"locality"
},
  "geometry": {"coordinates":[17.73481,5.67044],"type":"Point"}
}