{
  "type": "Feature",
  "properties": {
    "gn:admin1_code":"6.0",
    "gn:admin2_code":"7731894.0",
    "gn:asciiname":"Deko-Togbo",
    "gn:country_code":"CF",
    "gn:dem":451,
    "gn:feature_class":"P",
    "gn:feature_code":"PPL",
    "gn:name":"D\u00e9ko-Togbo",
    "gn:population":0,
    "gn:timezone":"Africa/Bangui",
    "iso:country":"CF",
    "name:und_x_variant":[
        "D\u00e9ko-Togbo",
        "D\u00e9ko I"
    ],
    "wof:name":"Deko-Togbo",
    "wof:placetype":"locality"
},
  "geometry": {"coordinates":[19.57088,5.29917],"type":"Point"}
}