{
  "type": "Feature",
  "properties": {
    "gn:admin1_code":"8.0",
    "gn:admin2_code":"7731889.0",
    "gn:asciiname":"Dounga",
    "gn:country_code":"CF",
    "gn:dem":516,
    "gn:feature_class":"P",
    "gn:feature_code":"PPL",
    "gn:name":"Dounga",
    "gn:population":0,
    "gn:timezone":"Africa/Bangui",
    "iso:country":"CF",
    "wof:name":"Dounga",
    "wof:placetype":"locality"
},
  "geometry": {"coordinates":[22.4087,4.63488],"type":"Point"}
}