{
  "type": "Feature",
  "properties": {
    "gn:admin1_code":"4.0",
    "gn:admin2_code":"7732917.0",
    "gn:asciiname":"Gaboua",
    "gn:country_code":"CF",
    "gn:dem":688,
    "gn:feature_class":"P",
    "gn:feature_code":"PPL",
    "gn:name":"Gaboua",
    "gn:population":0,
    "gn:timezone":"Africa/Bangui",
    "iso:country":"CF",
    "name:und_x_variant":[
        "Ngubu",
        "Goubou",
        "Ngoubou",
        "Gaboua"
    ],
    "wof:name":"Gaboua",
    "wof:placetype":"locality"
},
  "geometry": {"coordinates":[16.53221,5.1714],"type":"Point"}
}