{
  "type": "Feature",
  "properties": {
    "gn:admin1_code":"03",
    "gn:admin2_code":"9143466.0",
    "gn:asciiname":"Yangou Abara",
    "gn:country_code":"CF",
    "gn:dem":727,
    "gn:feature_class":"P",
    "gn:feature_code":"PPL",
    "gn:name":"Yangou Abara",
    "gn:population":0,
    "gn:timezone":"Africa/Bangui",
    "iso:country":"CF",
    "name:fra_x_preferred":[
        "Yangou Abara"
    ],
    "wof:name":"Yangou Abara",
    "wof:placetype":"locality"
},
  "geometry": {"coordinates":[22.3856,8.10493],"type":"Point"}
}