{
  "type": "Feature",
  "properties": {
    "gn:admin1_code":"11.0",
    "gn:admin2_code":"7732062.0",
    "gn:asciiname":"Ingwinda I",
    "gn:country_code":"CF",
    "gn:dem":495,
    "gn:feature_class":"P",
    "gn:feature_code":"PPL",
    "gn:name":"Ingwinda I",
    "gn:population":0,
    "gn:timezone":"Africa/Bangui",
    "iso:country":"CF",
    "wof:name":"Ingwinda I",
    "wof:placetype":"locality"
},
  "geometry": {"coordinates":[20.57525,5.71402],"type":"Point"}
}