{
  "type": "Feature",
  "properties": {
    "gn:admin1_code":"11.0",
    "gn:admin2_code":"7732062.0",
    "gn:asciiname":"Binguibanda",
    "gn:country_code":"CF",
    "gn:dem":548,
    "gn:feature_class":"P",
    "gn:feature_code":"PPL",
    "gn:name":"Binguibanda",
    "gn:population":0,
    "gn:timezone":"Africa/Bangui",
    "iso:country":"CF",
    "wof:name":"Binguibanda",
    "wof:placetype":"locality"
},
  "geometry": {"coordinates":[20.46452,5.84095],"type":"Point"}
}