{
  "type": "Feature",
  "properties": {
    "gn:admin1_code":"13.0",
    "gn:admin2_code":"9143493.0",
    "gn:asciiname":"Mambourou",
    "gn:country_code":"CF",
    "gn:dem":601,
    "gn:feature_class":"P",
    "gn:feature_code":"PPL",
    "gn:name":"Mambourou",
    "gn:population":0,
    "gn:timezone":"Africa/Bangui",
    "iso:country":"CF",
    "name:und_x_variant":[
        "Mamboro",
        "Mambourou"
    ],
    "wof:name":"Mambourou",
    "wof:placetype":"locality"
},
  "geometry": {"coordinates":[16.05514,7.41024],"type":"Point"}
}