{
  "type": "Feature",
  "properties": {
    "gn:admin1_code":"5.0",
    "gn:admin2_code":"9143463.0",
    "gn:asciiname":"Bonbe",
    "gn:country_code":"CF",
    "gn:dem":647,
    "gn:feature_class":"P",
    "gn:feature_code":"PPL",
    "gn:name":"Bonbe",
    "gn:population":0,
    "gn:timezone":"Africa/Bangui",
    "iso:country":"CF",
    "wof:name":"Bonbe",
    "wof:placetype":"locality"
},
  "geometry": {"coordinates":[26.40702000000001,5.42821],"type":"Point"}
}