{
  "type": "Feature",
  "properties": {
    "gn:admin1_code":"11.0",
    "gn:admin2_code":"7732067.0",
    "gn:asciiname":"Madonguere",
    "gn:country_code":"CF",
    "gn:dem":653,
    "gn:feature_class":"P",
    "gn:feature_code":"PPL",
    "gn:name":"Madonguere",
    "gn:population":0,
    "gn:timezone":"Africa/Bangui",
    "iso:country":"CF",
    "name:und_x_variant":[
        "Modongouere",
        "Madangu\u00e9r\u00e9",
        "Modonguere",
        "Madonguere"
    ],
    "wof:name":"Madonguere",
    "wof:placetype":"locality"
},
  "geometry": {"coordinates":[21.09831,6.62652],"type":"Point"}
}