{
  "type": "Feature",
  "properties": {
    "gn:admin1_code":"15.0",
    "gn:admin2_code":"9143469.0",
    "gn:asciiname":"Boubou I",
    "gn:country_code":"CF",
    "gn:dem":444,
    "gn:feature_class":"P",
    "gn:feature_code":"PPL",
    "gn:name":"Boubou I",
    "gn:population":0,
    "gn:timezone":"Africa/Bangui",
    "iso:country":"CF",
    "name:und_x_variant":[
        "Boubou"
    ],
    "wof:name":"Boubou I",
    "wof:placetype":"locality"
},
  "geometry": {"coordinates":[19.23585,7.01729],"type":"Point"}
}