{
  "type": "Feature",
  "properties": {
    "gn:admin1_code":"15.0",
    "gn:admin2_code":"9143469.0",
    "gn:asciiname":"Dere",
    "gn:country_code":"CF",
    "gn:dem":452,
    "gn:feature_class":"P",
    "gn:feature_code":"PPL",
    "gn:name":"D\u00e9r\u00e9",
    "gn:population":0,
    "gn:timezone":"Africa/Bangui",
    "iso:country":"CF",
    "wof:name":"Dere",
    "wof:placetype":"locality"
},
  "geometry": {"coordinates":[19.2178,6.84416],"type":"Point"}
}