{
  "type": "Feature",
  "properties": {
    "gn:admin1_code":"12.0",
    "gn:admin2_code":"7732115.0",
    "gn:asciiname":"Kaba",
    "gn:country_code":"CF",
    "gn:dem":604,
    "gn:feature_class":"P",
    "gn:feature_code":"PPL",
    "gn:name":"Kaba",
    "gn:population":0,
    "gn:timezone":"Africa/Bangui",
    "iso:country":"CF",
    "name:ceb_x_preferred":[
        "Kaba"
    ],
    "name:deu_x_preferred":[
        "Kaba"
    ],
    "name:fin_x_preferred":[
        "Kaba"
    ],
    "name:fra_x_preferred":[
        "Kaba"
    ],
    "name:hrv_x_preferred":[
        "Kaba"
    ],
    "name:swe_x_preferred":[
        "Kaba"
    ],
    "wof:name":"Kaba",
    "wof:placetype":"locality"
},
  "geometry": {"coordinates":[17.43222,6.1011],"type":"Point"}
}