{
  "type": "Feature",
  "properties": {
    "gn:admin1_code":"12.0",
    "gn:admin2_code":"9143477.0",
    "gn:asciiname":"Goundou",
    "gn:country_code":"CF",
    "gn:dem":526,
    "gn:feature_class":"P",
    "gn:feature_code":"PPL",
    "gn:name":"Goundou",
    "gn:population":0,
    "gn:timezone":"Africa/Bangui",
    "iso:country":"CF",
    "name:ceb_x_preferred":[
        "Goundou"
    ],
    "name:fra_x_preferred":[
        "Goundou"
    ],
    "name:swe_x_preferred":[
        "Goundou"
    ],
    "wof:name":"Goundou",
    "wof:placetype":"locality"
},
  "geometry": {"coordinates":[18.35,5.93333],"type":"Point"}
}