{
  "type": "Feature",
  "properties": {
    "gn:admin1_code":"9.0",
    "gn:admin2_code":"7732085.0",
    "gn:asciiname":"Dare",
    "gn:country_code":"CF",
    "gn:dem":951,
    "gn:feature_class":"P",
    "gn:feature_code":"PPL",
    "gn:name":"Dar\u00e9",
    "gn:population":0,
    "gn:timezone":"Africa/Bangui",
    "iso:country":"CF",
    "wof:name":"Dare",
    "wof:placetype":"locality"
},
  "geometry": {"coordinates":[15.18521,6.1086],"type":"Point"}
}