{
  "type": "Feature",
  "properties": {
    "gn:admin1_code":"8.0",
    "gn:admin2_code":"7731888.0",
    "gn:asciiname":"Inzia",
    "gn:country_code":"CF",
    "gn:dem":481,
    "gn:feature_class":"P",
    "gn:feature_code":"PPL",
    "gn:name":"Inzia",
    "gn:population":0,
    "gn:timezone":"Africa/Bangui",
    "iso:country":"CF",
    "name:und_x_variant":[
        "Inza",
        "Inzia"
    ],
    "wof:name":"Inzia",
    "wof:placetype":"locality"
},
  "geometry": {"coordinates":[22.43011,4.39108],"type":"Point"}
}