{
  "type": "Feature",
  "properties": {
    "gn:admin1_code":"13.0",
    "gn:admin2_code":"8299286.0",
    "gn:asciiname":"Bodalou III",
    "gn:country_code":"CF",
    "gn:dem":526,
    "gn:feature_class":"P",
    "gn:feature_code":"PPL",
    "gn:name":"Bodalou III",
    "gn:population":0,
    "gn:timezone":"Africa/Bangui",
    "iso:country":"CF",
    "wof:name":"Bodalou III",
    "wof:placetype":"locality"
},
  "geometry": {"coordinates":[17.03988,6.45783],"type":"Point"}
}