{
  "type": "Feature",
  "properties": {
    "gn:admin1_code":"11.0",
    "gn:admin2_code":"7731893.0",
    "gn:asciiname":"Bida",
    "gn:country_code":"CF",
    "gn:dem":382,
    "gn:feature_class":"P",
    "gn:feature_code":"PPL",
    "gn:name":"Bida",
    "gn:population":0,
    "gn:timezone":"Africa/Bangui",
    "iso:country":"CF",
    "name:cat_x_preferred":[
        "Bida"
    ],
    "name:ceb_x_preferred":[
        "Bida"
    ],
    "name:epo_x_preferred":[
        "Bida"
    ],
    "name:fra_x_preferred":[
        "Bida"
    ],
    "name:hau_x_preferred":[
        "Bida"
    ],
    "name:ita_x_preferred":[
        "Bida"
    ],
    "name:pol_x_preferred":[
        "Bida"
    ],
    "name:por_x_preferred":[
        "Bida"
    ],
    "name:ron_x_preferred":[
        "Bida"
    ],
    "name:rus_x_preferred":[
        "\u0411\u0438\u0434\u0430"
    ],
    "name:spa_x_preferred":[
        "Bida"
    ],
    "name:swe_x_preferred":[
        "Bida"
    ],
    "name:yor_x_preferred":[
        "Bida"
    ],
    "wof:name":"Bida",
    "wof:placetype":"locality"
},
  "geometry": {"coordinates":[20.01667,4.98333],"type":"Point"}
}