{
  "type": "Feature",
  "properties": {
    "gn:admin1_code":"3.0",
    "gn:admin2_code":"9143475.0",
    "gn:asciiname":"Ngoto",
    "gn:country_code":"CF",
    "gn:dem":698,
    "gn:feature_class":"P",
    "gn:feature_code":"PPL",
    "gn:name":"Ngoto",
    "gn:population":0,
    "gn:timezone":"Africa/Bangui",
    "iso:country":"CF",
    "wof:name":"Ngoto",
    "wof:placetype":"locality"
},
  "geometry": {"coordinates":[23.05,6.41667],"type":"Point"}
}