{
  "type": "Feature",
  "properties": {
    "gn:admin1_code":"12.0",
    "gn:admin2_code":"7732115.0",
    "gn:asciiname":"Soumbe",
    "gn:country_code":"CF",
    "gn:dem":447,
    "gn:feature_class":"P",
    "gn:feature_code":"PPL",
    "gn:name":"Soumb\u00e9",
    "gn:population":0,
    "gn:timezone":"Africa/Bangui",
    "iso:country":"CF",
    "wof:name":"Soumbe",
    "wof:placetype":"locality"
},
  "geometry": {"coordinates":[17.56701,6.50918],"type":"Point"}
}