{
  "type": "Feature",
  "properties": {
    "gn:admin1_code":"2.0",
    "gn:admin2_code":"7732066.0",
    "gn:asciiname":"Banan",
    "gn:country_code":"CF",
    "gn:dem":507,
    "gn:feature_class":"P",
    "gn:feature_code":"PPL",
    "gn:name":"Banan",
    "gn:population":0,
    "gn:timezone":"Africa/Bangui",
    "iso:country":"CF",
    "name:deu_x_preferred":[
        "Banan"
    ],
    "name:rus_x_preferred":[
        "\u0411\u0430\u043d\u0430\u043d"
    ],
    "name:ukr_x_preferred":[
        "\u0411\u0430\u043d\u0430\u043d"
    ],
    "wof:name":"Banan",
    "wof:placetype":"locality"
},
  "geometry": {"coordinates":[21.88674,5.2659],"type":"Point"}
}