{
  "type": "Feature",
  "properties": {
    "gn:admin1_code":"8.0",
    "gn:admin2_code":"7731889.0",
    "gn:asciiname":"Ngake",
    "gn:country_code":"CF",
    "gn:dem":414,
    "gn:feature_class":"P",
    "gn:feature_code":"PPL",
    "gn:name":"Ngak\u00e9",
    "gn:population":0,
    "gn:timezone":"Africa/Bangui",
    "iso:country":"CF",
    "wof:name":"Ngake",
    "wof:placetype":"locality"
},
  "geometry": {"coordinates":[22.24225,4.13943],"type":"Point"}
}