{
  "type": "Feature",
  "properties": {
    "gn:admin1_code":"15.0",
    "gn:admin2_code":"9143469.0",
    "gn:asciiname":"Boto",
    "gn:country_code":"CF",
    "gn:dem":445,
    "gn:feature_class":"P",
    "gn:feature_code":"PPL",
    "gn:name":"Boto",
    "gn:population":0,
    "gn:timezone":"Africa/Bangui",
    "iso:country":"CF",
    "wof:name":"Boto",
    "wof:placetype":"locality"
},
  "geometry": {"coordinates":[19.13333,6.96667],"type":"Point"}
}