{
  "type": "Feature",
  "properties": {
    "gn:admin1_code":"17.0",
    "gn:admin2_code":"7731896.0",
    "gn:asciiname":"Bogo II",
    "gn:country_code":"CF",
    "gn:dem":341,
    "gn:feature_class":"P",
    "gn:feature_code":"PPL",
    "gn:name":"Bogo II",
    "gn:population":0,
    "gn:timezone":"Africa/Bangui",
    "iso:country":"CF",
    "wof:name":"Bogo II",
    "wof:placetype":"locality"
},
  "geometry": {"coordinates":[18.69347,4.36595],"type":"Point"}
}