{
  "type": "Feature",
  "properties": {
    "gn:admin1_code":"17.0",
    "gn:admin2_code":"9143490.0",
    "gn:asciiname":"Oualembou",
    "gn:country_code":"CF",
    "gn:dem":571,
    "gn:feature_class":"P",
    "gn:feature_code":"PPL",
    "gn:name":"Oualembou",
    "gn:population":0,
    "gn:timezone":"Africa/Bangui",
    "iso:country":"CF",
    "name:und_x_variant":[
        "Oualambou"
    ],
    "wof:name":"Oualembou",
    "wof:placetype":"locality"
},
  "geometry": {"coordinates":[18.13547,5.57216],"type":"Point"}
}