{
  "type": "Feature",
  "properties": {
    "gn:admin1_code":"17",
    "gn:admin2_code":"7732372.0",
    "gn:asciiname":"Bodoupa I",
    "gn:country_code":"CF",
    "gn:dem":730,
    "gn:feature_class":"P",
    "gn:feature_code":"PPL",
    "gn:name":"Bodoupa I",
    "gn:population":0,
    "gn:timezone":"Africa/Bangui",
    "iso:country":"CF",
    "wof:name":"Bodoupa I",
    "wof:placetype":"locality"
},
  "geometry": {"coordinates":[17.04411,5.35688],"type":"Point"}
}