{
  "type": "Feature",
  "properties": {
    "gn:admin1_code":"16",
    "gn:admin2_code":"7731904.0",
    "gn:asciiname":"Aloba",
    "gn:country_code":"CF",
    "gn:dem":667,
    "gn:feature_class":"P",
    "gn:feature_code":"PPL",
    "gn:name":"Aloba",
    "gn:population":0,
    "gn:timezone":"Africa/Bangui",
    "iso:country":"CF",
    "name:vie_x_preferred":[
        "Aloba"
    ],
    "wof:name":"Aloba",
    "wof:placetype":"locality"
},
  "geometry": {"coordinates":[15.95329,3.46215],"type":"Point"}
}