{
  "type": "Feature",
  "properties": {
    "gn:admin1_code":"7.0",
    "gn:admin2_code":"7732068.0",
    "gn:asciiname":"Zende",
    "gn:country_code":"CF",
    "gn:dem":399,
    "gn:feature_class":"P",
    "gn:feature_code":"PPL",
    "gn:name":"Zend\u00e9",
    "gn:population":0,
    "gn:timezone":"Africa/Bangui",
    "iso:country":"CF",
    "name:und_x_variant":[
        "Zendi",
        "Zend\u00e9"
    ],
    "wof:name":"Zende",
    "wof:placetype":"locality"
},
  "geometry": {"coordinates":[18.07239,4.18469],"type":"Point"}
}