{
  "type": "Feature",
  "properties": {
    "gn:admin1_code":"07",
    "gn:admin2_code":"7732068.0",
    "gn:asciiname":"Ancien Bakani",
    "gn:country_code":"CF",
    "gn:dem":379,
    "gn:feature_class":"P",
    "gn:feature_code":"PPL",
    "gn:name":"Ancien Bakani",
    "gn:population":0,
    "gn:timezone":"Africa/Bangui",
    "iso:country":"CF",
    "name:azb_x_preferred":[
        "\u0627\u0646\u0633\u06cc\u0646 \u0628\u0627\u06a9\u0627\u0646\u06cc"
    ],
    "name:fas_x_preferred":[
        "\u0627\u0646\u0633\u06cc\u0646 \u0628\u0627\u06a9\u0627\u0646\u06cc"
    ],
    "name:lit_x_preferred":[
        "Ancien Bakanis"
    ],
    "wof:name":"Ancien Bakani",
    "wof:placetype":"locality"
},
  "geometry": {"coordinates":[18.35,3.93333],"type":"Point"}
}