{
  "type": "Feature",
  "properties": {
    "gn:admin1_code":"12.0",
    "gn:admin2_code":"9143479.0",
    "gn:asciiname":"Guenebodo",
    "gn:country_code":"CF",
    "gn:dem":428,
    "gn:feature_class":"P",
    "gn:feature_code":"PPL",
    "gn:name":"Gu\u00e9n\u00e9bodo",
    "gn:population":0,
    "gn:timezone":"Africa/Bangui",
    "iso:country":"CF",
    "name:und_x_variant":[
        "G\u00e9n\u00e9bodo",
        "Gu\u00e9n\u00e9bodo"
    ],
    "wof:name":"Guenebodo",
    "wof:placetype":"locality"
},
  "geometry": {"coordinates":[17.53461,7.58904],"type":"Point"}
}