{
  "type": "Feature",
  "properties": {
    "gn:admin1_code":"8.0",
    "gn:admin2_code":"7732690.0",
    "gn:asciiname":"Wango Bangowili",
    "gn:country_code":"CF",
    "gn:dem":570,
    "gn:feature_class":"P",
    "gn:feature_code":"PPL",
    "gn:name":"Wango Bangowili",
    "gn:population":0,
    "gn:timezone":"Africa/Bangui",
    "iso:country":"CF",
    "wof:name":"Wango Bangowili",
    "wof:placetype":"locality"
},
  "geometry": {"coordinates":[22.83481,5.18506],"type":"Point"}
}