{
  "type": "Feature",
  "properties": {
    "gn:admin1_code":"13",
    "gn:admin2_code":"9143493.0",
    "gn:asciiname":"Damale",
    "gn:country_code":"CF",
    "gn:dem":783,
    "gn:feature_class":"P",
    "gn:feature_code":"PPL",
    "gn:name":"Damal\u00e9",
    "gn:population":0,
    "gn:timezone":"Africa/Bangui",
    "iso:country":"CF",
    "wof:name":"Damale",
    "wof:placetype":"locality"
},
  "geometry": {"coordinates":[15.9733,7.45352],"type":"Point"}
}