{
  "type": "Feature",
  "properties": {
    "gn:admin1_code":"01",
    "gn:admin2_code":"9143460.0",
    "gn:asciiname":"Miabolo",
    "gn:country_code":"CF",
    "gn:dem":383,
    "gn:feature_class":"P",
    "gn:feature_code":"PPL",
    "gn:name":"Miabolo",
    "gn:population":0,
    "gn:timezone":"Africa/Bangui",
    "iso:country":"CF",
    "name:fra_x_preferred":[
        "Miabolo"
    ],
    "wof:name":"Miabolo",
    "wof:placetype":"locality"
},
  "geometry": {"coordinates":[19.20797,8.89622],"type":"Point"}
}