{
  "type": "Feature",
  "properties": {
    "gn:admin1_code":"9.0",
    "gn:admin2_code":"7732085.0",
    "gn:asciiname":"Ndale",
    "gn:country_code":"CF",
    "gn:dem":763,
    "gn:feature_class":"P",
    "gn:feature_code":"PPL",
    "gn:name":"Ndal\u00e9",
    "gn:population":0,
    "gn:timezone":"Africa/Bangui",
    "iso:country":"CF",
    "wof:name":"Ndale",
    "wof:placetype":"locality"
},
  "geometry": {"coordinates":[15.53795,5.95353],"type":"Point"}
}