{
  "type": "Feature",
  "properties": {
    "gn:admin1_code":"17.0",
    "gn:admin2_code":"7731896.0",
    "gn:asciiname":"Bombele",
    "gn:country_code":"CF",
    "gn:dem":505,
    "gn:feature_class":"P",
    "gn:feature_code":"PPL",
    "gn:name":"Bomb\u00e9l\u00e9",
    "gn:population":0,
    "gn:timezone":"Africa/Bangui",
    "iso:country":"CF",
    "name:und_x_variant":[
        "Bomb\u00e9r\u00e9",
        "Bomb\u00e9l\u00e9"
    ],
    "wof:name":"Bombele",
    "wof:placetype":"locality"
},
  "geometry": {"coordinates":[18.52446,4.56534],"type":"Point"}
}