{
  "type": "Feature",
  "properties": {
    "gn:admin1_code":"6.0",
    "gn:admin2_code":"9143484.0",
    "gn:asciiname":"Gasamba",
    "gn:cc2":"CF",
    "gn:country_code":"CF",
    "gn:dem":560,
    "gn:feature_class":"P",
    "gn:feature_code":"PPL",
    "gn:name":"Gasamba",
    "gn:population":0,
    "gn:timezone":"Africa/Bangui",
    "iso:country":"CF",
    "name:und_x_variant":[
        "Gassamba",
        "Gasamba"
    ],
    "wof:name":"Gasamba",
    "wof:placetype":"locality"
},
  "geometry": {"coordinates":[19.08333,6.33333],"type":"Point"}
}