{
  "type": "Feature",
  "properties": {
    "gn:admin1_code":"6.0",
    "gn:admin2_code":"7731894.0",
    "gn:asciiname":"Tatakara",
    "gn:country_code":"CF",
    "gn:dem":432,
    "gn:feature_class":"P",
    "gn:feature_code":"PPL",
    "gn:name":"Tatakara",
    "gn:population":0,
    "gn:timezone":"Africa/Bangui",
    "iso:country":"CF",
    "wof:name":"Tatakara",
    "wof:placetype":"locality"
},
  "geometry": {"coordinates":[19.16667,5.23333],"type":"Point"}
}