{
  "type": "Feature",
  "properties": {
    "gn:admin1_code":"4.0",
    "gn:admin2_code":"7732685.0",
    "gn:asciiname":"Ngama",
    "gn:country_code":"CF",
    "gn:dem":567,
    "gn:feature_class":"P",
    "gn:feature_code":"PPL",
    "gn:name":"Ngama",
    "gn:population":0,
    "gn:timezone":"Africa/Bangui",
    "iso:country":"CF",
    "name:fra_x_preferred":[
        "Ngama"
    ],
    "name:pol_x_preferred":[
        "Ngama"
    ],
    "name:ron_x_preferred":[
        "Ngama"
    ],
    "name:rus_x_preferred":[
        "\u041d\u0433\u0430\u043c\u0430"
    ],
    "wof:name":"Ngama",
    "wof:placetype":"locality"
},
  "geometry": {"coordinates":[15.41667,4.26667],"type":"Point"}
}