{
  "type": "Feature",
  "properties": {
    "gn:admin1_code":"11.0",
    "gn:admin2_code":"9143471.0",
    "gn:asciiname":"Tongouyassi",
    "gn:country_code":"CF",
    "gn:dem":464,
    "gn:feature_class":"P",
    "gn:feature_code":"PPL",
    "gn:name":"Tongouyassi",
    "gn:population":0,
    "gn:timezone":"Africa/Bangui",
    "iso:country":"CF",
    "wof:name":"Tongouyassi",
    "wof:placetype":"locality"
},
  "geometry": {"coordinates":[20.43293,6.01033],"type":"Point"}
}