{
  "type": "Feature",
  "properties": {
    "gn:admin1_code":"1.0",
    "gn:admin2_code":"9143460.0",
    "gn:asciiname":"Kassena Souleyman",
    "gn:country_code":"CF",
    "gn:dem":476,
    "gn:feature_class":"P",
    "gn:feature_code":"PPL",
    "gn:name":"Kass\u00e9na Souleyman",
    "gn:population":0,
    "gn:timezone":"Africa/Bangui",
    "iso:country":"CF",
    "name:und_x_variant":[
        "Kass\u00e9na Souleyman"
    ],
    "wof:name":"Kassena Souleyman",
    "wof:placetype":"locality"
},
  "geometry": {"coordinates":[20.43333,8.56667],"type":"Point"}
}