{
  "type": "Feature",
  "properties": {
    "gn:admin1_code":"11.0",
    "gn:admin2_code":"7732062.0",
    "gn:asciiname":"Kidjipala",
    "gn:country_code":"CF",
    "gn:dem":549,
    "gn:feature_class":"P",
    "gn:feature_code":"PPL",
    "gn:name":"Kidjipala",
    "gn:population":0,
    "gn:timezone":"Africa/Bangui",
    "iso:country":"CF",
    "wof:name":"Kidjipala",
    "wof:placetype":"locality"
},
  "geometry": {"coordinates":[20.41997000000001,5.52138],"type":"Point"}
}