{
  "type": "Feature",
  "properties": {
    "gn:admin1_code":"7.0",
    "gn:admin2_code":"9143486.0",
    "gn:asciiname":"Bendem Sakada",
    "gn:country_code":"CF",
    "gn:dem":644,
    "gn:feature_class":"P",
    "gn:feature_code":"PPL",
    "gn:name":"Bendem Sakada",
    "gn:population":0,
    "gn:timezone":"Africa/Bangui",
    "iso:country":"CF",
    "wof:name":"Bendem Sakada",
    "wof:placetype":"locality"
},
  "geometry": {"coordinates":[16.94908,4.74828],"type":"Point"}
}