{
  "type": "Feature",
  "properties": {
    "gn:admin1_code":"09",
    "gn:admin2_code":"9143482.0",
    "gn:asciiname":"Bafio",
    "gn:country_code":"CF",
    "gn:dem":865,
    "gn:feature_class":"P",
    "gn:feature_code":"PPL",
    "gn:name":"Bafio",
    "gn:population":0,
    "gn:timezone":"Africa/Bangui",
    "iso:country":"CF",
    "wof:name":"Bafio",
    "wof:placetype":"locality"
},
  "geometry": {"coordinates":[15.41061,5.30865],"type":"Point"}
}