{
  "type": "Feature",
  "properties": {
    "gn:admin1_code":"4.0",
    "gn:admin2_code":"7732685.0",
    "gn:asciiname":"Toro",
    "gn:country_code":"CF",
    "gn:dem":473,
    "gn:feature_class":"P",
    "gn:feature_code":"PPL",
    "gn:name":"Toro",
    "gn:population":0,
    "gn:timezone":"Africa/Bangui",
    "iso:country":"CF",
    "wof:name":"Toro",
    "wof:placetype":"locality"
},
  "geometry": {"coordinates":[16.30802000000001,4.21929],"type":"Point"}
}