{
  "type": "Feature",
  "properties": {
    "gn:admin1_code":"7.0",
    "gn:admin2_code":"9143487.0",
    "gn:asciiname":"Bonini",
    "gn:country_code":"CF",
    "gn:dem":602,
    "gn:feature_class":"P",
    "gn:feature_code":"PPL",
    "gn:name":"Bonini",
    "gn:population":0,
    "gn:timezone":"Africa/Bangui",
    "iso:country":"CF",
    "name:bos_x_preferred":[
        "Bonini"
    ],
    "name:bul_x_preferred":[
        "\u0411\u043e\u043d\u0438\u043d\u0438"
    ],
    "name:ceb_x_preferred":[
        "Bonini"
    ],
    "name:ita_x_preferred":[
        "Bonini"
    ],
    "name:nld_x_preferred":[
        "Bonini"
    ],
    "name:pol_x_preferred":[
        "Bonini"
    ],
    "name:ron_x_preferred":[
        "Bonini"
    ],
    "name:slv_x_preferred":[
        "Bonini"
    ],
    "name:ukr_x_preferred":[
        "\u0411\u043e\u043d\u0438\u043d\u0438"
    ],
    "wof:name":"Bonini",
    "wof:placetype":"locality"
},
  "geometry": {"coordinates":[17.49992,4.38597],"type":"Point"}
}