{
  "type": "Feature",
  "properties": {
    "gn:admin1_code":"2.0",
    "gn:admin2_code":"7731891.0",
    "gn:asciiname":"Koyaba",
    "gn:country_code":"CF",
    "gn:dem":496,
    "gn:feature_class":"P",
    "gn:feature_code":"PPL",
    "gn:name":"Koyaba",
    "gn:population":0,
    "gn:timezone":"Africa/Bangui",
    "iso:country":"CF",
    "wof:name":"Koyaba",
    "wof:placetype":"locality"
},
  "geometry": {"coordinates":[21.28333,4.53333],"type":"Point"}
}