{
  "type": "Feature",
  "properties": {
    "gn:admin1_code":"11.0",
    "gn:admin2_code":"9143471.0",
    "gn:asciiname":"Piangou",
    "gn:country_code":"CF",
    "gn:dem":581,
    "gn:feature_class":"P",
    "gn:feature_code":"PPL",
    "gn:name":"Piangou",
    "gn:population":0,
    "gn:timezone":"Africa/Bangui",
    "iso:country":"CF",
    "name:und_x_variant":[
        "Piangu",
        "Piangou"
    ],
    "wof:name":"Piangou",
    "wof:placetype":"locality"
},
  "geometry": {"coordinates":[20.6511,6.19106],"type":"Point"}
}