{
  "type": "Feature",
  "properties": {
    "gn:admin1_code":"12.0",
    "gn:admin2_code":"9143477.0",
    "gn:asciiname":"Baya",
    "gn:country_code":"CF",
    "gn:dem":467,
    "gn:feature_class":"P",
    "gn:feature_code":"PPL",
    "gn:name":"Baya",
    "gn:population":0,
    "gn:timezone":"Africa/Bangui",
    "iso:country":"CF",
    "name:ara_x_preferred":[
        "\u0628\u0627\u064a\u0629"
    ],
    "name:ceb_x_preferred":[
        "Baya"
    ],
    "name:deu_x_preferred":[
        "Baya"
    ],
    "name:fra_x_preferred":[
        "Baya"
    ],
    "name:spa_x_preferred":[
        "Baya"
    ],
    "name:swe_x_preferred":[
        "Baya"
    ],
    "wof:name":"Baya",
    "wof:placetype":"locality"
},
  "geometry": {"coordinates":[18.54329,6.93377],"type":"Point"}
}