{
  "type": "Feature",
  "properties": {
    "gn:admin1_code":"11.0",
    "gn:admin2_code":"7732062.0",
    "gn:asciiname":"Yabougoua",
    "gn:cc2":"CF",
    "gn:country_code":"CF",
    "gn:dem":551,
    "gn:feature_class":"P",
    "gn:feature_code":"PPL",
    "gn:name":"Yabougoua",
    "gn:population":0,
    "gn:timezone":"Africa/Bangui",
    "iso:country":"CF",
    "name:und_x_variant":[
        "Bongo",
        "Yabougoua"
    ],
    "wof:name":"Yabougoua",
    "wof:placetype":"locality"
},
  "geometry": {"coordinates":[20.56667,5.68333],"type":"Point"}
}