{
  "type": "Feature",
  "properties": {
    "gn:admin1_code":"17.0",
    "gn:admin2_code":"8299285.0",
    "gn:asciiname":"Borofio",
    "gn:country_code":"CF",
    "gn:dem":419,
    "gn:feature_class":"P",
    "gn:feature_code":"PPL",
    "gn:name":"Borofio",
    "gn:population":0,
    "gn:timezone":"Africa/Bangui",
    "iso:country":"CF",
    "name:und_x_variant":[
        "Bourofio",
        "Boukoufio",
        "Bouroufio",
        "Boukoufia",
        "Borofio"
    ],
    "wof:name":"Borofio",
    "wof:placetype":"locality"
},
  "geometry": {"coordinates":[17.77319,4.54301],"type":"Point"}
}