{
  "type": "Feature",
  "properties": {
    "gn:admin1_code":"11.0",
    "gn:admin2_code":"7732377.0",
    "gn:asciiname":"Kombanga",
    "gn:country_code":"CF",
    "gn:dem":458,
    "gn:feature_class":"P",
    "gn:feature_code":"PPL",
    "gn:name":"Kombanga",
    "gn:population":0,
    "gn:timezone":"Africa/Bangui",
    "iso:country":"CF",
    "name:und_x_variant":[
        "Kongbanga"
    ],
    "wof:name":"Kombanga",
    "wof:placetype":"locality"
},
  "geometry": {"coordinates":[19.97091,5.77798],"type":"Point"}
}