{
  "type": "Feature",
  "properties": {
    "gn:admin1_code":"13",
    "gn:admin2_code":"9143493.0",
    "gn:asciiname":"Mboum",
    "gn:country_code":"CF",
    "gn:dem":648,
    "gn:feature_class":"P",
    "gn:feature_code":"PPL",
    "gn:name":"Mboum",
    "gn:population":0,
    "gn:timezone":"Africa/Bangui",
    "iso:country":"CF",
    "wof:name":"Mboum",
    "wof:placetype":"locality"
},
  "geometry": {"coordinates":[15.53409,7.44811],"type":"Point"}
}