{
  "type": "Feature",
  "properties": {
    "gn:admin1_code":"13.0",
    "gn:admin2_code":"9143491.0",
    "gn:asciiname":"Maneke",
    "gn:country_code":"CF",
    "gn:dem":942,
    "gn:feature_class":"P",
    "gn:feature_code":"PPL",
    "gn:name":"Manek\u00e9",
    "gn:population":0,
    "gn:timezone":"Africa/Bangui",
    "iso:country":"CF",
    "wof:name":"Maneke",
    "wof:placetype":"locality"
},
  "geometry": {"coordinates":[15.92804,6.75547],"type":"Point"}
}