{
  "type": "Feature",
  "properties": {
    "gn:admin1_code":"12.0",
    "gn:admin2_code":"7732115.0",
    "gn:asciiname":"Bazien",
    "gn:country_code":"CF",
    "gn:dem":539,
    "gn:feature_class":"P",
    "gn:feature_code":"PPL",
    "gn:name":"Bazien",
    "gn:population":0,
    "gn:timezone":"Africa/Bangui",
    "iso:country":"CF",
    "name:bug_x_preferred":[
        "Bazien"
    ],
    "name:cat_x_preferred":[
        "Bazien"
    ],
    "name:ceb_x_preferred":[
        "Bazien"
    ],
    "name:deu_x_preferred":[
        "Bazien"
    ],
    "name:eus_x_preferred":[
        "Bazien"
    ],
    "name:fra_x_preferred":[
        "Bazien"
    ],
    "name:hun_x_preferred":[
        "Bazien"
    ],
    "name:ind_x_preferred":[
        "Bazien"
    ],
    "name:ita_x_preferred":[
        "Bazien"
    ],
    "name:kaz_x_preferred":[
        "\u0411\u0430\u0437\u044c\u044f\u043d"
    ],
    "name:mlg_x_preferred":[
        "Bazien"
    ],
    "name:msa_x_preferred":[
        "Bazien"
    ],
    "name:nld_x_preferred":[
        "Bazien"
    ],
    "name:oci_x_preferred":[
        "Bazien"
    ],
    "name:pol_x_preferred":[
        "Bazien"
    ],
    "name:slk_x_preferred":[
        "Bazien"
    ],
    "name:spa_x_preferred":[
        "Bazien"
    ],
    "name:sqi_x_preferred":[
        "Bazien"
    ],
    "name:srp_x_preferred":[
        "\u0411\u0430\u0437\u0458\u0435\u043d"
    ],
    "name:swe_x_preferred":[
        "Bazien"
    ],
    "name:ukr_x_preferred":[
        "\u0411\u0430\u0437\u044c\u044f\u043d"
    ],
    "name:uzb_x_preferred":[
        "Bazien"
    ],
    "name:vie_x_preferred":[
        "Bazien"
    ],
    "name:vol_x_preferred":[
        "Bazien"
    ],
    "name:war_x_preferred":[
        "Bazien"
    ],
    "name:zho_x_preferred":[
        "\u5df4\u9f50\u5b89"
    ],
    "wof:name":"Bazien",
    "wof:placetype":"locality"
},
  "geometry": {"coordinates":[17.15,6.48333],"type":"Point"}
}