{
  "type": "Feature",
  "properties": {
    "gn:admin1_code":"12.0",
    "gn:admin2_code":"9143480.0",
    "gn:asciiname":"Bofara",
    "gn:country_code":"CF",
    "gn:dem":548,
    "gn:feature_class":"P",
    "gn:feature_code":"PPL",
    "gn:name":"Bofara",
    "gn:population":0,
    "gn:timezone":"Africa/Bangui",
    "iso:country":"CF",
    "wof:name":"Bofara",
    "wof:placetype":"locality"
},
  "geometry": {"coordinates":[17.38332999999999,6.81165],"type":"Point"}
}