{
  "type": "Feature",
  "properties": {
    "gn:admin1_code":"0.0",
    "gn:asciiname":"Deng",
    "gn:country_code":"CF",
    "gn:dem":911,
    "gn:feature_class":"P",
    "gn:feature_code":"PPL",
    "gn:name":"Deng",
    "gn:population":0,
    "gn:timezone":"Africa/Bangui",
    "iso:country":"CF",
    "name:ceb_x_preferred":[
        "Deng"
    ],
    "name:ces_x_preferred":[
        "Deng"
    ],
    "name:deu_x_preferred":[
        "Deng"
    ],
    "name:fra_x_preferred":[
        "Deng"
    ],
    "name:kur_x_preferred":[
        "Deng"
    ],
    "name:pol_x_preferred":[
        "Deng"
    ],
    "name:por_x_preferred":[
        "Deng"
    ],
    "name:rus_x_preferred":[
        "\u0414\u0435\u043d\u0433"
    ],
    "name:spa_x_preferred":[
        "Deng"
    ],
    "name:swe_x_preferred":[
        "Deng"
    ],
    "wof:name":"Deng",
    "wof:placetype":"locality"
},
  "geometry": {"coordinates":[15.81667,7.45],"type":"Point"}
}