{
  "type": "Feature",
  "properties": {
    "gn:admin1_code":"06",
    "gn:admin2_code":"7731894.0",
    "gn:asciiname":"Bouasse-Karaota",
    "gn:country_code":"CF",
    "gn:dem":386,
    "gn:feature_class":"P",
    "gn:feature_code":"PPL",
    "gn:name":"Bouass\u00e9-Karaota",
    "gn:population":0,
    "gn:timezone":"Africa/Bangui",
    "iso:country":"CF",
    "wof:name":"Bouasse-Karaota",
    "wof:placetype":"locality"
},
  "geometry": {"coordinates":[19.49735,5.18924],"type":"Point"}
}