{
  "type": "Feature",
  "properties": {
    "gn:admin1_code":"13.0",
    "gn:admin2_code":"9143494.0",
    "gn:asciiname":"Souris",
    "gn:country_code":"CF",
    "gn:dem":727,
    "gn:feature_class":"P",
    "gn:feature_code":"PPL",
    "gn:name":"Souris",
    "gn:population":0,
    "gn:timezone":"Africa/Bangui",
    "iso:country":"CF",
    "name:ceb_x_preferred":[
        "Souris"
    ],
    "name:deu_x_preferred":[
        "Souris"
    ],
    "name:fra_x_preferred":[
        "Souris"
    ],
    "name:ita_x_preferred":[
        "Souris"
    ],
    "name:nld_x_preferred":[
        "Souris"
    ],
    "name:oci_x_preferred":[
        "Mirga"
    ],
    "name:pol_x_preferred":[
        "Souris"
    ],
    "name:rus_x_preferred":[
        "\u0421\u0443\u0440\u0438\u0441"
    ],
    "name:spa_x_preferred":[
        "Souris"
    ],
    "name:srp_x_preferred":[
        "\u0421\u0443\u0440\u0438\u0441"
    ],
    "name:swe_x_preferred":[
        "Souris"
    ],
    "wof:name":"Souris",
    "wof:placetype":"locality"
},
  "geometry": {"coordinates":[16.1366,7.08101],"type":"Point"}
}