{
  "type": "Feature",
  "properties": {
    "gn:admin1_code":"1.0",
    "gn:admin2_code":"9143460.0",
    "gn:asciiname":"Ngoudjaka",
    "gn:country_code":"CF",
    "gn:dem":633,
    "gn:feature_class":"P",
    "gn:feature_code":"PPL",
    "gn:name":"Ngoudjaka",
    "gn:population":0,
    "gn:timezone":"Africa/Bangui",
    "iso:country":"CF",
    "wof:name":"Ngoudjaka",
    "wof:placetype":"locality"
},
  "geometry": {"coordinates":[20.69691,8.36866],"type":"Point"}
}