{
  "type": "Feature",
  "properties": {
    "gn:admin1_code":"17.0",
    "gn:admin2_code":"7732723.0",
    "gn:asciiname":"Bokoin",
    "gn:country_code":"CF",
    "gn:dem":704,
    "gn:feature_class":"P",
    "gn:feature_code":"PPL",
    "gn:name":"Bokoin",
    "gn:population":0,
    "gn:timezone":"Africa/Bangui",
    "iso:country":"CF",
    "name:und_x_variant":[
        "Bogoin"
    ],
    "wof:name":"Bokoin",
    "wof:placetype":"locality"
},
  "geometry": {"coordinates":[17.76916,5.14256],"type":"Point"}
}