{
  "type": "Feature",
  "properties": {
    "gn:admin1_code":"16.0",
    "gn:admin2_code":"7731904.0",
    "gn:asciiname":"Tondo",
    "gn:country_code":"CF",
    "gn:dem":645,
    "gn:feature_class":"P",
    "gn:feature_code":"PPL",
    "gn:name":"Tondo",
    "gn:population":0,
    "gn:timezone":"Africa/Bangui",
    "iso:country":"CF",
    "name:ceb_x_preferred":[
        "Tondo"
    ],
    "name:deu_x_preferred":[
        "Tondo"
    ],
    "name:fra_x_preferred":[
        "Tondo"
    ],
    "name:ita_x_preferred":[
        "Tondo"
    ],
    "name:nld_x_preferred":[
        "Tondo"
    ],
    "name:nor_x_preferred":[
        "Tondo"
    ],
    "name:rus_x_preferred":[
        "\u0422\u043e\u043d\u0434\u043e"
    ],
    "name:sco_x_preferred":[
        "Tondo"
    ],
    "name:spa_x_preferred":[
        "Tondo"
    ],
    "name:swe_x_preferred":[
        "Tondo"
    ],
    "name:tgl_x_preferred":[
        "Tondo"
    ],
    "wof:name":"Tondo",
    "wof:placetype":"locality"
},
  "geometry": {"coordinates":[15.67232,3.40513],"type":"Point"}
}