{
  "type": "Feature",
  "properties": {
    "gn:admin1_code":"7.0",
    "gn:admin2_code":"9143487.0",
    "gn:asciiname":"Bouento",
    "gn:country_code":"CF",
    "gn:dem":570,
    "gn:feature_class":"P",
    "gn:feature_code":"PPL",
    "gn:name":"Bouento",
    "gn:population":0,
    "gn:timezone":"Africa/Bangui",
    "iso:country":"CF",
    "wof:name":"Bouento",
    "wof:placetype":"locality"
},
  "geometry": {"coordinates":[17.12203,4.35186],"type":"Point"}
}