{
  "type": "Feature",
  "properties": {
    "gn:admin1_code":"16.0",
    "gn:admin2_code":"7731904.0",
    "gn:asciiname":"Ngoulo",
    "gn:country_code":"CF",
    "gn:dem":620,
    "gn:feature_class":"P",
    "gn:feature_code":"PPL",
    "gn:name":"Ngoulo",
    "gn:population":0,
    "gn:timezone":"Africa/Bangui",
    "iso:country":"CF",
    "name:und_x_variant":[
        "Ngoul\u00e9",
        "Ngoulo"
    ],
    "wof:name":"Ngoulo",
    "wof:placetype":"locality"
},
  "geometry": {"coordinates":[16.17067999999999,3.48131],"type":"Point"}
}