{
  "type": "Feature",
  "properties": {
    "gn:admin1_code":"4.0",
    "gn:admin2_code":"7732917.0",
    "gn:asciiname":"Yoro",
    "gn:country_code":"CF",
    "gn:dem":676,
    "gn:feature_class":"P",
    "gn:feature_code":"PPL",
    "gn:name":"Yoro",
    "gn:population":0,
    "gn:timezone":"Africa/Bangui",
    "iso:country":"CF",
    "name:ceb_x_preferred":[
        "Yoro"
    ],
    "name:fra_x_preferred":[
        "Yoro"
    ],
    "name:ita_x_preferred":[
        "Yoro"
    ],
    "name:kor_x_preferred":[
        "\uc694\ub85c"
    ],
    "name:lit_x_preferred":[
        "Joras"
    ],
    "name:mar_x_preferred":[
        "\u092f\u094b\u0930\u094b"
    ],
    "name:nld_x_preferred":[
        "Yoro"
    ],
    "name:pol_x_preferred":[
        "Yoro"
    ],
    "name:por_x_preferred":[
        "Yoro"
    ],
    "name:que_x_preferred":[
        "Yoro"
    ],
    "name:rus_x_preferred":[
        "\u0419\u043e\u0440\u043e"
    ],
    "name:spa_x_preferred":[
        "Yoro"
    ],
    "name:swe_x_preferred":[
        "Yoro"
    ],
    "name:ukr_x_preferred":[
        "\u0419\u043e\u0440\u043e"
    ],
    "name:urd_x_preferred":[
        "\u06cc\u0648\u0631\u0648"
    ],
    "name:war_x_preferred":[
        "Yoro"
    ],
    "wof:name":"Yoro",
    "wof:placetype":"locality"
},
  "geometry": {"coordinates":[16.65128,5.18488],"type":"Point"}
}