{
  "type": "Feature",
  "properties": {
    "gn:admin1_code":"3.0",
    "gn:admin2_code":"9143465.0",
    "gn:asciiname":"Ndagra",
    "gn:country_code":"CF",
    "gn:dem":590,
    "gn:feature_class":"P",
    "gn:feature_code":"PPL",
    "gn:name":"Ndagra",
    "gn:population":0,
    "gn:timezone":"Africa/Bangui",
    "iso:country":"CF",
    "wof:name":"Ndagra",
    "wof:placetype":"locality"
},
  "geometry": {"coordinates":[21.99307,6.56514],"type":"Point"}
}