{
  "type": "Feature",
  "properties": {
    "gn:admin1_code":"4.0",
    "gn:admin2_code":"9143488.0",
    "gn:asciiname":"Banban",
    "gn:country_code":"CF",
    "gn:dem":606,
    "gn:feature_class":"P",
    "gn:feature_code":"PPL",
    "gn:name":"Banban",
    "gn:population":0,
    "gn:timezone":"Africa/Bangui",
    "iso:country":"CF",
    "name:und_x_variant":[
        "Bamban",
        "Banban"
    ],
    "wof:name":"Banban",
    "wof:placetype":"locality"
},
  "geometry": {"coordinates":[15.32849,3.77514],"type":"Point"}
}