{
  "type": "Feature",
  "properties": {
    "gn:admin1_code":"9.0",
    "gn:admin2_code":"7732085.0",
    "gn:asciiname":"Dongue Yoyo",
    "gn:country_code":"CF",
    "gn:dem":1088,
    "gn:feature_class":"P",
    "gn:feature_code":"PPL",
    "gn:name":"Dongu\u00e9 Yoyo",
    "gn:population":0,
    "gn:timezone":"Africa/Bangui",
    "iso:country":"CF",
    "wof:name":"Dongue Yoyo",
    "wof:placetype":"locality"
},
  "geometry": {"coordinates":[15.55648,6.08551],"type":"Point"}
}