{
  "type": "Feature",
  "properties": {
    "gn:admin1_code":"8.0",
    "gn:admin2_code":"7732690.0",
    "gn:asciiname":"Ndete",
    "gn:country_code":"CF",
    "gn:dem":690,
    "gn:feature_class":"P",
    "gn:feature_code":"PPL",
    "gn:name":"Nd\u00e9t\u00e9",
    "gn:population":0,
    "gn:timezone":"Africa/Bangui",
    "iso:country":"CF",
    "name:und_x_variant":[
        "Ndett\u00e9",
        "Nd\u00e9t\u00e9"
    ],
    "wof:name":"Ndete",
    "wof:placetype":"locality"
},
  "geometry": {"coordinates":[22.68983,5.71691],"type":"Point"}
}