{
  "type": "Feature",
  "properties": {
    "gn:admin1_code":"17.0",
    "gn:admin2_code":"7732372.0",
    "gn:asciiname":"Bokede III",
    "gn:country_code":"CF",
    "gn:dem":693,
    "gn:feature_class":"P",
    "gn:feature_code":"PPL",
    "gn:name":"Bok\u00e9d\u00e9 III",
    "gn:population":0,
    "gn:timezone":"Africa/Bangui",
    "iso:country":"CF",
    "name:und_x_variant":[
        "Bok\u00e9d\u00e9 III",
        "Bok\u00e9d\u00e9"
    ],
    "wof:name":"Bokede III",
    "wof:placetype":"locality"
},
  "geometry": {"coordinates":[17.13332,5.16669],"type":"Point"}
}