{
  "type": "Feature",
  "properties": {
    "gn:admin1_code":"13.0",
    "gn:admin2_code":"8299286.0",
    "gn:asciiname":"Zonbie",
    "gn:country_code":"CF",
    "gn:dem":884,
    "gn:feature_class":"P",
    "gn:feature_code":"PPL",
    "gn:name":"Zonbi\u00e9",
    "gn:population":0,
    "gn:timezone":"Africa/Bangui",
    "iso:country":"CF",
    "wof:name":"Zonbie",
    "wof:placetype":"locality"
},
  "geometry": {"coordinates":[16.01602,6.40974],"type":"Point"}
}