{
  "type": "Feature",
  "properties": {
    "gn:admin1_code":"12.0",
    "gn:admin2_code":"9143472.0",
    "gn:asciiname":"Kadi",
    "gn:country_code":"CF",
    "gn:dem":448,
    "gn:feature_class":"P",
    "gn:feature_code":"PPL",
    "gn:name":"Kadi",
    "gn:population":0,
    "gn:timezone":"Africa/Bangui",
    "iso:country":"CF",
    "name:ceb_x_preferred":[
        "Kadi"
    ],
    "name:ces_x_preferred":[
        "Kadi"
    ],
    "name:deu_x_preferred":[
        "Kadi"
    ],
    "name:fas_x_preferred":[
        "\u0642\u0627\u0636\u06cc"
    ],
    "name:fra_x_preferred":[
        "Kadi"
    ],
    "name:ita_x_preferred":[
        "Kadi"
    ],
    "name:nld_x_preferred":[
        "Kadi"
    ],
    "name:rus_x_preferred":[
        "\u041a\u0430\u0434\u0438"
    ],
    "name:swe_x_preferred":[
        "Kadi"
    ],
    "wof:name":"Kadi",
    "wof:placetype":"locality"
},
  "geometry": {"coordinates":[18.35299,7.09109],"type":"Point"}
}