{
  "type": "Feature",
  "properties": {
    "gn:admin1_code":"12.0",
    "gn:admin2_code":"9143472.0",
    "gn:asciiname":"Kadi",
    "gn:country_code":"CF",
    "gn:dem":448,
    "gn:feature_class":"P",
    "gn:feature_code":"PPL",
    "gn:name":"Kadi",
    "gn:population":0,
    "gn:timezone":"Africa/Bangui",
    "iso:country":"CF",
    "wof:name":"Kadi",
    "wof:placetype":"locality"
},
  "geometry": {"coordinates":[18.35299,7.09109],"type":"Point"}
}