{
  "type": "Feature",
  "properties": {
    "gn:admin1_code":"5.0",
    "gn:admin2_code":"9143462.0",
    "gn:asciiname":"Koumbare",
    "gn:country_code":"CF",
    "gn:dem":606,
    "gn:feature_class":"P",
    "gn:feature_code":"PPL",
    "gn:name":"Koumbar\u00e9",
    "gn:population":0,
    "gn:timezone":"Africa/Bangui",
    "iso:country":"CF",
    "wof:name":"Koumbare",
    "wof:placetype":"locality"
},
  "geometry": {"coordinates":[25.3353,6.04923],"type":"Point"}
}