{
  "type": "Feature",
  "properties": {
    "gn:admin1_code":"06",
    "gn:admin2_code":"7732483.0",
    "gn:asciiname":"Tatakpain II",
    "gn:country_code":"CF",
    "gn:dem":495,
    "gn:feature_class":"P",
    "gn:feature_code":"PPL",
    "gn:name":"Tatakpain II",
    "gn:population":0,
    "gn:timezone":"Africa/Bangui",
    "iso:country":"CF",
    "wof:name":"Tatakpain II",
    "wof:placetype":"locality"
},
  "geometry": {"coordinates":[19.11914,5.80428],"type":"Point"}
}