{
  "type": "Feature",
  "properties": {
    "gn:admin1_code":"13",
    "gn:admin2_code":"9143494.0",
    "gn:asciiname":"Boaze",
    "gn:country_code":"CF",
    "gn:dem":432,
    "gn:feature_class":"P",
    "gn:feature_code":"PPL",
    "gn:name":"Boaz\u00e9",
    "gn:population":0,
    "gn:timezone":"Africa/Bangui",
    "iso:country":"CF",
    "wof:name":"Boaze",
    "wof:placetype":"locality"
},
  "geometry": {"coordinates":[16.37293,7.6666],"type":"Point"}
}