{
  "type": "Feature",
  "properties": {
    "gn:admin1_code":"4.0",
    "gn:admin2_code":"9143489.0",
    "gn:asciiname":"Nakombo Sangha",
    "gn:country_code":"CF",
    "gn:dem":473,
    "gn:feature_class":"P",
    "gn:feature_code":"PPL",
    "gn:name":"Nakombo Sangha",
    "gn:population":0,
    "gn:timezone":"Africa/Bangui",
    "iso:country":"CF",
    "wof:name":"Nakombo Sangha",
    "wof:placetype":"locality"
},
  "geometry": {"coordinates":[15.6626,3.78981],"type":"Point"}
}