{
  "type": "Feature",
  "properties": {
    "gn:admin1_code":"16.0",
    "gn:admin2_code":"7731904.0",
    "gn:asciiname":"Walpandji",
    "gn:country_code":"CF",
    "gn:dem":605,
    "gn:feature_class":"P",
    "gn:feature_code":"PPL",
    "gn:name":"Walpandji",
    "gn:population":0,
    "gn:timezone":"Africa/Bangui",
    "iso:country":"CF",
    "wof:name":"Walpandji",
    "wof:placetype":"locality"
},
  "geometry": {"coordinates":[16.18639,3.39535],"type":"Point"}
}