{
  "type": "Feature",
  "properties": {
    "gn:admin1_code":"3.0",
    "gn:admin2_code":"9143465.0",
    "gn:asciiname":"Koubou",
    "gn:country_code":"CF",
    "gn:dem":722,
    "gn:feature_class":"P",
    "gn:feature_code":"PPL",
    "gn:name":"Koubou",
    "gn:population":0,
    "gn:timezone":"Africa/Bangui",
    "iso:country":"CF",
    "wof:name":"Koubou",
    "wof:placetype":"locality"
},
  "geometry": {"coordinates":[21.81667,6.51667],"type":"Point"}
}