{
  "type": "Feature",
  "properties": {
    "gn:admin1_code":"13",
    "gn:admin2_code":"9143493.0",
    "gn:asciiname":"Man",
    "gn:country_code":"CF",
    "gn:dem":1032,
    "gn:feature_class":"P",
    "gn:feature_code":"PPL",
    "gn:name":"Man",
    "gn:population":0,
    "gn:timezone":"Africa/Bangui",
    "iso:country":"CF",
    "wof:name":"Man",
    "wof:placetype":"locality"
},
  "geometry": {"coordinates":[15.76064,7.34516],"type":"Point"}
}