{
  "type": "Feature",
  "properties": {
    "gn:admin1_code":"6.0",
    "gn:admin2_code":"7731894.0",
    "gn:asciiname":"Ouondoro",
    "gn:country_code":"CF",
    "gn:dem":415,
    "gn:feature_class":"P",
    "gn:feature_code":"PPL",
    "gn:name":"Ouondoro",
    "gn:population":0,
    "gn:timezone":"Africa/Bangui",
    "iso:country":"CF",
    "name:und_x_variant":[
        "Ouand\u00e9ro",
        "Oundao",
        "Ouondoro"
    ],
    "wof:name":"Ouondoro",
    "wof:placetype":"locality"
},
  "geometry": {"coordinates":[19.08245,5.67552],"type":"Point"}
}