{
  "type": "Feature",
  "properties": {
    "gn:admin1_code":"12.0",
    "gn:admin2_code":"9143477.0",
    "gn:asciiname":"Bandamandjia",
    "gn:country_code":"CF",
    "gn:dem":475,
    "gn:feature_class":"P",
    "gn:feature_code":"PPL",
    "gn:name":"Bandamandjia",
    "gn:population":0,
    "gn:timezone":"Africa/Bangui",
    "iso:country":"CF",
    "wof:name":"Bandamandjia",
    "wof:placetype":"locality"
},
  "geometry": {"coordinates":[18.30627,6.46038],"type":"Point"}
}