{
  "type": "Feature",
  "properties": {
    "gn:admin1_code":"2.0",
    "gn:admin2_code":"7731892.0",
    "gn:asciiname":"Mbeleba",
    "gn:country_code":"CF",
    "gn:dem":425,
    "gn:feature_class":"P",
    "gn:feature_code":"PPL",
    "gn:name":"Mb\u00e9l\u00e9ba",
    "gn:population":0,
    "gn:timezone":"Africa/Bangui",
    "iso:country":"CF",
    "wof:name":"Mbeleba",
    "wof:placetype":"locality"
},
  "geometry": {"coordinates":[20.91667,4.55],"type":"Point"}
}