{
  "type": "Feature",
  "properties": {
    "gn:admin1_code":"17.0",
    "gn:admin2_code":"7732723.0",
    "gn:asciiname":"Gadey",
    "gn:country_code":"CF",
    "gn:dem":686,
    "gn:feature_class":"P",
    "gn:feature_code":"PPL",
    "gn:name":"Gadey",
    "gn:population":0,
    "gn:timezone":"Africa/Bangui",
    "iso:country":"CF",
    "wof:name":"Gadey",
    "wof:placetype":"locality"
},
  "geometry": {"coordinates":[17.55,5.13333],"type":"Point"}
}