{
  "type": "Feature",
  "properties": {
    "gn:admin1_code":"2.0",
    "gn:admin2_code":"7731891.0",
    "gn:asciiname":"Kolobo",
    "gn:country_code":"CF",
    "gn:dem":409,
    "gn:feature_class":"P",
    "gn:feature_code":"PPL",
    "gn:name":"Kolobo",
    "gn:population":0,
    "gn:timezone":"Africa/Bangui",
    "iso:country":"CF",
    "wof:name":"Kolobo",
    "wof:placetype":"locality"
},
  "geometry": {"coordinates":[21.1552,4.35943],"type":"Point"}
}