{
  "type": "Feature",
  "properties": {
    "gn:admin1_code":"7.0",
    "gn:admin2_code":"7732068.0",
    "gn:asciiname":"Boundara",
    "gn:country_code":"CF",
    "gn:dem":381,
    "gn:feature_class":"P",
    "gn:feature_code":"PPL",
    "gn:name":"Boundara",
    "gn:population":0,
    "gn:timezone":"Africa/Bangui",
    "iso:country":"CF",
    "name:nld_x_preferred":[
        "Boundara"
    ],
    "wof:name":"Boundara",
    "wof:placetype":"locality"
},
  "geometry": {"coordinates":[18.18981,3.93638],"type":"Point"}
}