{
  "type": "Feature",
  "properties": {
    "gn:admin1_code":"06",
    "gn:admin2_code":"7731894.0",
    "gn:asciiname":"Hengue",
    "gn:country_code":"CF",
    "gn:dem":384,
    "gn:feature_class":"P",
    "gn:feature_code":"PPL",
    "gn:name":"H\u00e8ngu\u00e9",
    "gn:population":0,
    "gn:timezone":"Africa/Bangui",
    "iso:country":"CF",
    "wof:name":"Hengue",
    "wof:placetype":"locality"
},
  "geometry": {"coordinates":[19.5303,5.22796],"type":"Point"}
}