{
  "type": "Feature",
  "properties": {
    "gn:admin1_code":"9.0",
    "gn:admin2_code":"2390511.0",
    "gn:asciiname":"Zoukombo",
    "gn:country_code":"CF",
    "gn:dem":1030,
    "gn:feature_class":"P",
    "gn:feature_code":"PPL",
    "gn:name":"Zoukombo",
    "gn:population":0,
    "gn:timezone":"Africa/Bangui",
    "iso:country":"CF",
    "name:und_x_variant":[
        "Soukambo",
        "Soukombo",
        "Zoukombo"
    ],
    "wof:name":"Zoukombo",
    "wof:placetype":"locality"
},
  "geometry": {"coordinates":[14.68433,5.83608],"type":"Point"}
}