{
  "type": "Feature",
  "properties": {
    "gn:admin1_code":"13.0",
    "gn:admin2_code":"9143493.0",
    "gn:asciiname":"Koussaye",
    "gn:country_code":"CF",
    "gn:dem":990,
    "gn:feature_class":"P",
    "gn:feature_code":"PPL",
    "gn:name":"Koussaye",
    "gn:population":0,
    "gn:timezone":"Africa/Bangui",
    "iso:country":"CF",
    "name:und_x_variant":[
        "Kounsay",
        "Koussaye"
    ],
    "wof:name":"Koussaye",
    "wof:placetype":"locality"
},
  "geometry": {"coordinates":[15.69435,7.38485],"type":"Point"}
}