{
  "type": "Feature",
  "properties": {
    "gn:admin1_code":"4.0",
    "gn:admin2_code":"7732917.0",
    "gn:asciiname":"Limbo",
    "gn:country_code":"CF",
    "gn:dem":709,
    "gn:feature_class":"P",
    "gn:feature_code":"PPL",
    "gn:name":"Limbo",
    "gn:population":0,
    "gn:timezone":"Africa/Bangui",
    "iso:country":"CF",
    "wof:name":"Limbo",
    "wof:placetype":"locality"
},
  "geometry": {"coordinates":[16.16351,5.04255],"type":"Point"}
}