{
  "type": "Feature",
  "properties": {
    "gn:admin1_code":"11.0",
    "gn:admin2_code":"7732062.0",
    "gn:asciiname":"Andjitolakri",
    "gn:country_code":"CF",
    "gn:dem":560,
    "gn:feature_class":"P",
    "gn:feature_code":"PPL",
    "gn:name":"Andjitolakri",
    "gn:population":0,
    "gn:timezone":"Africa/Bangui",
    "iso:country":"CF",
    "wof:name":"Andjitolakri",
    "wof:placetype":"locality"
},
  "geometry": {"coordinates":[21.33569,5.82785],"type":"Point"}
}