{
  "type": "Feature",
  "properties": {
    "gn:admin1_code":"9.0",
    "gn:admin2_code":"2390511.0",
    "gn:asciiname":"Besson",
    "gn:country_code":"CF",
    "gn:dem":1045,
    "gn:feature_class":"P",
    "gn:feature_code":"PPL",
    "gn:name":"Besson",
    "gn:population":0,
    "gn:timezone":"Africa/Bangui",
    "iso:country":"CF",
    "name:bel_x_preferred":[
        "\u0411\u0435\u0441\u043e\u043d"
    ],
    "name:cat_x_preferred":[
        "Besson"
    ],
    "name:deu_x_preferred":[
        "Besson"
    ],
    "name:fra_x_preferred":[
        "Besson"
    ],
    "name:ita_x_preferred":[
        "Besson"
    ],
    "name:jpn_x_preferred":[
        "\u30d9\u30c3\u30bd\u30f3"
    ],
    "name:nds_x_preferred":[
        "Besson"
    ],
    "name:nld_x_preferred":[
        "Besson"
    ],
    "name:rus_x_preferred":[
        "\u0411\u0435\u0441\u0441\u043e\u043d"
    ],
    "name:sqi_x_preferred":[
        "Besson"
    ],
    "name:srp_x_preferred":[
        "\u0411\u0435\u0441\u043e\u043d"
    ],
    "name:swe_x_preferred":[
        "Besson"
    ],
    "wof:name":"Besson",
    "wof:placetype":"locality"
},
  "geometry": {"coordinates":[14.82921,6.25197],"type":"Point"}
}