{
  "type": "Feature",
  "properties": {
    "gn:admin1_code":"9.0",
    "gn:admin2_code":"2390511.0",
    "gn:asciiname":"Besson",
    "gn:country_code":"CF",
    "gn:dem":1045,
    "gn:feature_class":"P",
    "gn:feature_code":"PPL",
    "gn:name":"Besson",
    "gn:population":0,
    "gn:timezone":"Africa/Bangui",
    "iso:country":"CF",
    "wof:name":"Besson",
    "wof:placetype":"locality"
},
  "geometry": {"coordinates":[14.82921,6.25197],"type":"Point"}
}