{
  "type": "Feature",
  "properties": {
    "gn:admin1_code":"13",
    "gn:admin2_code":"9143493.0",
    "gn:asciiname":"Kole",
    "gn:country_code":"CF",
    "gn:dem":622,
    "gn:feature_class":"P",
    "gn:feature_code":"PPL",
    "gn:name":"Kol\u00e9",
    "gn:population":0,
    "gn:timezone":"Africa/Bangui",
    "iso:country":"CF",
    "wof:name":"Kole",
    "wof:placetype":"locality"
},
  "geometry": {"coordinates":[15.53751,7.46848],"type":"Point"}
}