{
  "type": "Feature",
  "properties": {
    "gn:admin1_code":"8.0",
    "gn:admin2_code":"7731889.0",
    "gn:asciiname":"Kaounga",
    "gn:country_code":"CF",
    "gn:dem":595,
    "gn:feature_class":"P",
    "gn:feature_code":"PPL",
    "gn:name":"Kaounga",
    "gn:population":0,
    "gn:timezone":"Africa/Bangui",
    "iso:country":"CF",
    "wof:name":"Kaounga",
    "wof:placetype":"locality"
},
  "geometry": {"coordinates":[21.95,4.61667],"type":"Point"}
}