{
  "type": "Feature",
  "properties": {
    "gn:admin1_code":"6.0",
    "gn:admin2_code":"9143484.0",
    "gn:asciiname":"Malibingui",
    "gn:country_code":"CF",
    "gn:dem":494,
    "gn:feature_class":"P",
    "gn:feature_code":"PPL",
    "gn:name":"Malibingui",
    "gn:population":0,
    "gn:timezone":"Africa/Bangui",
    "iso:country":"CF",
    "wof:name":"Malibingui",
    "wof:placetype":"locality"
},
  "geometry": {"coordinates":[19.41667,6.18333],"type":"Point"}
}