{
  "type": "Feature",
  "properties": {
    "gn:admin1_code":"7.0",
    "gn:admin2_code":"7732068.0",
    "gn:asciiname":"Bogaye",
    "gn:country_code":"CF",
    "gn:dem":600,
    "gn:feature_class":"P",
    "gn:feature_code":"PPL",
    "gn:name":"Bogaye",
    "gn:population":0,
    "gn:timezone":"Africa/Bangui",
    "iso:country":"CF",
    "wof:name":"Bogaye",
    "wof:placetype":"locality"
},
  "geometry": {"coordinates":[17.82427999999999,4.04079],"type":"Point"}
}