{
  "type": "Feature",
  "properties": {
    "gn:admin1_code":"12.0",
    "gn:admin2_code":"9143481.0",
    "gn:asciiname":"Bokote Sese",
    "gn:country_code":"CF",
    "gn:dem":574,
    "gn:feature_class":"P",
    "gn:feature_code":"PPL",
    "gn:name":"Bokot\u00e9 Ses\u00e9",
    "gn:population":0,
    "gn:timezone":"Africa/Bangui",
    "iso:country":"CF",
    "wof:name":"Bokote Sese",
    "wof:placetype":"locality"
},
  "geometry": {"coordinates":[16.71244,6.96547],"type":"Point"}
}