{
  "type": "Feature",
  "properties": {
    "gn:admin1_code":"12.0",
    "gn:admin2_code":"7732115.0",
    "gn:asciiname":"Zoro",
    "gn:country_code":"CF",
    "gn:dem":516,
    "gn:feature_class":"P",
    "gn:feature_code":"PPL",
    "gn:name":"Zoro",
    "gn:population":0,
    "gn:timezone":"Africa/Bangui",
    "iso:country":"CF",
    "name:ceb_x_preferred":[
        "Zoro"
    ],
    "name:fin_x_preferred":[
        "Zoro"
    ],
    "name:ita_x_preferred":[
        "Zoro"
    ],
    "name:swe_x_preferred":[
        "Zoro"
    ],
    "name:tgl_x_preferred":[
        "Zoro"
    ],
    "wof:name":"Zoro",
    "wof:placetype":"locality"
},
  "geometry": {"coordinates":[17.66677,6.77641],"type":"Point"}
}