{
  "type": "Feature",
  "properties": {
    "gn:admin1_code":"12.0",
    "gn:admin2_code":"9143481.0",
    "gn:asciiname":"Boumbaye",
    "gn:country_code":"CF",
    "gn:dem":542,
    "gn:feature_class":"P",
    "gn:feature_code":"PPL",
    "gn:name":"Boumbaye",
    "gn:population":0,
    "gn:timezone":"Africa/Bangui",
    "iso:country":"CF",
    "wof:name":"Boumbaye",
    "wof:placetype":"locality"
},
  "geometry": {"coordinates":[16.97289,7.22375],"type":"Point"}
}