{
  "type": "Feature",
  "properties": {
    "gn:admin1_code":"9.0",
    "gn:admin2_code":"9143482.0",
    "gn:asciiname":"Boyombo",
    "gn:country_code":"CF",
    "gn:dem":796,
    "gn:feature_class":"P",
    "gn:feature_code":"PPL",
    "gn:name":"Boyombo",
    "gn:population":0,
    "gn:timezone":"Africa/Bangui",
    "iso:country":"CF",
    "wof:name":"Boyombo",
    "wof:placetype":"locality"
},
  "geometry": {"coordinates":[15.56775,5.13073],"type":"Point"}
}