{
  "type": "Feature",
  "properties": {
    "gn:admin1_code":"12.0",
    "gn:admin2_code":"9143477.0",
    "gn:asciiname":"Bongone",
    "gn:country_code":"CF",
    "gn:dem":427,
    "gn:feature_class":"P",
    "gn:feature_code":"PPL",
    "gn:name":"Bongone",
    "gn:population":0,
    "gn:timezone":"Africa/Bangui",
    "iso:country":"CF",
    "wof:name":"Bongone",
    "wof:placetype":"locality"
},
  "geometry": {"coordinates":[17.88332999999999,6.78333],"type":"Point"}
}