{
  "type": "Feature",
  "properties": {
    "gn:admin1_code":"4.0",
    "gn:admin2_code":"2387494.0",
    "gn:asciiname":"Camp Bo-Niama",
    "gn:country_code":"CF",
    "gn:dem":656,
    "gn:feature_class":"P",
    "gn:feature_code":"PPL",
    "gn:name":"Camp Bo-Niama",
    "gn:population":0,
    "gn:timezone":"Africa/Bangui",
    "iso:country":"CF",
    "wof:name":"Camp Bo-Niama",
    "wof:placetype":"locality"
},
  "geometry": {"coordinates":[16.48333,4.65],"type":"Point"}
}