{
  "type": "Feature",
  "properties": {
    "gn:admin1_code":"12.0",
    "gn:admin2_code":"7732115.0",
    "gn:asciiname":"Zere",
    "gn:country_code":"CF",
    "gn:dem":473,
    "gn:feature_class":"P",
    "gn:feature_code":"PPL",
    "gn:name":"Zere",
    "gn:population":0,
    "gn:timezone":"Africa/Bangui",
    "iso:country":"CF",
    "wof:name":"Zere",
    "wof:placetype":"locality"
},
  "geometry": {"coordinates":[17.67771,6.44398],"type":"Point"}
}