{
  "type": "Feature",
  "properties": {
    "gn:admin1_code":"01",
    "gn:admin2_code":"9143460.0",
    "gn:asciiname":"Kasena",
    "gn:country_code":"CF",
    "gn:dem":429,
    "gn:feature_class":"P",
    "gn:feature_code":"PPL",
    "gn:name":"Kas\u00e8na",
    "gn:population":0,
    "gn:timezone":"Africa/Bangui",
    "iso:country":"CF",
    "name:fra_x_preferred":[
        "Kas\u00e8na"
    ],
    "wof:name":"Kasena",
    "wof:placetype":"locality"
},
  "geometry": {"coordinates":[21.2464,9.10433],"type":"Point"}
}