{
  "type": "Feature",
  "properties": {
    "gn:admin1_code":"12.0",
    "gn:admin2_code":"9143480.0",
    "gn:asciiname":"Konre",
    "gn:country_code":"CF",
    "gn:dem":426,
    "gn:feature_class":"P",
    "gn:feature_code":"PPL",
    "gn:name":"Konr\u00e9",
    "gn:population":0,
    "gn:timezone":"Africa/Bangui",
    "iso:country":"CF",
    "wof:name":"Konre",
    "wof:placetype":"locality"
},
  "geometry": {"coordinates":[17.35,7.16667],"type":"Point"}
}