{
  "type": "Feature",
  "properties": {
    "gn:admin1_code":"11.0",
    "gn:admin2_code":"7732067.0",
    "gn:asciiname":"Angora",
    "gn:country_code":"CF",
    "gn:dem":660,
    "gn:feature_class":"P",
    "gn:feature_code":"PPL",
    "gn:name":"Angora",
    "gn:population":0,
    "gn:timezone":"Africa/Bangui",
    "iso:country":"CF",
    "wof:name":"Angora",
    "wof:placetype":"locality"
},
  "geometry": {"coordinates":[20.85,6.23333],"type":"Point"}
}