{
  "type": "Feature",
  "properties": {
    "gn:admin1_code":"11.0",
    "gn:admin2_code":"7732067.0",
    "gn:asciiname":"Angora",
    "gn:country_code":"CF",
    "gn:dem":660,
    "gn:feature_class":"P",
    "gn:feature_code":"PPL",
    "gn:name":"Angora",
    "gn:population":0,
    "gn:timezone":"Africa/Bangui",
    "iso:country":"CF",
    "name:bos_x_preferred":[
        "Angora"
    ],
    "name:cat_x_preferred":[
        "Angora"
    ],
    "name:ceb_x_preferred":[
        "Angora"
    ],
    "name:dan_x_preferred":[
        "Angora"
    ],
    "name:deu_x_preferred":[
        "Angora"
    ],
    "name:eus_x_preferred":[
        "Angora"
    ],
    "name:fra_x_preferred":[
        "Angora"
    ],
    "name:hun_x_preferred":[
        "Angora"
    ],
    "name:ina_x_preferred":[
        "Angora"
    ],
    "name:ita_x_preferred":[
        "Angora"
    ],
    "name:jpn_x_preferred":[
        "\u30a2\u30f3\u30b4\u30e9"
    ],
    "name:kor_x_preferred":[
        "\uc559\uace0\ub77c"
    ],
    "name:nld_x_preferred":[
        "Angora"
    ],
    "name:pol_x_preferred":[
        "Angora"
    ],
    "name:por_x_preferred":[
        "Angor\u00e1"
    ],
    "name:ron_x_preferred":[
        "Angora"
    ],
    "name:rus_x_preferred":[
        "\u0410\u043d\u0433\u043e\u0440\u0430"
    ],
    "name:sco_x_preferred":[
        "Angora"
    ],
    "name:spa_x_preferred":[
        "Angora"
    ],
    "name:swe_x_preferred":[
        "Angora"
    ],
    "name:tur_x_preferred":[
        "Angora"
    ],
    "name:ukr_x_preferred":[
        "\u0410\u043d\u0433\u043e\u0440\u0430"
    ],
    "wof:name":"Angora",
    "wof:placetype":"locality"
},
  "geometry": {"coordinates":[20.85,6.23333],"type":"Point"}
}