{
  "type": "Feature",
  "properties": {
    "gn:admin1_code":"16.0",
    "gn:admin2_code":"9143473.0",
    "gn:asciiname":"Danza",
    "gn:country_code":"CF",
    "gn:dem":541,
    "gn:feature_class":"P",
    "gn:feature_code":"PPL",
    "gn:name":"Danza",
    "gn:population":0,
    "gn:timezone":"Africa/Bangui",
    "iso:country":"CF",
    "name:nld_x_preferred":[
        "Danza"
    ],
    "name:rus_x_preferred":[
        "\u0414\u0430\u043d\u0441\u0430"
    ],
    "name:ukr_x_preferred":[
        "\u0414\u0430\u043d\u0437\u0430"
    ],
    "wof:name":"Danza",
    "wof:placetype":"locality"
},
  "geometry": {"coordinates":[16.80529,3.65605],"type":"Point"}
}