{
  "type": "Feature",
  "properties": {
    "gn:admin1_code":"11.0",
    "gn:admin2_code":"7731893.0",
    "gn:asciiname":"Pierlat",
    "gn:country_code":"CF",
    "gn:dem":402,
    "gn:feature_class":"P",
    "gn:feature_code":"PPL",
    "gn:name":"Pierlat",
    "gn:population":0,
    "gn:timezone":"Africa/Bangui",
    "iso:country":"CF",
    "name:und_x_variant":[
        "Pierla",
        "Pierlat"
    ],
    "wof:name":"Pierlat",
    "wof:placetype":"locality"
},
  "geometry": {"coordinates":[20.14232,5.14241],"type":"Point"}
}