{
  "type": "Feature",
  "properties": {
    "gn:admin1_code":"11.0",
    "gn:admin2_code":"7732062.0",
    "gn:asciiname":"Dongo",
    "gn:country_code":"CF",
    "gn:dem":461,
    "gn:feature_class":"P",
    "gn:feature_code":"PPL",
    "gn:name":"Dongo",
    "gn:population":0,
    "gn:timezone":"Africa/Bangui",
    "iso:country":"CF",
    "name:ceb_x_preferred":[
        "Dongo"
    ],
    "name:deu_x_preferred":[
        "Dongo"
    ],
    "name:epo_x_preferred":[
        "Dongo"
    ],
    "name:fra_x_preferred":[
        "Dongo"
    ],
    "name:ita_x_preferred":[
        "Dongo"
    ],
    "name:nld_x_preferred":[
        "Dongo"
    ],
    "name:rus_x_preferred":[
        "\u0414\u043e\u043d\u0433\u043e"
    ],
    "name:swe_x_preferred":[
        "Dongo"
    ],
    "wof:name":"Dongo",
    "wof:placetype":"locality"
},
  "geometry": {"coordinates":[20.68333,5.76667],"type":"Point"}
}