{
  "type": "Feature",
  "properties": {
    "gn:admin1_code":"12.0",
    "gn:admin2_code":"7732115.0",
    "gn:asciiname":"Dollo",
    "gn:country_code":"CF",
    "gn:dem":570,
    "gn:feature_class":"P",
    "gn:feature_code":"PPL",
    "gn:name":"Dollo",
    "gn:population":0,
    "gn:timezone":"Africa/Bangui",
    "iso:country":"CF",
    "wof:name":"Dollo",
    "wof:placetype":"locality"
},
  "geometry": {"coordinates":[17.01237,6.7192],"type":"Point"}
}