{
  "type": "Feature",
  "properties": {
    "gn:admin1_code":"12.0",
    "gn:admin2_code":"9143479.0",
    "gn:asciiname":"Bati",
    "gn:country_code":"CF",
    "gn:dem":432,
    "gn:feature_class":"P",
    "gn:feature_code":"PPL",
    "gn:name":"Bati",
    "gn:population":0,
    "gn:timezone":"Africa/Bangui",
    "iso:country":"CF",
    "name:ceb_x_preferred":[
        "Bati"
    ],
    "name:deu_x_preferred":[
        "Bati"
    ],
    "name:fra_x_preferred":[
        "Bati"
    ],
    "name:srp_x_preferred":[
        "\u0411\u0430\u0442\u0438"
    ],
    "name:swe_x_preferred":[
        "Bati"
    ],
    "wof:name":"Bati",
    "wof:placetype":"locality"
},
  "geometry": {"coordinates":[17.16667,7.66667],"type":"Point"}
}