{
  "type": "Feature",
  "properties": {
    "gn:admin1_code":"5.0",
    "gn:admin2_code":"9143462.0",
    "gn:asciiname":"Ourou",
    "gn:country_code":"CF",
    "gn:dem":650,
    "gn:feature_class":"P",
    "gn:feature_code":"PPL",
    "gn:name":"Ourou",
    "gn:population":0,
    "gn:timezone":"Africa/Bangui",
    "iso:country":"CF",
    "wof:name":"Ourou",
    "wof:placetype":"locality"
},
  "geometry": {"coordinates":[25.35197,6.04099],"type":"Point"}
}