{
  "type": "Feature",
  "properties": {
    "gn:admin1_code":"11.0",
    "gn:admin2_code":"7732062.0",
    "gn:asciiname":"Kouzoukoumbou",
    "gn:country_code":"CF",
    "gn:dem":582,
    "gn:feature_class":"P",
    "gn:feature_code":"PPL",
    "gn:name":"Kouzoukoumbou",
    "gn:population":0,
    "gn:timezone":"Africa/Bangui",
    "iso:country":"CF",
    "wof:name":"Kouzoukoumbou",
    "wof:placetype":"locality"
},
  "geometry": {"coordinates":[21.16596,5.93904],"type":"Point"}
}