{
  "type": "Feature",
  "properties": {
    "gn:admin1_code":"2.0",
    "gn:admin2_code":"7731890.0",
    "gn:asciiname":"Dabe",
    "gn:country_code":"CF",
    "gn:dem":463,
    "gn:feature_class":"P",
    "gn:feature_code":"PPL",
    "gn:name":"Dab\u00e9",
    "gn:population":0,
    "gn:timezone":"Africa/Bangui",
    "iso:country":"CF",
    "wof:name":"Dabe",
    "wof:placetype":"locality"
},
  "geometry": {"coordinates":[21.56667,4.48333],"type":"Point"}
}