{
  "type": "Feature",
  "properties": {
    "gn:admin1_code":"4.0",
    "gn:admin2_code":"9143488.0",
    "gn:asciiname":"Lengou",
    "gn:country_code":"CF",
    "gn:dem":582,
    "gn:feature_class":"P",
    "gn:feature_code":"PPL",
    "gn:name":"Lengou",
    "gn:population":0,
    "gn:timezone":"Africa/Bangui",
    "iso:country":"CF",
    "wof:name":"Lengou",
    "wof:placetype":"locality"
},
  "geometry": {"coordinates":[15.34183,3.89372],"type":"Point"}
}