{
  "type": "Feature",
  "properties": {
    "gn:admin1_code":"09",
    "gn:admin2_code":"2390511.0",
    "gn:asciiname":"Bagari",
    "gn:country_code":"CF",
    "gn:dem":931,
    "gn:feature_class":"P",
    "gn:feature_code":"PPL",
    "gn:name":"Bagari",
    "gn:population":0,
    "gn:timezone":"Africa/Bangui",
    "iso:country":"CF",
    "name:und_x_variant":[
        "Bagali-Bouar",
        "Bagari"
    ],
    "wof:name":"Bagari",
    "wof:placetype":"locality"
},
  "geometry": {"coordinates":[14.77238,5.21091],"type":"Point"}
}