{
  "type": "Feature",
  "properties": {
    "gn:admin1_code":"9.0",
    "gn:admin2_code":"7732103.0",
    "gn:asciiname":"Zaromadjia",
    "gn:country_code":"CF",
    "gn:dem":557,
    "gn:feature_class":"P",
    "gn:feature_code":"PPL",
    "gn:name":"Zaromadjia",
    "gn:population":0,
    "gn:timezone":"Africa/Bangui",
    "iso:country":"CF",
    "wof:name":"Zaromadjia",
    "wof:placetype":"locality"
},
  "geometry": {"coordinates":[15.85041,5.09496],"type":"Point"}
}