{
  "type": "Feature",
  "properties": {
    "gn:admin1_code":"4.0",
    "gn:admin2_code":"7732917.0",
    "gn:asciiname":"Boubaboro Boupane",
    "gn:country_code":"CF",
    "gn:dem":600,
    "gn:feature_class":"P",
    "gn:feature_code":"PPL",
    "gn:name":"Boubaboro Boupane",
    "gn:population":0,
    "gn:timezone":"Africa/Bangui",
    "iso:country":"CF",
    "wof:name":"Boubaboro Boupane",
    "wof:placetype":"locality"
},
  "geometry": {"coordinates":[16.83333,4.98333],"type":"Point"}
}