{
  "type": "Feature",
  "properties": {
    "gn:admin1_code":"8.0",
    "gn:admin2_code":"7732690.0",
    "gn:asciiname":"Badali",
    "gn:country_code":"CF",
    "gn:dem":492,
    "gn:feature_class":"P",
    "gn:feature_code":"PPL",
    "gn:name":"Badali",
    "gn:population":0,
    "gn:timezone":"Africa/Bangui",
    "iso:country":"CF",
    "name:azb_x_preferred":[
        "\u0628\u062f\u0644\u06cc(\u0628\u0647\u0628\u0647\u0627\u0646)"
    ],
    "name:ceb_x_preferred":[
        "Badal\u012b"
    ],
    "name:fas_x_preferred":[
        "\u0628\u062f\u0644\u06cc"
    ],
    "name:swe_x_preferred":[
        "Badal\u012b"
    ],
    "wof:name":"Badali",
    "wof:placetype":"locality"
},
  "geometry": {"coordinates":[22.87135,4.89943],"type":"Point"}
}