{
  "type": "Feature",
  "properties": {
    "gn:admin1_code":"11.0",
    "gn:admin2_code":"7732062.0",
    "gn:asciiname":"Zamahou",
    "gn:country_code":"CF",
    "gn:dem":580,
    "gn:feature_class":"P",
    "gn:feature_code":"PPL",
    "gn:name":"Zamahou",
    "gn:population":0,
    "gn:timezone":"Africa/Bangui",
    "iso:country":"CF",
    "wof:name":"Zamahou",
    "wof:placetype":"locality"
},
  "geometry": {"coordinates":[21.12626,5.8983],"type":"Point"}
}