{
  "type": "Feature",
  "properties": {
    "gn:admin1_code":"2.0",
    "gn:admin2_code":"7731892.0",
    "gn:asciiname":"Mbala",
    "gn:country_code":"CF",
    "gn:dem":429,
    "gn:feature_class":"P",
    "gn:feature_code":"PPL",
    "gn:name":"Mbala",
    "gn:population":0,
    "gn:timezone":"Africa/Bangui",
    "iso:country":"CF",
    "name:ben_x_preferred":[
        "\u098f\u09ae\u09ac\u09be\u09b2\u09be"
    ],
    "name:ceb_x_preferred":[
        "Mbala"
    ],
    "name:ell_x_preferred":[
        "\u039c\u03c0\u03ac\u03bb\u03b1"
    ],
    "name:fas_x_preferred":[
        "\u0627\u0645\u0628\u0627\u0644\u0627"
    ],
    "name:fra_x_preferred":[
        "Mbala"
    ],
    "name:heb_x_preferred":[
        "\u05de\u05d1\u05dc\u05d4"
    ],
    "name:hin_x_preferred":[
        "\u092e\u094d\u092c\u093e\u0932\u093e"
    ],
    "name:hun_x_preferred":[
        "Mbala"
    ],
    "name:ind_x_preferred":[
        "Mbala"
    ],
    "name:kor_x_preferred":[
        "\uc74c\ubc1c\ub77c"
    ],
    "name:swe_x_preferred":[
        "Mbala"
    ],
    "name:tur_x_preferred":[
        "Mbala"
    ],
    "name:ukr_x_preferred":[
        "\u041c\u0431\u0430\u043b\u0430"
    ],
    "name:urd_x_preferred":[
        "\u0627\u06cc\u0645\u0628\u0627\u0644\u0627"
    ],
    "name:vie_x_preferred":[
        "Mbala"
    ],
    "wof:name":"Mbala",
    "wof:placetype":"locality"
},
  "geometry": {"coordinates":[20.66992,4.55256],"type":"Point"}
}