{
  "type": "Feature",
  "properties": {
    "gn:admin1_code":"9.0",
    "gn:admin2_code":"2390511.0",
    "gn:asciiname":"Garba",
    "gn:country_code":"CF",
    "gn:dem":955,
    "gn:feature_class":"P",
    "gn:feature_code":"PPL",
    "gn:name":"Garba",
    "gn:population":0,
    "gn:timezone":"Africa/Bangui",
    "iso:country":"CF",
    "name:ceb_x_preferred":[
        "Garba"
    ],
    "name:deu_x_preferred":[
        "Garba"
    ],
    "name:fra_x_preferred":[
        "Garba"
    ],
    "name:swe_x_preferred":[
        "Garba"
    ],
    "name:ukr_x_preferred":[
        "\u0413\u0430\u0440\u0431\u0430"
    ],
    "wof:name":"Garba",
    "wof:placetype":"locality"
},
  "geometry": {"coordinates":[14.72543,5.44632],"type":"Point"}
}