{
  "type": "Feature",
  "properties": {
    "gn:admin1_code":"4.0",
    "gn:admin2_code":"2387494.0",
    "gn:asciiname":"Boko-Boutane",
    "gn:country_code":"CF",
    "gn:dem":629,
    "gn:feature_class":"P",
    "gn:feature_code":"PPL",
    "gn:name":"Boko-Boutane",
    "gn:population":0,
    "gn:timezone":"Africa/Bangui",
    "iso:country":"CF",
    "name:und_x_variant":[
        "Boutane",
        "Boko-Boutane"
    ],
    "wof:name":"Boko-Boutane",
    "wof:placetype":"locality"
},
  "geometry": {"coordinates":[15.82749,4.79459],"type":"Point"}
}