{
  "type": "Feature",
  "properties": {
    "gn:admin1_code":"12.0",
    "gn:admin2_code":"9143478.0",
    "gn:asciiname":"Bogama I",
    "gn:country_code":"CF",
    "gn:dem":449,
    "gn:feature_class":"P",
    "gn:feature_code":"PPL",
    "gn:name":"Bogama I",
    "gn:population":0,
    "gn:timezone":"Africa/Bangui",
    "iso:country":"CF",
    "wof:name":"Bogama I",
    "wof:placetype":"locality"
},
  "geometry": {"coordinates":[18.72621,7.25506],"type":"Point"}
}