{
  "type": "Feature",
  "properties": {
    "gn:admin1_code":"4.0",
    "gn:admin2_code":"7732916.0",
    "gn:asciiname":"Noufou",
    "gn:country_code":"CF",
    "gn:dem":672,
    "gn:feature_class":"P",
    "gn:feature_code":"PPL",
    "gn:name":"Noufou",
    "gn:population":0,
    "gn:timezone":"Africa/Bangui",
    "iso:country":"CF",
    "wof:name":"Noufou",
    "wof:placetype":"locality"
},
  "geometry": {"coordinates":[14.79104,4.58572],"type":"Point"}
}