{
  "type": "Feature",
  "properties": {
    "gn:admin1_code":"4.0",
    "gn:admin2_code":"7732685.0",
    "gn:asciiname":"Go",
    "gn:country_code":"CF",
    "gn:dem":438,
    "gn:feature_class":"P",
    "gn:feature_code":"PPL",
    "gn:name":"G\u00f4",
    "gn:population":0,
    "gn:timezone":"Africa/Bangui",
    "iso:country":"CF",
    "name:dan_x_preferred":[
        "Go"
    ],
    "name:est_x_preferred":[
        "Go"
    ],
    "name:fin_x_preferred":[
        "Go"
    ],
    "name:hun_x_preferred":[
        "Go"
    ],
    "name:pol_x_preferred":[
        "Go"
    ],
    "name:rus_x_preferred":[
        "\u0413\u043e"
    ],
    "name:spa_x_preferred":[
        "Go"
    ],
    "name:tur_x_preferred":[
        "Go"
    ],
    "wof:name":"Go",
    "wof:placetype":"locality"
},
  "geometry": {"coordinates":[16.17154,4.38621],"type":"Point"}
}