{
  "type": "Feature",
  "properties": {
    "gn:admin1_code":"16.0",
    "gn:admin2_code":"9143473.0",
    "gn:asciiname":"Domo",
    "gn:country_code":"CF",
    "gn:dem":503,
    "gn:feature_class":"P",
    "gn:feature_code":"PPL",
    "gn:name":"Domo",
    "gn:population":0,
    "gn:timezone":"Africa/Bangui",
    "iso:country":"CF",
    "name:ceb_x_preferred":[
        "Domo"
    ],
    "name:ita_x_preferred":[
        "Domo"
    ],
    "name:nld_x_preferred":[
        "Domo"
    ],
    "name:por_x_preferred":[
        "Domo"
    ],
    "name:spa_x_preferred":[
        "Domo"
    ],
    "name:srp_x_preferred":[
        "Domo"
    ],
    "name:swe_x_preferred":[
        "Domo"
    ],
    "wof:name":"Domo",
    "wof:placetype":"locality"
},
  "geometry": {"coordinates":[16.8884,3.98901],"type":"Point"}
}