{
  "type": "Feature",
  "properties": {
    "gn:admin1_code":"7.0",
    "gn:admin2_code":"7731898.0",
    "gn:asciiname":"Mongangou",
    "gn:country_code":"CF",
    "gn:dem":368,
    "gn:feature_class":"P",
    "gn:feature_code":"PPL",
    "gn:name":"Mongangou",
    "gn:population":0,
    "gn:timezone":"Africa/Bangui",
    "iso:country":"CF",
    "wof:name":"Mongangou",
    "wof:placetype":"locality"
},
  "geometry": {"coordinates":[18.59766,3.5737],"type":"Point"}
}