{
  "type": "Feature",
  "properties": {
    "gn:admin1_code":"17.0",
    "gn:admin2_code":"9143490.0",
    "gn:asciiname":"Bousse Kana",
    "gn:cc2":"CF",
    "gn:country_code":"CF",
    "gn:dem":530,
    "gn:feature_class":"P",
    "gn:feature_code":"PPL",
    "gn:name":"Bouss\u00e9 Kana",
    "gn:population":0,
    "gn:timezone":"Africa/Bangui",
    "iso:country":"CF",
    "name:und_x_variant":[
        "Bagoro",
        "Bossakala",
        "Bosakala",
        "Bouss\u00e9 Kana"
    ],
    "wof:name":"Bousse Kana",
    "wof:placetype":"locality"
},
  "geometry": {"coordinates":[18.06667,5.31667],"type":"Point"}
}