{
  "type": "Feature",
  "properties": {
    "gn:admin1_code":"06",
    "gn:admin2_code":"7732483.0",
    "gn:asciiname":"Kaougouta",
    "gn:country_code":"CF",
    "gn:dem":561,
    "gn:feature_class":"P",
    "gn:feature_code":"PPL",
    "gn:name":"Kaougouta",
    "gn:population":0,
    "gn:timezone":"Africa/Bangui",
    "iso:country":"CF",
    "wof:name":"Kaougouta",
    "wof:placetype":"locality"
},
  "geometry": {"coordinates":[19.15306,5.89405],"type":"Point"}
}