{
  "type": "Feature",
  "properties": {
    "gn:admin1_code":"8.0",
    "gn:admin2_code":"7731889.0",
    "gn:asciiname":"Ngounga",
    "gn:country_code":"CF",
    "gn:dem":527,
    "gn:feature_class":"P",
    "gn:feature_code":"PPL",
    "gn:name":"Ngounga",
    "gn:population":0,
    "gn:timezone":"Africa/Bangui",
    "iso:country":"CF",
    "name:und_x_variant":[
        "Ndounga",
        "Ngounga"
    ],
    "wof:name":"Ngounga",
    "wof:placetype":"locality"
},
  "geometry": {"coordinates":[22.38011,4.62963],"type":"Point"}
}