{
  "type": "Feature",
  "properties": {
    "gn:admin1_code":"7.0",
    "gn:admin2_code":"7732068.0",
    "gn:asciiname":"Boteke",
    "gn:country_code":"CF",
    "gn:dem":381,
    "gn:feature_class":"P",
    "gn:feature_code":"PPL",
    "gn:name":"Boteke",
    "gn:population":0,
    "gn:timezone":"Africa/Bangui",
    "iso:country":"CF",
    "wof:name":"Boteke",
    "wof:placetype":"locality"
},
  "geometry": {"coordinates":[18.05,3.63333],"type":"Point"}
}