{
  "type": "Feature",
  "properties": {
    "gn:admin1_code":"13.0",
    "gn:admin2_code":"9143483.0",
    "gn:asciiname":"Bamboro II",
    "gn:country_code":"CF",
    "gn:dem":768,
    "gn:feature_class":"P",
    "gn:feature_code":"PPL",
    "gn:name":"Bamboro II",
    "gn:population":0,
    "gn:timezone":"Africa/Bangui",
    "iso:country":"CF",
    "wof:name":"Bamboro II",
    "wof:placetype":"locality"
},
  "geometry": {"coordinates":[16.21703,6.06818],"type":"Point"}
}