{
  "type": "Feature",
  "properties": {
    "gn:admin1_code":"4.0",
    "gn:admin2_code":"9143488.0",
    "gn:asciiname":"Bandiforo",
    "gn:country_code":"CF",
    "gn:dem":593,
    "gn:feature_class":"P",
    "gn:feature_code":"PPL",
    "gn:name":"Bandiforo",
    "gn:population":0,
    "gn:timezone":"Africa/Bangui",
    "iso:country":"CF",
    "name:und_x_variant":[
        "Bandziforo",
        "Bondiforo",
        "Bandiforo"
    ],
    "wof:name":"Bandiforo",
    "wof:placetype":"locality"
},
  "geometry": {"coordinates":[15.15803,4.03624],"type":"Point"}
}