{
  "type": "Feature",
  "properties": {
    "gn:admin1_code":"2.0",
    "gn:admin2_code":"7731891.0",
    "gn:asciiname":"Songo",
    "gn:country_code":"CF",
    "gn:dem":520,
    "gn:feature_class":"P",
    "gn:feature_code":"PPL",
    "gn:name":"Songo",
    "gn:population":0,
    "gn:timezone":"Africa/Bangui",
    "iso:country":"CF",
    "name:ceb_x_preferred":[
        "Songo"
    ],
    "name:deu_x_preferred":[
        "Songo"
    ],
    "name:fra_x_preferred":[
        "Songo"
    ],
    "name:por_x_preferred":[
        "Songo"
    ],
    "name:swe_x_preferred":[
        "Songo"
    ],
    "wof:name":"Songo",
    "wof:placetype":"locality"
},
  "geometry": {"coordinates":[21.25935,4.51183],"type":"Point"}
}