{
  "type": "Feature",
  "properties": {
    "gn:admin1_code":"13.0",
    "gn:admin2_code":"8299286.0",
    "gn:asciiname":"Voudou III",
    "gn:country_code":"CF",
    "gn:dem":665,
    "gn:feature_class":"P",
    "gn:feature_code":"PPL",
    "gn:name":"Voudou III",
    "gn:population":0,
    "gn:timezone":"Africa/Bangui",
    "iso:country":"CF",
    "wof:name":"Voudou III",
    "wof:placetype":"locality"
},
  "geometry": {"coordinates":[16.70165,6.27974],"type":"Point"}
}