{
  "type": "Feature",
  "properties": {
    "gn:admin1_code":"11.0",
    "gn:admin2_code":"7731893.0",
    "gn:asciiname":"Dacpa",
    "gn:country_code":"CF",
    "gn:dem":532,
    "gn:feature_class":"P",
    "gn:feature_code":"PPL",
    "gn:name":"Dacpa",
    "gn:population":0,
    "gn:timezone":"Africa/Bangui",
    "iso:country":"CF",
    "wof:name":"Dacpa",
    "wof:placetype":"locality"
},
  "geometry": {"coordinates":[20.71667,5.13333],"type":"Point"}
}