{
  "type": "Feature",
  "properties": {
    "gn:admin1_code":"12.0",
    "gn:admin2_code":"9143478.0",
    "gn:asciiname":"Molo",
    "gn:country_code":"CF",
    "gn:dem":386,
    "gn:feature_class":"P",
    "gn:feature_code":"PPL",
    "gn:name":"Molo",
    "gn:population":0,
    "gn:timezone":"Africa/Bangui",
    "iso:country":"CF",
    "wof:name":"Molo",
    "wof:placetype":"locality"
},
  "geometry": {"coordinates":[18.95994,8.35916],"type":"Point"}
}