{
  "type": "Feature",
  "properties": {
    "gn:admin1_code":"11.0",
    "gn:admin2_code":"7732062.0",
    "gn:asciiname":"Tromondji",
    "gn:country_code":"CF",
    "gn:dem":445,
    "gn:feature_class":"P",
    "gn:feature_code":"PPL",
    "gn:name":"Tromondji",
    "gn:population":0,
    "gn:timezone":"Africa/Bangui",
    "iso:country":"CF",
    "wof:name":"Tromondji",
    "wof:placetype":"locality"
},
  "geometry": {"coordinates":[20.70695,5.66626],"type":"Point"}
}