{
  "type": "Feature",
  "properties": {
    "gn:admin1_code":"09",
    "gn:admin2_code":"2390511.0",
    "gn:asciiname":"Ardo",
    "gn:country_code":"CF",
    "gn:dem":1115,
    "gn:feature_class":"P",
    "gn:feature_code":"PPL",
    "gn:name":"Ardo",
    "gn:population":0,
    "gn:timezone":"Africa/Bangui",
    "iso:country":"CF",
    "wof:name":"Ardo",
    "wof:placetype":"locality"
},
  "geometry": {"coordinates":[14.82436,6.27237],"type":"Point"}
}