{
  "type": "Feature",
  "properties": {
    "gn:admin1_code":"13.0",
    "gn:admin2_code":"9143494.0",
    "gn:asciiname":"Yene",
    "gn:country_code":"CF",
    "gn:dem":442,
    "gn:feature_class":"P",
    "gn:feature_code":"PPL",
    "gn:name":"Yen\u00e9",
    "gn:population":0,
    "gn:timezone":"Africa/Bangui",
    "iso:country":"CF",
    "wof:name":"Yene",
    "wof:placetype":"locality"
},
  "geometry": {"coordinates":[16.503,7.78507],"type":"Point"}
}