{
  "type": "Feature",
  "properties": {
    "gn:admin1_code":"17",
    "gn:admin2_code":"7731895.0",
    "gn:asciiname":"Vangue II",
    "gn:country_code":"CF",
    "gn:dem":410,
    "gn:feature_class":"P",
    "gn:feature_code":"PPL",
    "gn:name":"Vangu\u00e9 II",
    "gn:population":0,
    "gn:timezone":"Africa/Bangui",
    "iso:country":"CF",
    "name:und_x_variant":[
        "Vangu\u00e9 II",
        "Vangu\u00e9"
    ],
    "wof:name":"Vangue II",
    "wof:placetype":"locality"
},
  "geometry": {"coordinates":[18.82002,5.07898],"type":"Point"}
}