{
  "type": "Feature",
  "properties": {
    "gn:admin1_code":"3.0",
    "gn:admin2_code":"9143465.0",
    "gn:asciiname":"Komangue",
    "gn:country_code":"CF",
    "gn:dem":626,
    "gn:feature_class":"P",
    "gn:feature_code":"PPL",
    "gn:name":"Komangu\u00e9",
    "gn:population":0,
    "gn:timezone":"Africa/Bangui",
    "iso:country":"CF",
    "wof:name":"Komangue",
    "wof:placetype":"locality"
},
  "geometry": {"coordinates":[22.23333,6.46667],"type":"Point"}
}