{
  "type": "Feature",
  "properties": {
    "gn:admin1_code":"13.0",
    "gn:admin2_code":"8299286.0",
    "gn:asciiname":"Konekare",
    "gn:country_code":"CF",
    "gn:dem":737,
    "gn:feature_class":"P",
    "gn:feature_code":"PPL",
    "gn:name":"Kon\u00e9kar\u00e9",
    "gn:population":0,
    "gn:timezone":"Africa/Bangui",
    "iso:country":"CF",
    "wof:name":"Konekare",
    "wof:placetype":"locality"
},
  "geometry": {"coordinates":[16.38939,6.55021],"type":"Point"}
}