{
  "type": "Feature",
  "properties": {
    "gn:admin1_code":"13",
    "gn:admin2_code":"9143494.0",
    "gn:asciiname":"Guila",
    "gn:country_code":"CF",
    "gn:dem":711,
    "gn:feature_class":"P",
    "gn:feature_code":"PPL",
    "gn:name":"Guila",
    "gn:population":0,
    "gn:timezone":"Africa/Bangui",
    "iso:country":"CF",
    "wof:name":"Guila",
    "wof:placetype":"locality"
},
  "geometry": {"coordinates":[16.11823,7.09474],"type":"Point"}
}