{
  "type": "Feature",
  "properties": {
    "gn:admin1_code":"17.0",
    "gn:admin2_code":"7732372.0",
    "gn:asciiname":"Bekajoute",
    "gn:country_code":"CF",
    "gn:dem":770,
    "gn:feature_class":"P",
    "gn:feature_code":"PPL",
    "gn:name":"B\u00e9kajout\u00e9",
    "gn:population":0,
    "gn:timezone":"Africa/Bangui",
    "iso:country":"CF",
    "wof:name":"Bekajoute",
    "wof:placetype":"locality"
},
  "geometry": {"coordinates":[16.77956,5.50284],"type":"Point"}
}