{
  "type": "Feature",
  "properties": {
    "gn:admin1_code":"4.0",
    "gn:admin2_code":"7732685.0",
    "gn:asciiname":"Zaoromera",
    "gn:country_code":"CF",
    "gn:dem":481,
    "gn:feature_class":"P",
    "gn:feature_code":"PPL",
    "gn:name":"Zaoromera",
    "gn:population":0,
    "gn:timezone":"Africa/Bangui",
    "iso:country":"CF",
    "wof:name":"Zaoromera",
    "wof:placetype":"locality"
},
  "geometry": {"coordinates":[16.07734,4.09382],"type":"Point"}
}