{
  "type": "Feature",
  "properties": {
    "gn:admin1_code":"2.0",
    "gn:admin2_code":"7731890.0",
    "gn:asciiname":"Melego",
    "gn:cc2":"CF",
    "gn:country_code":"CF",
    "gn:dem":463,
    "gn:feature_class":"P",
    "gn:feature_code":"PPL",
    "gn:name":"M\u00e9l\u00e9go",
    "gn:population":0,
    "gn:timezone":"Africa/Bangui",
    "iso:country":"CF",
    "name:und_x_variant":[
        "Liou",
        "M\u00e9l\u00e9go"
    ],
    "wof:name":"Melego",
    "wof:placetype":"locality"
},
  "geometry": {"coordinates":[21.46667,4.68333],"type":"Point"}
}