{
  "type": "Feature",
  "properties": {
    "gn:admin1_code":"8.0",
    "gn:admin2_code":"7731889.0",
    "gn:asciiname":"Bito",
    "gn:country_code":"CF",
    "gn:dem":402,
    "gn:feature_class":"P",
    "gn:feature_code":"PPL",
    "gn:name":"Bito",
    "gn:population":0,
    "gn:timezone":"Africa/Bangui",
    "iso:country":"CF",
    "name:und_x_variant":[
        "Bitto",
        "Bito"
    ],
    "wof:name":"Bito",
    "wof:placetype":"locality"
},
  "geometry": {"coordinates":[22.19195,4.15877],"type":"Point"}
}