{
  "type": "Feature",
  "properties": {
    "gn:admin1_code":"17",
    "gn:admin2_code":"7732723.0",
    "gn:asciiname":"Bouani",
    "gn:country_code":"CF",
    "gn:dem":687,
    "gn:feature_class":"P",
    "gn:feature_code":"PPL",
    "gn:name":"Bouani",
    "gn:population":0,
    "gn:timezone":"Africa/Bangui",
    "iso:country":"CF",
    "wof:name":"Bouani",
    "wof:placetype":"locality"
},
  "geometry": {"coordinates":[17.55707,5.12077],"type":"Point"}
}