{
  "type": "Feature",
  "properties": {
    "gn:admin1_code":"2.0",
    "gn:admin2_code":"7731891.0",
    "gn:asciiname":"Tchoko",
    "gn:country_code":"CF",
    "gn:dem":521,
    "gn:feature_class":"P",
    "gn:feature_code":"PPL",
    "gn:name":"Tchoko",
    "gn:population":0,
    "gn:timezone":"Africa/Bangui",
    "iso:country":"CF",
    "wof:name":"Tchoko",
    "wof:placetype":"locality"
},
  "geometry": {"coordinates":[21.2739,4.53982],"type":"Point"}
}