{
  "type": "Feature",
  "properties": {
    "gn:admin1_code":"9.0",
    "gn:admin2_code":"2390511.0",
    "gn:asciiname":"Gallo-Boyo",
    "gn:country_code":"CF",
    "gn:dem":682,
    "gn:feature_class":"P",
    "gn:feature_code":"PPL",
    "gn:name":"Gallo-Boyo",
    "gn:population":0,
    "gn:timezone":"Africa/Bangui",
    "iso:country":"CF",
    "name:und_x_variant":[
        "Gallo-Bouya",
        "Gallo-Boyo"
    ],
    "wof:name":"Gallo-Boyo",
    "wof:placetype":"locality"
},
  "geometry": {"coordinates":[15.17085,5.80049],"type":"Point"}
}