{
  "type": "Feature",
  "properties": {
    "gn:admin1_code":"12.0",
    "gn:admin2_code":"9143477.0",
    "gn:asciiname":"Bekofe I",
    "gn:country_code":"CF",
    "gn:dem":484,
    "gn:feature_class":"P",
    "gn:feature_code":"PPL",
    "gn:name":"B\u00e9kofe I",
    "gn:population":0,
    "gn:timezone":"Africa/Bangui",
    "iso:country":"CF",
    "wof:name":"Bekofe I",
    "wof:placetype":"locality"
},
  "geometry": {"coordinates":[18.35219,6.27543],"type":"Point"}
}