{
  "type": "Feature",
  "properties": {
    "gn:admin1_code":"11.0",
    "gn:admin2_code":"7731893.0",
    "gn:asciiname":"Mono",
    "gn:country_code":"CF",
    "gn:dem":472,
    "gn:feature_class":"P",
    "gn:feature_code":"PPL",
    "gn:name":"Mono",
    "gn:population":0,
    "gn:timezone":"Africa/Bangui",
    "iso:country":"CF",
    "name:cat_x_preferred":[
        "Mono"
    ],
    "name:ceb_x_preferred":[
        "Mono"
    ],
    "name:ces_x_preferred":[
        "Mono"
    ],
    "name:dan_x_preferred":[
        "Mono"
    ],
    "name:deu_x_preferred":[
        "Mono"
    ],
    "name:ell_x_preferred":[
        "Mono"
    ],
    "name:epo_x_preferred":[
        "Mono"
    ],
    "name:fas_x_preferred":[
        "\u0645\u0648\u0646\u0648"
    ],
    "name:fin_x_preferred":[
        "Mono"
    ],
    "name:fra_x_preferred":[
        "Mono"
    ],
    "name:glg_x_preferred":[
        "Mono"
    ],
    "name:heb_x_preferred":[
        "\u05de\u05d5\u05e0\u05d5"
    ],
    "name:hun_x_preferred":[
        "Mono"
    ],
    "name:ita_x_preferred":[
        "Mono"
    ],
    "name:kir_x_preferred":[
        "\u041c\u043e\u043d\u043e..."
    ],
    "name:nld_x_preferred":[
        "Mono"
    ],
    "name:nno_x_preferred":[
        "Mono"
    ],
    "name:nor_x_preferred":[
        "Mono"
    ],
    "name:pol_x_preferred":[
        "Mono"
    ],
    "name:por_x_preferred":[
        "Mono"
    ],
    "name:rus_x_preferred":[
        "\u041c\u043e\u043d\u043e"
    ],
    "name:slk_x_preferred":[
        "Mono"
    ],
    "name:slv_x_preferred":[
        "Mono"
    ],
    "name:spa_x_preferred":[
        "Mono"
    ],
    "name:swe_x_preferred":[
        "Mono"
    ],
    "name:tur_x_preferred":[
        "Mono"
    ],
    "name:ukr_x_preferred":[
        "Mono"
    ],
    "name:vie_x_preferred":[
        "Mono"
    ],
    "name:zho_x_preferred":[
        "Mono"
    ],
    "wof:name":"Mono",
    "wof:placetype":"locality"
},
  "geometry": {"coordinates":[20.16667,5.28333],"type":"Point"}
}