{
  "type": "Feature",
  "properties": {
    "gn:admin1_code":"15.0",
    "gn:admin2_code":"9143469.0",
    "gn:asciiname":"Kingui",
    "gn:country_code":"CF",
    "gn:dem":424,
    "gn:feature_class":"P",
    "gn:feature_code":"PPL",
    "gn:name":"Kingui",
    "gn:population":0,
    "gn:timezone":"Africa/Bangui",
    "iso:country":"CF",
    "wof:name":"Kingui",
    "wof:placetype":"locality"
},
  "geometry": {"coordinates":[19.18333,7.03333],"type":"Point"}
}