{
  "type": "Feature",
  "properties": {
    "gn:admin1_code":"13",
    "gn:admin2_code":"9143493.0",
    "gn:asciiname":"Koussi",
    "gn:country_code":"CF",
    "gn:dem":632,
    "gn:feature_class":"P",
    "gn:feature_code":"PPL",
    "gn:name":"Koussi",
    "gn:population":0,
    "gn:timezone":"Africa/Bangui",
    "iso:country":"CF",
    "wof:name":"Koussi",
    "wof:placetype":"locality"
},
  "geometry": {"coordinates":[15.61608,7.47306],"type":"Point"}
}