{
  "type": "Feature",
  "properties": {
    "gn:admin1_code":"13.0",
    "gn:admin2_code":"9143491.0",
    "gn:asciiname":"Bomango",
    "gn:country_code":"CF",
    "gn:dem":1163,
    "gn:feature_class":"P",
    "gn:feature_code":"PPL",
    "gn:name":"Bomango",
    "gn:population":0,
    "gn:timezone":"Africa/Bangui",
    "iso:country":"CF",
    "wof:name":"Bomango",
    "wof:placetype":"locality"
},
  "geometry": {"coordinates":[15.53092,6.80065],"type":"Point"}
}