{
  "type": "Feature",
  "properties": {
    "gn:admin1_code":"17.0",
    "gn:admin2_code":"7731896.0",
    "gn:asciiname":"Mongobolo",
    "gn:country_code":"CF",
    "gn:dem":354,
    "gn:feature_class":"P",
    "gn:feature_code":"PPL",
    "gn:name":"Mongobolo",
    "gn:population":0,
    "gn:timezone":"Africa/Bangui",
    "iso:country":"CF",
    "wof:name":"Mongobolo",
    "wof:placetype":"locality"
},
  "geometry": {"coordinates":[18.58333,3.88333],"type":"Point"}
}