{
  "type": "Feature",
  "properties": {
    "gn:admin1_code":"7.0",
    "gn:admin2_code":"9143467.0",
    "gn:asciiname":"Boudoy",
    "gn:country_code":"CF",
    "gn:dem":559,
    "gn:feature_class":"P",
    "gn:feature_code":"PPL",
    "gn:name":"Boudoy",
    "gn:population":0,
    "gn:timezone":"Africa/Bangui",
    "iso:country":"CF",
    "name:und_x_variant":[
        "Boundoy",
        "Boudoy"
    ],
    "wof:name":"Boudoy",
    "wof:placetype":"locality"
},
  "geometry": {"coordinates":[17.44057,4.1727],"type":"Point"}
}