{
  "type": "Feature",
  "properties": {
    "gn:admin1_code":"13.0",
    "gn:admin2_code":"9143494.0",
    "gn:asciiname":"Souma",
    "gn:country_code":"CF",
    "gn:dem":610,
    "gn:feature_class":"P",
    "gn:feature_code":"PPL",
    "gn:name":"Souma",
    "gn:population":0,
    "gn:timezone":"Africa/Bangui",
    "iso:country":"CF",
    "name:ceb_x_preferred":[
        "Souma"
    ],
    "name:fra_x_preferred":[
        "Souma"
    ],
    "name:swe_x_preferred":[
        "Souma"
    ],
    "wof:name":"Souma",
    "wof:placetype":"locality"
},
  "geometry": {"coordinates":[16.43419,7.25771],"type":"Point"}
}