{
  "type": "Feature",
  "properties": {
    "gn:admin1_code":"9.0",
    "gn:admin2_code":"7732085.0",
    "gn:asciiname":"Koursou",
    "gn:country_code":"CF",
    "gn:dem":939,
    "gn:feature_class":"P",
    "gn:feature_code":"PPL",
    "gn:name":"Koursou",
    "gn:population":0,
    "gn:timezone":"Africa/Bangui",
    "iso:country":"CF",
    "wof:name":"Koursou",
    "wof:placetype":"locality"
},
  "geometry": {"coordinates":[15.86905,5.83679],"type":"Point"}
}