{
  "type": "Feature",
  "properties": {
    "gn:admin1_code":"3.0",
    "gn:admin2_code":"9143475.0",
    "gn:asciiname":"Doungou",
    "gn:country_code":"CF",
    "gn:dem":668,
    "gn:feature_class":"P",
    "gn:feature_code":"PPL",
    "gn:name":"Doungou",
    "gn:population":0,
    "gn:timezone":"Africa/Bangui",
    "iso:country":"CF",
    "name:deu_x_preferred":[
        "Doungou"
    ],
    "name:fra_x_preferred":[
        "Doungou"
    ],
    "name:ita_x_preferred":[
        "Doungou"
    ],
    "name:msa_x_preferred":[
        "Doungou"
    ],
    "name:ron_x_preferred":[
        "Doungou"
    ],
    "name:spa_x_preferred":[
        "Doungou"
    ],
    "wof:name":"Doungou",
    "wof:placetype":"locality"
},
  "geometry": {"coordinates":[22.90449,6.44922],"type":"Point"}
}