{
  "type": "Feature",
  "properties": {
    "gn:admin1_code":"12",
    "gn:admin2_code":"9143472.0",
    "gn:asciiname":"Kada",
    "gn:country_code":"CF",
    "gn:dem":436,
    "gn:feature_class":"P",
    "gn:feature_code":"PPL",
    "gn:name":"Kada",
    "gn:population":0,
    "gn:timezone":"Africa/Bangui",
    "iso:country":"CF",
    "name:ceb_x_preferred":[
        "Kada"
    ],
    "name:deu_x_preferred":[
        "Kada"
    ],
    "name:est_x_preferred":[
        "Kada"
    ],
    "name:fra_x_preferred":[
        "Kada"
    ],
    "name:rus_x_preferred":[
        "\u041a\u0430\u0434\u0430"
    ],
    "name:swe_x_preferred":[
        "Kada"
    ],
    "wof:name":"Kada",
    "wof:placetype":"locality"
},
  "geometry": {"coordinates":[18.33841,7.32677],"type":"Point"}
}