{
  "type": "Feature",
  "properties": {
    "gn:admin1_code":"9.0",
    "gn:admin2_code":"7732103.0",
    "gn:asciiname":"Gazi",
    "gn:country_code":"CF",
    "gn:dem":800,
    "gn:feature_class":"P",
    "gn:feature_code":"PPL",
    "gn:name":"Gazi",
    "gn:population":0,
    "gn:timezone":"Africa/Bangui",
    "iso:country":"CF",
    "wof:name":"Gazi",
    "wof:placetype":"locality"
},
  "geometry": {"coordinates":[16.10931,5.62143],"type":"Point"}
}