{
  "type": "Feature",
  "properties": {
    "gn:admin1_code":"9.0",
    "gn:admin2_code":"9143482.0",
    "gn:asciiname":"Camp Zeze",
    "gn:country_code":"CF",
    "gn:dem":791,
    "gn:feature_class":"P",
    "gn:feature_code":"PPL",
    "gn:name":"Camp Z\u00e9z\u00e9",
    "gn:population":0,
    "gn:timezone":"Africa/Bangui",
    "iso:country":"CF",
    "wof:name":"Camp Zeze",
    "wof:placetype":"locality"
},
  "geometry": {"coordinates":[14.95017,5.14254],"type":"Point"}
}