{
  "type": "Feature",
  "properties": {
    "gn:admin1_code":"13.0",
    "gn:admin2_code":"9143493.0",
    "gn:asciiname":"Ndouy",
    "gn:cc2":"CF",
    "gn:country_code":"CF",
    "gn:dem":883,
    "gn:feature_class":"P",
    "gn:feature_code":"PPL",
    "gn:name":"Ndouy",
    "gn:population":0,
    "gn:timezone":"Africa/Bangui",
    "iso:country":"CF",
    "name:und_x_variant":[
        "Doui",
        "Ndouy"
    ],
    "wof:name":"Ndouy",
    "wof:placetype":"locality"
},
  "geometry": {"coordinates":[15.38333,7.25],"type":"Point"}
}