{
  "type": "Feature",
  "properties": {
    "gn:admin1_code":"5.0",
    "gn:admin2_code":"9143464.0",
    "gn:asciiname":"Barrh",
    "gn:country_code":"CF",
    "gn:dem":622,
    "gn:feature_class":"P",
    "gn:feature_code":"PPL",
    "gn:name":"Barrh",
    "gn:population":0,
    "gn:timezone":"Africa/Bangui",
    "iso:country":"CF",
    "wof:name":"Barrh",
    "wof:placetype":"locality"
},
  "geometry": {"coordinates":[24.88333,5.25],"type":"Point"}
}