{
  "type": "Feature",
  "properties": {
    "gn:admin1_code":"17",
    "gn:admin2_code":"7731896.0",
    "gn:asciiname":"Zimba",
    "gn:country_code":"CF",
    "gn:dem":344,
    "gn:feature_class":"P",
    "gn:feature_code":"PPL",
    "gn:name":"Zimba",
    "gn:population":0,
    "gn:timezone":"Africa/Bangui",
    "iso:country":"CF",
    "name:ceb_x_preferred":[
        "Zimba"
    ],
    "name:deu_x_preferred":[
        "Zimba"
    ],
    "name:fra_x_preferred":[
        "Zimba"
    ],
    "name:swe_x_preferred":[
        "Zimba"
    ],
    "wof:name":"Zimba",
    "wof:placetype":"locality"
},
  "geometry": {"coordinates":[18.61985,4.12269],"type":"Point"}
}