{
  "type": "Feature",
  "properties": {
    "gn:admin1_code":"17.0",
    "gn:admin2_code":"7732723.0",
    "gn:asciiname":"Bosegbien II",
    "gn:country_code":"CF",
    "gn:dem":602,
    "gn:feature_class":"P",
    "gn:feature_code":"PPL",
    "gn:name":"Bosegbien II",
    "gn:population":0,
    "gn:timezone":"Africa/Bangui",
    "iso:country":"CF",
    "name:und_x_variant":[
        "Bossogbien"
    ],
    "wof:name":"Bosegbien II",
    "wof:placetype":"locality"
},
  "geometry": {"coordinates":[17.60142,5.69132],"type":"Point"}
}