{
  "type": "Feature",
  "properties": {
    "gn:admin1_code":"12.0",
    "gn:admin2_code":"9143479.0",
    "gn:asciiname":"Kakambia",
    "gn:country_code":"CF",
    "gn:dem":475,
    "gn:feature_class":"P",
    "gn:feature_code":"PPL",
    "gn:name":"Kakambia",
    "gn:population":0,
    "gn:timezone":"Africa/Bangui",
    "iso:country":"CF",
    "name:und_x_variant":[
        "Cacamba",
        "Kakambia"
    ],
    "wof:name":"Kakambia",
    "wof:placetype":"locality"
},
  "geometry": {"coordinates":[17.04038,7.36479],"type":"Point"}
}