{
  "type": "Feature",
  "properties": {
    "gn:admin1_code":"16.0",
    "gn:admin2_code":"9143473.0",
    "gn:asciiname":"Senago",
    "gn:country_code":"CF",
    "gn:dem":570,
    "gn:feature_class":"P",
    "gn:feature_code":"PPL",
    "gn:name":"S\u00e9nago",
    "gn:population":0,
    "gn:timezone":"Africa/Bangui",
    "iso:country":"CF",
    "name:azb_x_preferred":[
        "\u0633\u0646\u0627\u0642\u0648"
    ],
    "name:bar_x_preferred":[
        "Senago"
    ],
    "name:bul_x_preferred":[
        "\u0421\u0435\u043d\u0430\u0433\u043e"
    ],
    "name:cat_x_preferred":[
        "Senago"
    ],
    "name:ceb_x_preferred":[
        "Senago"
    ],
    "name:deu_x_preferred":[
        "Senago"
    ],
    "name:epo_x_preferred":[
        "Senago"
    ],
    "name:eus_x_preferred":[
        "Senago"
    ],
    "name:fas_x_preferred":[
        "\u0633\u0646\u0627\u06af\u0648"
    ],
    "name:fra_x_preferred":[
        "Senago"
    ],
    "name:hun_x_preferred":[
        "Senago"
    ],
    "name:hye_x_preferred":[
        "\u054d\u0565\u0576\u0561\u0563\u0578"
    ],
    "name:ita_x_preferred":[
        "Senago"
    ],
    "name:jpn_x_preferred":[
        "\u30bb\u30ca\u30fc\u30b4"
    ],
    "name:kaz_x_preferred":[
        "\u0421\u0435\u043d\u0430\u0433\u043e"
    ],
    "name:lat_x_preferred":[
        "Senagum"
    ],
    "name:lmo_x_preferred":[
        "Senagh"
    ],
    "name:msa_x_preferred":[
        "Senago"
    ],
    "name:nap_x_preferred":[
        "Senago"
    ],
    "name:nld_x_preferred":[
        "Senago"
    ],
    "name:pms_x_preferred":[
        "Senago"
    ],
    "name:pol_x_preferred":[
        "Senago"
    ],
    "name:por_x_preferred":[
        "Senago"
    ],
    "name:ron_x_preferred":[
        "Senago"
    ],
    "name:rus_x_preferred":[
        "\u0421\u0435\u043d\u0430\u0433\u043e"
    ],
    "name:scn_x_preferred":[
        "Senago"
    ],
    "name:sco_x_preferred":[
        "Senago"
    ],
    "name:spa_x_preferred":[
        "Senago"
    ],
    "name:srp_x_preferred":[
        "\u0421\u0435\u043d\u0430\u0433\u043e"
    ],
    "name:tgl_x_preferred":[
        "Senago"
    ],
    "name:ukr_x_preferred":[
        "\u0421\u0435\u043d\u0430\u0433\u043e"
    ],
    "name:uzb_x_preferred":[
        "Senago"
    ],
    "name:vie_x_preferred":[
        "Senago"
    ],
    "name:vol_x_preferred":[
        "Senago"
    ],
    "name:war_x_preferred":[
        "Senago"
    ],
    "name:zho_x_preferred":[
        "\u585e\u7eb3\u6208"
    ],
    "wof:name":"Senago",
    "wof:placetype":"locality"
},
  "geometry": {"coordinates":[16.73333,3.75],"type":"Point"}
}