{
  "type": "Feature",
  "properties": {
    "gn:admin1_code":"7.0",
    "gn:admin2_code":"7732068.0",
    "gn:asciiname":"Lebe I",
    "gn:country_code":"CF",
    "gn:dem":414,
    "gn:feature_class":"P",
    "gn:feature_code":"PPL",
    "gn:name":"L\u00e9b\u00e9 I",
    "gn:population":0,
    "gn:timezone":"Africa/Bangui",
    "iso:country":"CF",
    "wof:name":"Lebe I",
    "wof:placetype":"locality"
},
  "geometry": {"coordinates":[17.51879,3.76052],"type":"Point"}
}