{
  "type": "Feature",
  "properties": {
    "gn:admin1_code":"17.0",
    "gn:admin2_code":"7731896.0",
    "gn:asciiname":"Yatigamba",
    "gn:country_code":"CF",
    "gn:dem":349,
    "gn:feature_class":"P",
    "gn:feature_code":"PPL",
    "gn:name":"Yatigamba",
    "gn:population":0,
    "gn:timezone":"Africa/Bangui",
    "iso:country":"CF",
    "wof:name":"Yatigamba",
    "wof:placetype":"locality"
},
  "geometry": {"coordinates":[18.48333,4.35],"type":"Point"}
}