{
  "type": "Feature",
  "properties": {
    "gn:admin1_code":"11.0",
    "gn:admin2_code":"7732062.0",
    "gn:asciiname":"Geregea",
    "gn:country_code":"CF",
    "gn:dem":456,
    "gn:feature_class":"P",
    "gn:feature_code":"PPL",
    "gn:name":"G\u00e9r\u00e9gea",
    "gn:population":0,
    "gn:timezone":"Africa/Bangui",
    "iso:country":"CF",
    "wof:name":"Geregea",
    "wof:placetype":"locality"
},
  "geometry": {"coordinates":[20.70336,5.80577],"type":"Point"}
}