{
  "type": "Feature",
  "properties": {
    "gn:admin1_code":"4.0",
    "gn:admin2_code":"9143489.0",
    "gn:asciiname":"Zako",
    "gn:country_code":"CF",
    "gn:dem":719,
    "gn:feature_class":"P",
    "gn:feature_code":"PPL",
    "gn:name":"Zako",
    "gn:population":0,
    "gn:timezone":"Africa/Bangui",
    "iso:country":"CF",
    "wof:name":"Zako",
    "wof:placetype":"locality"
},
  "geometry": {"coordinates":[15.50224,3.92537],"type":"Point"}
}