{
  "type": "Feature",
  "properties": {
    "gn:admin1_code":"12.0",
    "gn:admin2_code":"9143477.0",
    "gn:asciiname":"Bogue",
    "gn:country_code":"CF",
    "gn:dem":501,
    "gn:feature_class":"P",
    "gn:feature_code":"PPL",
    "gn:name":"Bogu\u00e9",
    "gn:population":0,
    "gn:timezone":"Africa/Bangui",
    "iso:country":"CF",
    "name:ceb_x_preferred":[
        "Bogue"
    ],
    "name:deu_x_preferred":[
        "Bogue"
    ],
    "name:fra_x_preferred":[
        "Bogue"
    ],
    "name:ita_x_preferred":[
        "Bogue"
    ],
    "name:nld_x_preferred":[
        "Bogue"
    ],
    "name:pol_x_preferred":[
        "Bogue"
    ],
    "name:por_x_preferred":[
        "Bogue"
    ],
    "name:srp_x_preferred":[
        "\u0411\u043e\u0443\u0433"
    ],
    "name:swe_x_preferred":[
        "Bogue"
    ],
    "name:ukr_x_preferred":[
        "\u0411\u043e\u0433"
    ],
    "name:vol_x_preferred":[
        "Bogue"
    ],
    "wof:name":"Bogue",
    "wof:placetype":"locality"
},
  "geometry": {"coordinates":[18.3944,6.52555],"type":"Point"}
}