{
  "type": "Feature",
  "properties": {
    "gn:admin1_code":"17.0",
    "gn:admin2_code":"7732723.0",
    "gn:asciiname":"Bogoudi",
    "gn:country_code":"CF",
    "gn:dem":635,
    "gn:feature_class":"P",
    "gn:feature_code":"PPL",
    "gn:name":"Bogoudi",
    "gn:population":0,
    "gn:timezone":"Africa/Bangui",
    "iso:country":"CF",
    "wof:name":"Bogoudi",
    "wof:placetype":"locality"
},
  "geometry": {"coordinates":[17.62877000000001,5.45018],"type":"Point"}
}