{
  "type": "Feature",
  "properties": {
    "gn:admin1_code":"09",
    "gn:admin2_code":"7732085.0",
    "gn:asciiname":"Abba-Bogani",
    "gn:country_code":"CF",
    "gn:dem":774,
    "gn:feature_class":"P",
    "gn:feature_code":"PPL",
    "gn:name":"Abba-Bogani",
    "gn:population":0,
    "gn:timezone":"Africa/Bangui",
    "iso:country":"CF",
    "wof:name":"Abba-Bogani",
    "wof:placetype":"locality"
},
  "geometry": {"coordinates":[15.51935,5.83044],"type":"Point"}
}