{
  "type": "Feature",
  "properties": {
    "gn:admin1_code":"12",
    "gn:admin2_code":"9143478.0",
    "gn:asciiname":"Danze",
    "gn:country_code":"CF",
    "gn:dem":406,
    "gn:feature_class":"P",
    "gn:feature_code":"PPL",
    "gn:name":"Danz\u00e9",
    "gn:population":0,
    "gn:timezone":"Africa/Bangui",
    "iso:country":"CF",
    "name:und_x_variant":[
        "Dandz\u00e9",
        "Danz\u00e9"
    ],
    "wof:name":"Danze",
    "wof:placetype":"locality"
},
  "geometry": {"coordinates":[18.70312,8.02997],"type":"Point"}
}