{
  "type": "Feature",
  "properties": {
    "gn:admin1_code":"8.0",
    "gn:admin2_code":"7731888.0",
    "gn:asciiname":"Nielo",
    "gn:country_code":"CF",
    "gn:dem":486,
    "gn:feature_class":"P",
    "gn:feature_code":"PPL",
    "gn:name":"Nielo",
    "gn:population":0,
    "gn:timezone":"Africa/Bangui",
    "iso:country":"CF",
    "wof:name":"Nielo",
    "wof:placetype":"locality"
},
  "geometry": {"coordinates":[22.50392,4.43055],"type":"Point"}
}