{
  "type": "Feature",
  "properties": {
    "gn:admin1_code":"2.0",
    "gn:admin2_code":"7732066.0",
    "gn:asciiname":"Moro",
    "gn:country_code":"CF",
    "gn:dem":452,
    "gn:feature_class":"P",
    "gn:feature_code":"PPL",
    "gn:name":"Moro",
    "gn:population":0,
    "gn:timezone":"Africa/Bangui",
    "iso:country":"CF",
    "wof:name":"Moro",
    "wof:placetype":"locality"
},
  "geometry": {"coordinates":[21.25,5.35],"type":"Point"}
}