{
  "type": "Feature",
  "properties": {
    "gn:admin1_code":"15.0",
    "gn:admin2_code":"9143470.0",
    "gn:asciiname":"Tao",
    "gn:country_code":"CF",
    "gn:dem":581,
    "gn:feature_class":"P",
    "gn:feature_code":"PPL",
    "gn:name":"Tao",
    "gn:population":0,
    "gn:timezone":"Africa/Bangui",
    "iso:country":"CF",
    "name:afr_x_preferred":[
        "Tao"
    ],
    "name:aze_x_preferred":[
        "Dao"
    ],
    "name:bel_x_preferred":[
        "\u0414\u0430\u0430"
    ],
    "name:bos_x_preferred":[
        "Tao"
    ],
    "name:bul_x_preferred":[
        "\u0414\u0430\u043e"
    ],
    "name:cat_x_preferred":[
        "Tao"
    ],
    "name:deu_x_preferred":[
        "Dao"
    ],
    "name:epo_x_preferred":[
        "Tao"
    ],
    "name:est_x_preferred":[
        "Dao"
    ],
    "name:eus_x_preferred":[
        "Tao"
    ],
    "name:fas_x_preferred":[
        "\u062a\u0627\u0626\u0648"
    ],
    "name:fin_x_preferred":[
        "Dao"
    ],
    "name:fra_x_preferred":[
        "Tao"
    ],
    "name:heb_x_preferred":[
        "\u05d3\u05d0\u05d5"
    ],
    "name:hrv_x_preferred":[
        "Tao"
    ],
    "name:hun_x_preferred":[
        "Tao"
    ],
    "name:ita_x_preferred":[
        "Tao"
    ],
    "name:jpn_x_preferred":[
        "\u9053"
    ],
    "name:kaz_x_preferred":[
        "\u0414\u0430\u043e"
    ],
    "name:kir_x_preferred":[
        "\u0414\u0430\u043e"
    ],
    "name:kor_x_preferred":[
        "\ub3c4"
    ],
    "name:lat_x_preferred":[
        "Tao"
    ],
    "name:lav_x_preferred":[
        "Dao"
    ],
    "name:lim_x_preferred":[
        "Tao"
    ],
    "name:lit_x_preferred":[
        "Dao"
    ],
    "name:ltz_x_preferred":[
        "Dao"
    ],
    "name:mar_x_preferred":[
        "\u0924\u093e\u0913"
    ],
    "name:mkd_x_preferred":[
        "\u0422\u0430\u043e"
    ],
    "name:nld_x_preferred":[
        "Tao"
    ],
    "name:nor_x_preferred":[
        "Tao"
    ],
    "name:oci_x_preferred":[
        "Tao"
    ],
    "name:pol_x_preferred":[
        "Dao"
    ],
    "name:por_x_preferred":[
        "Tao"
    ],
    "name:ron_x_preferred":[
        "Tao"
    ],
    "name:rus_x_preferred":[
        "\u0414\u0430\u043e"
    ],
    "name:sco_x_preferred":[
        "Tao"
    ],
    "name:slk_x_preferred":[
        "Tao"
    ],
    "name:spa_x_preferred":[
        "Tao"
    ],
    "name:srp_x_preferred":[
        "\u0422\u0430\u043e"
    ],
    "name:swe_x_preferred":[
        "Dao"
    ],
    "name:tha_x_preferred":[
        "\u0e40\u0e15\u0e4b\u0e32"
    ],
    "name:tur_x_preferred":[
        "Tao"
    ],
    "name:ukr_x_preferred":[
        "\u0414\u0430\u043e"
    ],
    "name:uzb_x_preferred":[
        "Dao"
    ],
    "name:vie_x_preferred":[
        "\u0110\u1ea1o"
    ],
    "wof:name":"Tao",
    "wof:placetype":"locality"
},
  "geometry": {"coordinates":[19.86639,6.47772],"type":"Point"}
}