{
  "type": "Feature",
  "properties": {
    "gn:admin1_code":"15.0",
    "gn:admin2_code":"9143470.0",
    "gn:asciiname":"Tao",
    "gn:country_code":"CF",
    "gn:dem":581,
    "gn:feature_class":"P",
    "gn:feature_code":"PPL",
    "gn:name":"Tao",
    "gn:population":0,
    "gn:timezone":"Africa/Bangui",
    "iso:country":"CF",
    "wof:name":"Tao",
    "wof:placetype":"locality"
},
  "geometry": {"coordinates":[19.86639,6.47772],"type":"Point"}
}