{
  "type": "Feature",
  "properties": {
    "gn:admin1_code":"16.0",
    "gn:admin2_code":"7731905.0",
    "gn:asciiname":"Lidjombo",
    "gn:country_code":"CF",
    "gn:dem":406,
    "gn:feature_class":"P",
    "gn:feature_code":"PPL",
    "gn:name":"Lidjombo",
    "gn:population":0,
    "gn:timezone":"Africa/Bangui",
    "iso:country":"CF",
    "name:und_x_variant":[
        "Lidjombo II",
        "Lidjombo"
    ],
    "wof:name":"Lidjombo",
    "wof:placetype":"locality"
},
  "geometry": {"coordinates":[16.10364,2.70279],"type":"Point"}
}