{
  "type": "Feature",
  "properties": {
    "gn:admin1_code":"16.0",
    "gn:admin2_code":"7731905.0",
    "gn:asciiname":"Kandzia",
    "gn:country_code":"CF",
    "gn:dem":497,
    "gn:feature_class":"P",
    "gn:feature_code":"PPL",
    "gn:name":"Kandzia",
    "gn:population":0,
    "gn:timezone":"Africa/Bangui",
    "iso:country":"CF",
    "wof:name":"Kandzia",
    "wof:placetype":"locality"
},
  "geometry": {"coordinates":[16.25,3.15],"type":"Point"}
}