{
  "type": "Feature",
  "properties": {
    "gn:admin1_code":"7.0",
    "gn:admin2_code":"7732068.0",
    "gn:asciiname":"Bonganou",
    "gn:country_code":"CF",
    "gn:dem":375,
    "gn:feature_class":"P",
    "gn:feature_code":"PPL",
    "gn:name":"Bonganou",
    "gn:population":0,
    "gn:timezone":"Africa/Bangui",
    "iso:country":"CF",
    "name:und_x_variant":[
        "Bongano",
        "Bogano",
        "Bongamo",
        "Bonganou"
    ],
    "wof:name":"Bonganou",
    "wof:placetype":"locality"
},
  "geometry": {"coordinates":[18.27349,4.27795],"type":"Point"}
}