{
  "type": "Feature",
  "properties": {
    "gn:admin1_code":"5.0",
    "gn:admin2_code":"9143461.0",
    "gn:asciiname":"Mabeko",
    "gn:country_code":"CF",
    "gn:dem":664,
    "gn:feature_class":"P",
    "gn:feature_code":"PPL",
    "gn:name":"Mabeko",
    "gn:population":0,
    "gn:timezone":"Africa/Bangui",
    "iso:country":"CF",
    "wof:name":"Mabeko",
    "wof:placetype":"locality"
},
  "geometry": {"coordinates":[26.87603,5.29417],"type":"Point"}
}