{
  "type": "Feature",
  "properties": {
    "gn:admin1_code":"12.0",
    "gn:admin2_code":"9143480.0",
    "gn:asciiname":"Bozoun",
    "gn:country_code":"CF",
    "gn:dem":477,
    "gn:feature_class":"P",
    "gn:feature_code":"PPL",
    "gn:name":"Bozoun",
    "gn:population":0,
    "gn:timezone":"Africa/Bangui",
    "iso:country":"CF",
    "wof:name":"Bozoun",
    "wof:placetype":"locality"
},
  "geometry": {"coordinates":[17.29504,7.03387],"type":"Point"}
}