{
  "type": "Feature",
  "properties": {
    "gn:admin1_code":"3.0",
    "gn:admin2_code":"9143466.0",
    "gn:asciiname":"Akochio",
    "gn:country_code":"CF",
    "gn:dem":737,
    "gn:feature_class":"P",
    "gn:feature_code":"PPL",
    "gn:name":"Akochio",
    "gn:population":0,
    "gn:timezone":"Africa/Bangui",
    "iso:country":"CF",
    "wof:name":"Akochio",
    "wof:placetype":"locality"
},
  "geometry": {"coordinates":[22.39929,7.90433],"type":"Point"}
}