{
  "type": "Feature",
  "properties": {
    "gn:admin1_code":"11.0",
    "gn:admin2_code":"7732062.0",
    "gn:asciiname":"Lingao",
    "gn:country_code":"CF",
    "gn:dem":598,
    "gn:feature_class":"P",
    "gn:feature_code":"PPL",
    "gn:name":"Linga\u00f4",
    "gn:population":0,
    "gn:timezone":"Africa/Bangui",
    "iso:country":"CF",
    "wof:name":"Lingao",
    "wof:placetype":"locality"
},
  "geometry": {"coordinates":[20.51342,5.6632],"type":"Point"}
}