{
  "type": "Feature",
  "properties": {
    "gn:admin1_code":"13.0",
    "gn:admin2_code":"9143493.0",
    "gn:asciiname":"Bindoye",
    "gn:country_code":"CF",
    "gn:dem":587,
    "gn:feature_class":"P",
    "gn:feature_code":"PPL",
    "gn:name":"Bindoye",
    "gn:population":0,
    "gn:timezone":"Africa/Bangui",
    "iso:country":"CF",
    "name:und_x_variant":[
        "Bindoy",
        "Bindoye"
    ],
    "wof:name":"Bindoye",
    "wof:placetype":"locality"
},
  "geometry": {"coordinates":[16.06387,7.41584],"type":"Point"}
}