{
  "type": "Feature",
  "properties": {
    "gn:admin1_code":"2.0",
    "gn:admin2_code":"7731890.0",
    "gn:asciiname":"Mboyo",
    "gn:country_code":"CF",
    "gn:dem":403,
    "gn:feature_class":"P",
    "gn:feature_code":"PPL",
    "gn:name":"Mboyo",
    "gn:population":0,
    "gn:timezone":"Africa/Bangui",
    "iso:country":"CF",
    "wof:name":"Mboyo",
    "wof:placetype":"locality"
},
  "geometry": {"coordinates":[21.67066,4.33249],"type":"Point"}
}