{
  "type": "Feature",
  "properties": {
    "gn:admin1_code":"11.0",
    "gn:admin2_code":"7732062.0",
    "gn:asciiname":"Grembassa",
    "gn:country_code":"CF",
    "gn:dem":544,
    "gn:feature_class":"P",
    "gn:feature_code":"PPL",
    "gn:name":"Grembassa",
    "gn:population":0,
    "gn:timezone":"Africa/Bangui",
    "iso:country":"CF",
    "wof:name":"Grembassa",
    "wof:placetype":"locality"
},
  "geometry": {"coordinates":[21.30877000000001,5.87566],"type":"Point"}
}