{
  "type": "Feature",
  "properties": {
    "gn:admin1_code":"8.0",
    "gn:admin2_code":"7732064.0",
    "gn:asciiname":"Gambou",
    "gn:country_code":"CF",
    "gn:dem":568,
    "gn:feature_class":"P",
    "gn:feature_code":"PPL",
    "gn:name":"Gambou",
    "gn:population":0,
    "gn:timezone":"Africa/Bangui",
    "iso:country":"CF",
    "wof:name":"Gambou",
    "wof:placetype":"locality"
},
  "geometry": {"coordinates":[22.98946,5.05592],"type":"Point"}
}