{
  "type": "Feature",
  "properties": {
    "gn:admin1_code":"12.0",
    "gn:admin2_code":"9143478.0",
    "gn:asciiname":"Mera",
    "gn:country_code":"CF",
    "gn:dem":408,
    "gn:feature_class":"P",
    "gn:feature_code":"PPL",
    "gn:name":"M\u00e9ra",
    "gn:population":0,
    "gn:timezone":"Africa/Bangui",
    "iso:country":"CF",
    "name:bel_x_preferred":[
        "\u041c\u0435\u0440\u0430"
    ],
    "name:bre_x_preferred":[
        "Mera"
    ],
    "name:cat_x_preferred":[
        "Mera"
    ],
    "name:ceb_x_preferred":[
        "Mera"
    ],
    "name:ces_x_preferred":[
        "Mera"
    ],
    "name:deu_x_preferred":[
        "Mera"
    ],
    "name:fra_x_preferred":[
        "Mera"
    ],
    "name:glg_x_preferred":[
        "Mera"
    ],
    "name:hun_x_preferred":[
        "Mera"
    ],
    "name:ita_x_preferred":[
        "Mera"
    ],
    "name:nld_x_preferred":[
        "Mera"
    ],
    "name:pol_x_preferred":[
        "Mera"
    ],
    "name:por_x_preferred":[
        "Mera"
    ],
    "name:ron_x_preferred":[
        "Mera"
    ],
    "name:rus_x_preferred":[
        "\u041c\u0435\u0440\u0430"
    ],
    "name:spa_x_preferred":[
        "Mera"
    ],
    "name:srp_x_preferred":[
        "\u041c\u0435\u0440\u0430"
    ],
    "name:swe_x_preferred":[
        "Mera"
    ],
    "name:und_x_variant":[
        "M\u00e9ra",
        "Mura"
    ],
    "name:vie_x_preferred":[
        "Mera"
    ],
    "wof:name":"Mera",
    "wof:placetype":"locality"
},
  "geometry": {"coordinates":[18.04301,7.8961],"type":"Point"}
}