{
  "type": "Feature",
  "properties": {
    "gn:admin1_code":"1.0",
    "gn:admin2_code":"9143460.0",
    "gn:asciiname":"Godovo",
    "gn:country_code":"CF",
    "gn:dem":498,
    "gn:feature_class":"P",
    "gn:feature_code":"PPL",
    "gn:name":"Godovo",
    "gn:population":0,
    "gn:timezone":"Africa/Bangui",
    "iso:country":"CF",
    "wof:name":"Godovo",
    "wof:placetype":"locality"
},
  "geometry": {"coordinates":[20.75,8.01667],"type":"Point"}
}