{
  "type": "Feature",
  "properties": {
    "gn:admin1_code":"13.0",
    "gn:admin2_code":"8299286.0",
    "gn:asciiname":"Bakoui",
    "gn:country_code":"CF",
    "gn:dem":686,
    "gn:feature_class":"P",
    "gn:feature_code":"PPL",
    "gn:name":"Bakoui",
    "gn:population":0,
    "gn:timezone":"Africa/Bangui",
    "iso:country":"CF",
    "name:und_x_variant":[
        "Bukou\u00e9",
        "Bokun",
        "Bokoua",
        "Bakoui"
    ],
    "wof:name":"Bakoui",
    "wof:placetype":"locality"
},
  "geometry": {"coordinates":[16.41212,6.31843],"type":"Point"}
}