{
  "type": "Feature",
  "properties": {
    "gn:admin1_code":"15",
    "gn:admin2_code":"9143469.0",
    "gn:asciiname":"Vami II",
    "gn:country_code":"CF",
    "gn:dem":413,
    "gn:feature_class":"P",
    "gn:feature_code":"PPL",
    "gn:name":"Vami II",
    "gn:population":0,
    "gn:timezone":"Africa/Bangui",
    "iso:country":"CF",
    "wof:name":"Vami II",
    "wof:placetype":"locality"
},
  "geometry": {"coordinates":[18.88588,7.40981],"type":"Point"}
}