{
  "type": "Feature",
  "properties": {
    "gn:admin1_code":"2.0",
    "gn:admin2_code":"7731891.0",
    "gn:asciiname":"Mbama",
    "gn:country_code":"CF",
    "gn:dem":573,
    "gn:feature_class":"P",
    "gn:feature_code":"PPL",
    "gn:name":"Mbama",
    "gn:population":0,
    "gn:timezone":"Africa/Bangui",
    "iso:country":"CF",
    "name:ceb_x_preferred":[
        "Mbama"
    ],
    "name:swe_x_preferred":[
        "Mbama"
    ],
    "wof:name":"Mbama",
    "wof:placetype":"locality"
},
  "geometry": {"coordinates":[21.2204,4.41118],"type":"Point"}
}