{
  "type": "Feature",
  "properties": {
    "gn:admin1_code":"14.0",
    "gn:admin2_code":"9143458.0",
    "gn:asciiname":"Sadjer",
    "gn:country_code":"CF",
    "gn:dem":434,
    "gn:feature_class":"P",
    "gn:feature_code":"PPL",
    "gn:name":"Sadjer",
    "gn:population":0,
    "gn:timezone":"Africa/Bangui",
    "iso:country":"CF",
    "wof:name":"Sadjer",
    "wof:placetype":"locality"
},
  "geometry": {"coordinates":[21.9534,10.1162],"type":"Point"}
}