{
  "type": "Feature",
  "properties": {
    "gn:admin1_code":"9.0",
    "gn:admin2_code":"7732103.0",
    "gn:asciiname":"Bogani",
    "gn:country_code":"CF",
    "gn:dem":815,
    "gn:feature_class":"P",
    "gn:feature_code":"PPL",
    "gn:name":"Bogani",
    "gn:population":0,
    "gn:timezone":"Africa/Bangui",
    "iso:country":"CF",
    "wof:name":"Bogani",
    "wof:placetype":"locality"
},
  "geometry": {"coordinates":[16.35972000000001,5.59047],"type":"Point"}
}