{
  "type": "Feature",
  "properties": {
    "gn:admin1_code":"12.0",
    "gn:admin2_code":"9143481.0",
    "gn:asciiname":"Banou",
    "gn:country_code":"CF",
    "gn:dem":582,
    "gn:feature_class":"P",
    "gn:feature_code":"PPL",
    "gn:name":"Banou",
    "gn:population":0,
    "gn:timezone":"Africa/Bangui",
    "iso:country":"CF",
    "name:und_x_variant":[
        "Bayalo-Banou",
        "Banou"
    ],
    "wof:name":"Banou",
    "wof:placetype":"locality"
},
  "geometry": {"coordinates":[17.00388,7.10447],"type":"Point"}
}