{
  "type": "Feature",
  "properties": {
    "gn:admin1_code":"3.0",
    "gn:admin2_code":"9143475.0",
    "gn:asciiname":"Doungou III",
    "gn:country_code":"CF",
    "gn:dem":662,
    "gn:feature_class":"P",
    "gn:feature_code":"PPL",
    "gn:name":"Doungou III",
    "gn:population":0,
    "gn:timezone":"Africa/Bangui",
    "iso:country":"CF",
    "wof:name":"Doungou III",
    "wof:placetype":"locality"
},
  "geometry": {"coordinates":[22.72218,6.47943],"type":"Point"}
}