{
  "type": "Feature",
  "properties": {
    "gn:admin1_code":"2.0",
    "gn:admin2_code":"7731891.0",
    "gn:asciiname":"Zinda",
    "gn:country_code":"CF",
    "gn:dem":481,
    "gn:feature_class":"P",
    "gn:feature_code":"PPL",
    "gn:name":"Zinda",
    "gn:population":0,
    "gn:timezone":"Africa/Bangui",
    "iso:country":"CF",
    "wof:name":"Zinda",
    "wof:placetype":"locality"
},
  "geometry": {"coordinates":[21.28447,4.57831],"type":"Point"}
}