{
  "type": "Feature",
  "properties": {
    "gn:admin1_code":"01",
    "gn:admin2_code":"9143460.0",
    "gn:asciiname":"Dekoul",
    "gn:country_code":"CF",
    "gn:dem":430,
    "gn:feature_class":"P",
    "gn:feature_code":"PPL",
    "gn:name":"D\u00e9koul",
    "gn:population":0,
    "gn:timezone":"Africa/Bangui",
    "iso:country":"CF",
    "name:fra_x_preferred":[
        "D\u00e9koul"
    ],
    "wof:name":"Dekoul",
    "wof:placetype":"locality"
},
  "geometry": {"coordinates":[21.54835,9.42027],"type":"Point"}
}