{
  "type": "Feature",
  "properties": {
    "gn:admin1_code":"17.0",
    "gn:admin2_code":"7732723.0",
    "gn:asciiname":"Bouali",
    "gn:country_code":"CF",
    "gn:dem":587,
    "gn:feature_class":"P",
    "gn:feature_code":"PPL",
    "gn:name":"Bouali",
    "gn:population":0,
    "gn:timezone":"Africa/Bangui",
    "iso:country":"CF",
    "wof:name":"Bouali",
    "wof:placetype":"locality"
},
  "geometry": {"coordinates":[17.81667000000001,5.48333],"type":"Point"}
}