{
  "type": "Feature",
  "properties": {
    "gn:admin1_code":"3.0",
    "gn:admin2_code":"9143465.0",
    "gn:asciiname":"Mandjiro",
    "gn:country_code":"CF",
    "gn:dem":571,
    "gn:feature_class":"P",
    "gn:feature_code":"PPL",
    "gn:name":"Mandjiro",
    "gn:population":0,
    "gn:timezone":"Africa/Bangui",
    "iso:country":"CF",
    "wof:name":"Mandjiro",
    "wof:placetype":"locality"
},
  "geometry": {"coordinates":[22.04711,5.72571],"type":"Point"}
}