{
  "type": "Feature",
  "properties": {
    "gn:admin1_code":"1.0",
    "gn:admin2_code":"9143459.0",
    "gn:asciiname":"Bakolekpa",
    "gn:country_code":"CF",
    "gn:dem":422,
    "gn:feature_class":"P",
    "gn:feature_code":"PPL",
    "gn:name":"Bakolekpa",
    "gn:population":0,
    "gn:timezone":"Africa/Bangui",
    "iso:country":"CF",
    "wof:name":"Bakolekpa",
    "wof:placetype":"locality"
},
  "geometry": {"coordinates":[20.35861,8.10412],"type":"Point"}
}