{
  "type": "Feature",
  "properties": {
    "gn:admin1_code":"5.0",
    "gn:admin2_code":"9143464.0",
    "gn:asciiname":"Morkia",
    "gn:country_code":"CF",
    "gn:dem":609,
    "gn:feature_class":"P",
    "gn:feature_code":"PPL",
    "gn:name":"Morkia",
    "gn:population":0,
    "gn:timezone":"Africa/Bangui",
    "iso:country":"CF",
    "wof:name":"Morkia",
    "wof:placetype":"locality"
},
  "geometry": {"coordinates":[25.29087,5.67207],"type":"Point"}
}