{
  "type": "Feature",
  "properties": {
    "gn:admin1_code":"11.0",
    "gn:admin2_code":"7732062.0",
    "gn:asciiname":"Afrotcho",
    "gn:country_code":"CF",
    "gn:dem":558,
    "gn:feature_class":"P",
    "gn:feature_code":"PPL",
    "gn:name":"Afrotcho",
    "gn:population":0,
    "gn:timezone":"Africa/Bangui",
    "iso:country":"CF",
    "wof:name":"Afrotcho",
    "wof:placetype":"locality"
},
  "geometry": {"coordinates":[21.22379,5.92259],"type":"Point"}
}