{
  "type": "Feature",
  "properties": {
    "gn:admin1_code":"8.0",
    "gn:admin2_code":"7732690.0",
    "gn:asciiname":"Waraga",
    "gn:country_code":"CF",
    "gn:dem":546,
    "gn:feature_class":"P",
    "gn:feature_code":"PPL",
    "gn:name":"Waraga",
    "gn:population":0,
    "gn:timezone":"Africa/Bangui",
    "iso:country":"CF",
    "wof:name":"Waraga",
    "wof:placetype":"locality"
},
  "geometry": {"coordinates":[22.8798,5.6757],"type":"Point"}
}