{
  "type": "Feature",
  "properties": {
    "gn:admin1_code":"12.0",
    "gn:admin2_code":"7732115.0",
    "gn:asciiname":"Boudou",
    "gn:country_code":"CF",
    "gn:dem":588,
    "gn:feature_class":"P",
    "gn:feature_code":"PPL",
    "gn:name":"Boudou",
    "gn:population":0,
    "gn:timezone":"Africa/Bangui",
    "iso:country":"CF",
    "name:cat_x_preferred":[
        "Bodon"
    ],
    "name:ceb_x_preferred":[
        "Boudou"
    ],
    "name:deu_x_preferred":[
        "Boudou"
    ],
    "name:eus_x_preferred":[
        "Bodon"
    ],
    "name:fra_x_preferred":[
        "Boudou"
    ],
    "name:hun_x_preferred":[
        "Boudou"
    ],
    "name:ita_x_preferred":[
        "Boudou"
    ],
    "name:lat_x_preferred":[
        "Boudou"
    ],
    "name:mlg_x_preferred":[
        "Boudou"
    ],
    "name:msa_x_preferred":[
        "Boudou"
    ],
    "name:nld_x_preferred":[
        "Boudou"
    ],
    "name:oci_x_preferred":[
        "Bodon"
    ],
    "name:pms_x_preferred":[
        "Boudou"
    ],
    "name:pol_x_preferred":[
        "Boudou"
    ],
    "name:por_x_preferred":[
        "Boudou"
    ],
    "name:ron_x_preferred":[
        "Boudou"
    ],
    "name:slk_x_preferred":[
        "Boudou"
    ],
    "name:spa_x_preferred":[
        "Boudou"
    ],
    "name:srp_x_preferred":[
        "\u0411\u0443\u0434\u0443"
    ],
    "name:swe_x_preferred":[
        "Boudou"
    ],
    "name:ukr_x_preferred":[
        "\u0411\u0443\u0434\u0443"
    ],
    "name:vie_x_preferred":[
        "Boudou"
    ],
    "name:vol_x_preferred":[
        "Boudou"
    ],
    "name:war_x_preferred":[
        "Boudou"
    ],
    "wof:name":"Boudou",
    "wof:placetype":"locality"
},
  "geometry": {"coordinates":[16.90973,6.54337],"type":"Point"}
}