{
  "type": "Feature",
  "properties": {
    "gn:admin1_code":"12.0",
    "gn:admin2_code":"9143477.0",
    "gn:asciiname":"Mourou",
    "gn:country_code":"CF",
    "gn:dem":519,
    "gn:feature_class":"P",
    "gn:feature_code":"PPL",
    "gn:name":"Mourou",
    "gn:population":0,
    "gn:timezone":"Africa/Bangui",
    "iso:country":"CF",
    "name:deu_x_preferred":[
        "Mourou"
    ],
    "name:fra_x_preferred":[
        "Mourou"
    ],
    "name:nds_x_preferred":[
        "Mourou"
    ],
    "wof:name":"Mourou",
    "wof:placetype":"locality"
},
  "geometry": {"coordinates":[18.36667000000001,6.31667],"type":"Point"}
}