{
  "type": "Feature",
  "properties": {
    "gn:admin1_code":"13.0",
    "gn:admin2_code":"9143494.0",
    "gn:asciiname":"Bilagare",
    "gn:country_code":"CF",
    "gn:dem":789,
    "gn:feature_class":"P",
    "gn:feature_code":"PPL",
    "gn:name":"Bilagar\u00e9",
    "gn:population":0,
    "gn:timezone":"Africa/Bangui",
    "iso:country":"CF",
    "wof:name":"Bilagare",
    "wof:placetype":"locality"
},
  "geometry": {"coordinates":[16.14177999999999,6.76603],"type":"Point"}
}