{
  "type": "Feature",
  "properties": {
    "gn:admin1_code":"8.0",
    "gn:admin2_code":"7732064.0",
    "gn:asciiname":"Selim",
    "gn:country_code":"CF",
    "gn:dem":527,
    "gn:feature_class":"P",
    "gn:feature_code":"PPL",
    "gn:name":"S\u00e9lim",
    "gn:population":0,
    "gn:timezone":"Africa/Bangui",
    "iso:country":"CF",
    "wof:name":"Selim",
    "wof:placetype":"locality"
},
  "geometry": {"coordinates":[23.65574,4.94187],"type":"Point"}
}