{
  "type": "Feature",
  "properties": {
    "gn:admin1_code":"12.0",
    "gn:admin2_code":"7732115.0",
    "gn:asciiname":"Touinguede",
    "gn:country_code":"CF",
    "gn:dem":565,
    "gn:feature_class":"P",
    "gn:feature_code":"PPL",
    "gn:name":"Touingued\u00e9",
    "gn:population":0,
    "gn:timezone":"Africa/Bangui",
    "iso:country":"CF",
    "wof:name":"Touinguede",
    "wof:placetype":"locality"
},
  "geometry": {"coordinates":[17.18365,6.64263],"type":"Point"}
}