{
  "type": "Feature",
  "properties": {
    "gn:admin1_code":"9.0",
    "gn:admin2_code":"9143482.0",
    "gn:asciiname":"Mere Boudoytoro",
    "gn:country_code":"CF",
    "gn:dem":689,
    "gn:feature_class":"P",
    "gn:feature_code":"PPL",
    "gn:name":"M\u00e9r\u00e9 Boudoytoro",
    "gn:population":0,
    "gn:timezone":"Africa/Bangui",
    "iso:country":"CF",
    "name:und_x_variant":[
        "Mer\u00e9 Bodetoro",
        "M\u00e9r\u00e9 Boudoytoro"
    ],
    "wof:name":"Mere Boudoytoro",
    "wof:placetype":"locality"
},
  "geometry": {"coordinates":[15.30629,5.3803],"type":"Point"}
}