{
  "type": "Feature",
  "properties": {
    "gn:admin1_code":"17.0",
    "gn:admin2_code":"7732372.0",
    "gn:asciiname":"Bosenforo II",
    "gn:country_code":"CF",
    "gn:dem":696,
    "gn:feature_class":"P",
    "gn:feature_code":"PPL",
    "gn:name":"Bosenforo II",
    "gn:population":0,
    "gn:timezone":"Africa/Bangui",
    "iso:country":"CF",
    "name:und_x_variant":[
        "Bossemforo"
    ],
    "wof:name":"Bosenforo II",
    "wof:placetype":"locality"
},
  "geometry": {"coordinates":[17.21349,5.28394],"type":"Point"}
}