{
  "type": "Feature",
  "properties": {
    "gn:admin1_code":"11.0",
    "gn:admin2_code":"7732377.0",
    "gn:asciiname":"Pamgakora",
    "gn:country_code":"CF",
    "gn:dem":514,
    "gn:feature_class":"P",
    "gn:feature_code":"PPL",
    "gn:name":"Pamgakora",
    "gn:population":0,
    "gn:timezone":"Africa/Bangui",
    "iso:country":"CF",
    "name:und_x_variant":[
        "Pangakoura",
        "Pangakora",
        "Pamgakora"
    ],
    "wof:name":"Pamgakora",
    "wof:placetype":"locality"
},
  "geometry": {"coordinates":[19.69884,5.7588],"type":"Point"}
}