{
  "type": "Feature",
  "properties": {
    "gn:admin1_code":"13.0",
    "gn:admin2_code":"9143494.0",
    "gn:asciiname":"Sange",
    "gn:country_code":"CF",
    "gn:dem":708,
    "gn:feature_class":"P",
    "gn:feature_code":"PPL",
    "gn:name":"Sang\u00e9",
    "gn:population":0,
    "gn:timezone":"Africa/Bangui",
    "iso:country":"CF",
    "name:ceb_x_preferred":[
        "Sange"
    ],
    "name:deu_x_preferred":[
        "Sange"
    ],
    "name:fra_x_preferred":[
        "Sange"
    ],
    "name:swe_x_preferred":[
        "Sange"
    ],
    "wof:name":"Sange",
    "wof:placetype":"locality"
},
  "geometry": {"coordinates":[16.39493,6.60979],"type":"Point"}
}