{
  "type": "Feature",
  "properties": {
    "gn:admin1_code":"17",
    "gn:admin2_code":"7732723.0",
    "gn:asciiname":"Bodele",
    "gn:country_code":"CF",
    "gn:dem":596,
    "gn:feature_class":"P",
    "gn:feature_code":"PPL",
    "gn:name":"Bodel\u00e9",
    "gn:population":0,
    "gn:timezone":"Africa/Bangui",
    "iso:country":"CF",
    "wof:name":"Bodele",
    "wof:placetype":"locality"
},
  "geometry": {"coordinates":[17.72129,5.67972],"type":"Point"}
}