{
  "type": "Feature",
  "properties": {
    "gn:admin1_code":"11.0",
    "gn:admin2_code":"7732062.0",
    "gn:asciiname":"Gouyali",
    "gn:country_code":"CF",
    "gn:dem":601,
    "gn:feature_class":"P",
    "gn:feature_code":"PPL",
    "gn:name":"Gouyali",
    "gn:population":0,
    "gn:timezone":"Africa/Bangui",
    "iso:country":"CF",
    "wof:name":"Gouyali",
    "wof:placetype":"locality"
},
  "geometry": {"coordinates":[21.06359,5.87653],"type":"Point"}
}