{
  "type": "Feature",
  "properties": {
    "gn:admin1_code":"8.0",
    "gn:admin2_code":"9143468.0",
    "gn:asciiname":"Songopai",
    "gn:country_code":"CF",
    "gn:dem":580,
    "gn:feature_class":"P",
    "gn:feature_code":"PPL",
    "gn:name":"Songopa\u00ef",
    "gn:population":0,
    "gn:timezone":"Africa/Bangui",
    "iso:country":"CF",
    "wof:name":"Songopai",
    "wof:placetype":"locality"
},
  "geometry": {"coordinates":[24.28333,5.91667],"type":"Point"}
}