{
  "type": "Feature",
  "properties": {
    "gn:admin1_code":"11.0",
    "gn:admin2_code":"7731893.0",
    "gn:asciiname":"Ndihouda",
    "gn:country_code":"CF",
    "gn:dem":411,
    "gn:feature_class":"P",
    "gn:feature_code":"PPL",
    "gn:name":"Ndihouda",
    "gn:population":0,
    "gn:timezone":"Africa/Bangui",
    "iso:country":"CF",
    "wof:name":"Ndihouda",
    "wof:placetype":"locality"
},
  "geometry": {"coordinates":[20.46667,4.65],"type":"Point"}
}