{
  "type": "Feature",
  "properties": {
    "gn:admin1_code":"5.0",
    "gn:admin2_code":"9143461.0",
    "gn:asciiname":"Bougoua",
    "gn:country_code":"CF",
    "gn:dem":671,
    "gn:feature_class":"P",
    "gn:feature_code":"PPL",
    "gn:name":"Bougoua",
    "gn:population":0,
    "gn:timezone":"Africa/Bangui",
    "iso:country":"CF",
    "wof:name":"Bougoua",
    "wof:placetype":"locality"
},
  "geometry": {"coordinates":[26.76667,5.21667],"type":"Point"}
}