{
  "type": "Feature",
  "properties": {
    "gn:admin1_code":"12.0",
    "gn:admin2_code":"9143480.0",
    "gn:asciiname":"Bouaye",
    "gn:country_code":"CF",
    "gn:dem":497,
    "gn:feature_class":"P",
    "gn:feature_code":"PPL",
    "gn:name":"Bouay\u00e9",
    "gn:population":0,
    "gn:timezone":"Africa/Bangui",
    "iso:country":"CF",
    "name:aka_x_preferred":[
        "Bouaye"
    ],
    "name:ast_x_preferred":[
        "Bouaye"
    ],
    "name:bam_x_preferred":[
        "Bouaye"
    ],
    "name:bre_x_preferred":[
        "Bouez"
    ],
    "name:cat_x_preferred":[
        "Bouaye"
    ],
    "name:ceb_x_preferred":[
        "Bouaye"
    ],
    "name:cym_x_preferred":[
        "Bouez"
    ],
    "name:deu_x_preferred":[
        "Bouaye"
    ],
    "name:eus_x_preferred":[
        "Bouaye"
    ],
    "name:fra_x_preferred":[
        "Bouaye"
    ],
    "name:hun_x_preferred":[
        "Bouaye"
    ],
    "name:ita_x_preferred":[
        "Bouaye"
    ],
    "name:lat_x_preferred":[
        "Bouaye"
    ],
    "name:mlg_x_preferred":[
        "Bouaye"
    ],
    "name:msa_x_preferred":[
        "Bouaye"
    ],
    "name:nld_x_preferred":[
        "Bouaye"
    ],
    "name:oci_x_preferred":[
        "Bouez"
    ],
    "name:pol_x_preferred":[
        "Bouaye"
    ],
    "name:ron_x_preferred":[
        "Bouaye"
    ],
    "name:slk_x_preferred":[
        "Bouaye"
    ],
    "name:spa_x_preferred":[
        "Bouaye"
    ],
    "name:srp_x_preferred":[
        "\u0411\u0443\u0435"
    ],
    "name:swe_x_preferred":[
        "Bouaye"
    ],
    "name:ukr_x_preferred":[
        "\u0411\u0443\u0435"
    ],
    "name:vie_x_preferred":[
        "Bouaye"
    ],
    "name:vol_x_preferred":[
        "Bouaye"
    ],
    "name:war_x_preferred":[
        "Bouaye"
    ],
    "wof:name":"Bouaye",
    "wof:placetype":"locality"
},
  "geometry": {"coordinates":[17.51616,7.01109],"type":"Point"}
}