{
  "type": "Feature",
  "properties": {
    "gn:admin1_code":"12",
    "gn:admin2_code":"9143478.0",
    "gn:asciiname":"Ngonikira",
    "gn:country_code":"CF",
    "gn:dem":421,
    "gn:feature_class":"P",
    "gn:feature_code":"PPL",
    "gn:name":"Ngonikira",
    "gn:population":0,
    "gn:timezone":"Africa/Bangui",
    "iso:country":"CF",
    "wof:name":"Ngonikira",
    "wof:placetype":"locality"
},
  "geometry": {"coordinates":[18.52228,7.57383],"type":"Point"}
}