{
  "type": "Feature",
  "properties": {
    "gn:admin1_code":"6.0",
    "gn:admin2_code":"7732483.0",
    "gn:asciiname":"Domandere",
    "gn:cc2":"CF",
    "gn:country_code":"CF",
    "gn:dem":563,
    "gn:feature_class":"P",
    "gn:feature_code":"PPL",
    "gn:name":"Domandere",
    "gn:population":0,
    "gn:timezone":"Africa/Bangui",
    "iso:country":"CF",
    "name:und_x_variant":[
        "Dom\u00e9der\u00e9",
        "Domandere"
    ],
    "wof:name":"Domandere",
    "wof:placetype":"locality"
},
  "geometry": {"coordinates":[19.15,5.86667],"type":"Point"}
}