{
  "type": "Feature",
  "properties": {
    "gn:admin1_code":"11.0",
    "gn:admin2_code":"7732067.0",
    "gn:asciiname":"Ligoua",
    "gn:country_code":"CF",
    "gn:dem":546,
    "gn:feature_class":"P",
    "gn:feature_code":"PPL",
    "gn:name":"Ligoua",
    "gn:population":0,
    "gn:timezone":"Africa/Bangui",
    "iso:country":"CF",
    "wof:name":"Ligoua",
    "wof:placetype":"locality"
},
  "geometry": {"coordinates":[21.156,6.25326],"type":"Point"}
}