{
  "type": "Feature",
  "properties": {
    "gn:admin1_code":"2.0",
    "gn:admin2_code":"7731891.0",
    "gn:asciiname":"Balimingou",
    "gn:country_code":"CF",
    "gn:dem":432,
    "gn:feature_class":"P",
    "gn:feature_code":"PPL",
    "gn:name":"Balimingou",
    "gn:population":0,
    "gn:timezone":"Africa/Bangui",
    "iso:country":"CF",
    "wof:name":"Balimingou",
    "wof:placetype":"locality"
},
  "geometry": {"coordinates":[21.16667,4.68333],"type":"Point"}
}