{
  "type": "Feature",
  "properties": {
    "gn:admin1_code":"13.0",
    "gn:admin2_code":"9143493.0",
    "gn:asciiname":"Mann",
    "gn:country_code":"CF",
    "gn:dem":746,
    "gn:feature_class":"P",
    "gn:feature_code":"PPL",
    "gn:name":"Mann",
    "gn:population":0,
    "gn:timezone":"Africa/Bangui",
    "iso:country":"CF",
    "name:cat_x_preferred":[
        "Mann"
    ],
    "name:ceb_x_preferred":[
        "Mann"
    ],
    "name:ces_x_preferred":[
        "Mann"
    ],
    "name:deu_x_preferred":[
        "Mann"
    ],
    "name:fin_x_preferred":[
        "Mann"
    ],
    "name:fra_x_preferred":[
        "Mann"
    ],
    "name:heb_x_preferred":[
        "\u05de\u05d0\u05df"
    ],
    "name:ita_x_preferred":[
        "Mann"
    ],
    "name:lit_x_preferred":[
        "Mann"
    ],
    "name:nld_x_preferred":[
        "Mann"
    ],
    "name:nor_x_preferred":[
        "Mann"
    ],
    "name:pol_x_preferred":[
        "Mann"
    ],
    "name:por_x_preferred":[
        "Mann"
    ],
    "name:rus_x_preferred":[
        "\u041c\u0430\u043d\u043d"
    ],
    "name:slv_x_preferred":[
        "Mann"
    ],
    "name:spa_x_preferred":[
        "Mann"
    ],
    "name:swe_x_preferred":[
        "Mann"
    ],
    "name:tur_x_preferred":[
        "Mann"
    ],
    "name:ukr_x_preferred":[
        "\u041c\u0430\u043d\u043d"
    ],
    "wof:name":"Mann",
    "wof:placetype":"locality"
},
  "geometry": {"coordinates":[15.48638,7.37423],"type":"Point"}
}