{
  "type": "Feature",
  "properties": {
    "gn:admin1_code":"11.0",
    "gn:admin2_code":"7732062.0",
    "gn:asciiname":"Lapago",
    "gn:country_code":"CF",
    "gn:dem":443,
    "gn:feature_class":"P",
    "gn:feature_code":"PPL",
    "gn:name":"Lapago",
    "gn:population":0,
    "gn:timezone":"Africa/Bangui",
    "iso:country":"CF",
    "wof:name":"Lapago",
    "wof:placetype":"locality"
},
  "geometry": {"coordinates":[20.64673,5.78364],"type":"Point"}
}