{
  "type": "Feature",
  "properties": {
    "gn:admin1_code":"7.0",
    "gn:admin2_code":"7732068.0",
    "gn:asciiname":"Mete",
    "gn:country_code":"CF",
    "gn:dem":360,
    "gn:feature_class":"P",
    "gn:feature_code":"PPL",
    "gn:name":"Met\u00e9",
    "gn:population":0,
    "gn:timezone":"Africa/Bangui",
    "iso:country":"CF",
    "wof:name":"Mete",
    "wof:placetype":"locality"
},
  "geometry": {"coordinates":[18.07064,3.6314],"type":"Point"}
}