{
  "type": "Feature",
  "properties": {
    "gn:admin1_code":"12",
    "gn:admin2_code":"9143472.0",
    "gn:asciiname":"Beola",
    "gn:country_code":"CF",
    "gn:dem":426,
    "gn:feature_class":"P",
    "gn:feature_code":"PPL",
    "gn:name":"B\u00e9ola",
    "gn:population":0,
    "gn:timezone":"Africa/Bangui",
    "iso:country":"CF",
    "wof:name":"Beola",
    "wof:placetype":"locality"
},
  "geometry": {"coordinates":[18.17774,7.28249],"type":"Point"}
}