{
  "type": "Feature",
  "properties": {
    "gn:admin1_code":"12.0",
    "gn:admin2_code":"9143481.0",
    "gn:asciiname":"Botongo",
    "gn:country_code":"CF",
    "gn:dem":478,
    "gn:feature_class":"P",
    "gn:feature_code":"PPL",
    "gn:name":"Botongo",
    "gn:population":0,
    "gn:timezone":"Africa/Bangui",
    "iso:country":"CF",
    "name:und_x_variant":[
        "Botonga",
        "Botongo"
    ],
    "wof:name":"Botongo",
    "wof:placetype":"locality"
},
  "geometry": {"coordinates":[16.83895,7.32607],"type":"Point"}
}