{
  "type": "Feature",
  "properties": {
    "gn:admin1_code":"6.0",
    "gn:admin2_code":"7731894.0",
    "gn:asciiname":"Balango-Gbilinga",
    "gn:country_code":"CF",
    "gn:dem":379,
    "gn:feature_class":"P",
    "gn:feature_code":"PPL",
    "gn:name":"Balango-Gbilinga",
    "gn:population":0,
    "gn:timezone":"Africa/Bangui",
    "iso:country":"CF",
    "name:und_x_variant":[
        "Mbalango"
    ],
    "wof:name":"Balango-Gbilinga",
    "wof:placetype":"locality"
},
  "geometry": {"coordinates":[19.86285,5.08938],"type":"Point"}
}