{
  "type": "Feature",
  "properties": {
    "gn:admin1_code":"01",
    "gn:admin2_code":"9143460.0",
    "gn:asciiname":"Mainda",
    "gn:country_code":"CF",
    "gn:dem":380,
    "gn:feature_class":"P",
    "gn:feature_code":"PPL",
    "gn:name":"Ma\u00efnda",
    "gn:population":0,
    "gn:timezone":"Africa/Bangui",
    "iso:country":"CF",
    "name:fra_x_preferred":[
        "Ma\u00efnda"
    ],
    "wof:name":"Mainda",
    "wof:placetype":"locality"
},
  "geometry": {"coordinates":[19.20648,8.90227],"type":"Point"}
}