{
  "type": "Feature",
  "properties": {
    "gn:admin1_code":"17.0",
    "gn:admin2_code":"8299285.0",
    "gn:asciiname":"Dongue",
    "gn:country_code":"CF",
    "gn:dem":437,
    "gn:feature_class":"P",
    "gn:feature_code":"PPL",
    "gn:name":"Dongu\u00e9",
    "gn:population":0,
    "gn:timezone":"Africa/Bangui",
    "iso:country":"CF",
    "wof:name":"Dongue",
    "wof:placetype":"locality"
},
  "geometry": {"coordinates":[18.30813,4.8811],"type":"Point"}
}