{
  "type": "Feature",
  "properties": {
    "gn:admin1_code":"17.0",
    "gn:admin2_code":"7732372.0",
    "gn:asciiname":"Bobandoro II",
    "gn:country_code":"CF",
    "gn:dem":705,
    "gn:feature_class":"P",
    "gn:feature_code":"PPL",
    "gn:name":"Bobandoro II",
    "gn:population":0,
    "gn:timezone":"Africa/Bangui",
    "iso:country":"CF",
    "name:und_x_variant":[
        "Bobandoro"
    ],
    "wof:name":"Bobandoro II",
    "wof:placetype":"locality"
},
  "geometry": {"coordinates":[17.09649,5.29063],"type":"Point"}
}