{
  "type": "Feature",
  "properties": {
    "gn:admin1_code":"15",
    "gn:admin2_code":"9143469.0",
    "gn:asciiname":"Bissekebou",
    "gn:country_code":"CF",
    "gn:dem":437,
    "gn:feature_class":"P",
    "gn:feature_code":"PPL",
    "gn:name":"Biss\u00e9k\u00e9bou",
    "gn:population":0,
    "gn:timezone":"Africa/Bangui",
    "iso:country":"CF",
    "wof:name":"Bissekebou",
    "wof:placetype":"locality"
},
  "geometry": {"coordinates":[18.91143,7.2008],"type":"Point"}
}