{
  "type": "Feature",
  "properties": {
    "gn:admin1_code":"12",
    "gn:admin2_code":"9143478.0",
    "gn:asciiname":"Kimkaba II",
    "gn:country_code":"CF",
    "gn:dem":418,
    "gn:feature_class":"P",
    "gn:feature_code":"PPL",
    "gn:name":"Kimkaba II",
    "gn:population":0,
    "gn:timezone":"Africa/Bangui",
    "iso:country":"CF",
    "wof:name":"Kimkaba II",
    "wof:placetype":"locality"
},
  "geometry": {"coordinates":[18.59858,7.6642],"type":"Point"}
}