{
  "type": "Feature",
  "properties": {
    "gn:admin1_code":"11.0",
    "gn:admin2_code":"9143471.0",
    "gn:asciiname":"Wandalongo",
    "gn:country_code":"CF",
    "gn:dem":547,
    "gn:feature_class":"P",
    "gn:feature_code":"PPL",
    "gn:name":"Wandalongo",
    "gn:population":0,
    "gn:timezone":"Africa/Bangui",
    "iso:country":"CF",
    "wof:name":"Wandalongo",
    "wof:placetype":"locality"
},
  "geometry": {"coordinates":[19.88333,6.41667],"type":"Point"}
}