{
  "type": "Feature",
  "properties": {
    "gn:admin1_code":"8.0",
    "gn:admin2_code":"7732064.0",
    "gn:asciiname":"Dege",
    "gn:country_code":"CF",
    "gn:dem":497,
    "gn:feature_class":"P",
    "gn:feature_code":"PPL",
    "gn:name":"D\u00e9g\u00e9",
    "gn:population":0,
    "gn:timezone":"Africa/Bangui",
    "iso:country":"CF",
    "name:deu_x_preferred":[
        "Dege"
    ],
    "wof:name":"Dege",
    "wof:placetype":"locality"
},
  "geometry": {"coordinates":[23.01504,4.77466],"type":"Point"}
}