{
  "type": "Feature",
  "properties": {
    "gn:admin1_code":"4.0",
    "gn:admin2_code":"9143488.0",
    "gn:asciiname":"Mbossi",
    "gn:country_code":"CF",
    "gn:dem":562,
    "gn:feature_class":"P",
    "gn:feature_code":"PPL",
    "gn:name":"Mbossi",
    "gn:population":0,
    "gn:timezone":"Africa/Bangui",
    "iso:country":"CF",
    "wof:name":"Mbossi",
    "wof:placetype":"locality"
},
  "geometry": {"coordinates":[15.17227,4.01202],"type":"Point"}
}