{
  "type": "Feature",
  "properties": {
    "gn:admin1_code":"13.0",
    "gn:admin2_code":"9143494.0",
    "gn:asciiname":"Begangoro I",
    "gn:country_code":"CF",
    "gn:dem":507,
    "gn:feature_class":"P",
    "gn:feature_code":"PPL",
    "gn:name":"B\u00e9gangoro I",
    "gn:population":0,
    "gn:timezone":"Africa/Bangui",
    "iso:country":"CF",
    "name:und_x_variant":[
        "B\u00e9gangoro",
        "B\u00e9gangoro I"
    ],
    "wof:name":"Begangoro I",
    "wof:placetype":"locality"
},
  "geometry": {"coordinates":[16.60491,7.3852],"type":"Point"}
}