{
  "type": "Feature",
  "properties": {
    "gn:admin1_code":"17",
    "gn:admin2_code":"9143490.0",
    "gn:asciiname":"Bougali",
    "gn:country_code":"CF",
    "gn:dem":598,
    "gn:feature_class":"P",
    "gn:feature_code":"PPL",
    "gn:name":"Bougali",
    "gn:population":0,
    "gn:timezone":"Africa/Bangui",
    "iso:country":"CF",
    "wof:name":"Bougali",
    "wof:placetype":"locality"
},
  "geometry": {"coordinates":[17.87402999999999,5.61201],"type":"Point"}
}