{
  "type": "Feature",
  "properties": {
    "gn:admin1_code":"12.0",
    "gn:admin2_code":"9143477.0",
    "gn:asciiname":"Bodeke",
    "gn:country_code":"CF",
    "gn:dem":589,
    "gn:feature_class":"P",
    "gn:feature_code":"PPL",
    "gn:name":"Bodek\u00e9",
    "gn:population":0,
    "gn:timezone":"Africa/Bangui",
    "iso:country":"CF",
    "wof:name":"Bodeke",
    "wof:placetype":"locality"
},
  "geometry": {"coordinates":[18.56667,6.08333],"type":"Point"}
}