{
  "type": "Feature",
  "properties": {
    "gn:admin1_code":"11.0",
    "gn:admin2_code":"7732377.0",
    "gn:asciiname":"Gado",
    "gn:country_code":"CF",
    "gn:dem":562,
    "gn:feature_class":"P",
    "gn:feature_code":"PPL",
    "gn:name":"Gado",
    "gn:population":0,
    "gn:timezone":"Africa/Bangui",
    "iso:country":"CF",
    "name:ceb_x_preferred":[
        "Gado"
    ],
    "name:deu_x_preferred":[
        "Gado"
    ],
    "name:fra_x_preferred":[
        "Gado"
    ],
    "name:nld_x_preferred":[
        "Gado"
    ],
    "name:por_x_preferred":[
        "Gado"
    ],
    "name:swe_x_preferred":[
        "Gado"
    ],
    "wof:name":"Gado",
    "wof:placetype":"locality"
},
  "geometry": {"coordinates":[19.71522,6.02558],"type":"Point"}
}