{
  "type": "Feature",
  "properties": {
    "gn:admin1_code":"17.0",
    "gn:admin2_code":"8299285.0",
    "gn:asciiname":"Boubazongo",
    "gn:country_code":"CF",
    "gn:dem":523,
    "gn:feature_class":"P",
    "gn:feature_code":"PPL",
    "gn:name":"Boubazongo",
    "gn:population":0,
    "gn:timezone":"Africa/Bangui",
    "iso:country":"CF",
    "name:und_x_variant":[
        "Boubazone",
        "Boubazon",
        "Boubazongo"
    ],
    "wof:name":"Boubazongo",
    "wof:placetype":"locality"
},
  "geometry": {"coordinates":[17.75713,4.67903],"type":"Point"}
}