{
  "type": "Feature",
  "properties": {
    "gn:admin1_code":"17.0",
    "gn:admin2_code":"7732723.0",
    "gn:asciiname":"Bobissi",
    "gn:country_code":"CF",
    "gn:dem":606,
    "gn:feature_class":"P",
    "gn:feature_code":"PPL",
    "gn:name":"Bobissi",
    "gn:population":0,
    "gn:timezone":"Africa/Bangui",
    "iso:country":"CF",
    "wof:name":"Bobissi",
    "wof:placetype":"locality"
},
  "geometry": {"coordinates":[17.66667,4.88333],"type":"Point"}
}