{
  "type": "Feature",
  "properties": {
    "gn:admin1_code":"17.0",
    "gn:admin2_code":"7731896.0",
    "gn:asciiname":"Bobandio",
    "gn:country_code":"CF",
    "gn:dem":447,
    "gn:feature_class":"P",
    "gn:feature_code":"PPL",
    "gn:name":"Bobandio",
    "gn:population":0,
    "gn:timezone":"Africa/Bangui",
    "iso:country":"CF",
    "wof:name":"Bobandio",
    "wof:placetype":"locality"
},
  "geometry": {"coordinates":[18.40102000000001,4.57608],"type":"Point"}
}