{
  "type": "Feature",
  "properties": {
    "gn:admin1_code":"17.0",
    "gn:admin2_code":"7732723.0",
    "gn:asciiname":"Baloudou",
    "gn:country_code":"CF",
    "gn:dem":573,
    "gn:feature_class":"P",
    "gn:feature_code":"PPL",
    "gn:name":"Baloudou",
    "gn:population":0,
    "gn:timezone":"Africa/Bangui",
    "iso:country":"CF",
    "wof:name":"Baloudou",
    "wof:placetype":"locality"
},
  "geometry": {"coordinates":[17.91667,5.41667],"type":"Point"}
}