{
  "type": "Feature",
  "properties": {
    "gn:admin1_code":"2.0",
    "gn:admin2_code":"7731891.0",
    "gn:asciiname":"Yakpa",
    "gn:country_code":"CF",
    "gn:dem":437,
    "gn:feature_class":"P",
    "gn:feature_code":"PPL",
    "gn:name":"Yakpa",
    "gn:population":0,
    "gn:timezone":"Africa/Bangui",
    "iso:country":"CF",
    "wof:name":"Yakpa",
    "wof:placetype":"locality"
},
  "geometry": {"coordinates":[21.11667000000001,4.43333],"type":"Point"}
}