{
  "type": "Feature",
  "properties": {
    "gn:admin1_code":"5.0",
    "gn:admin2_code":"9143461.0",
    "gn:asciiname":"Bangbi II",
    "gn:country_code":"CF",
    "gn:dem":696,
    "gn:feature_class":"P",
    "gn:feature_code":"PPL",
    "gn:name":"Bangbi II",
    "gn:population":0,
    "gn:timezone":"Africa/Bangui",
    "iso:country":"CF",
    "wof:name":"Bangbi II",
    "wof:placetype":"locality"
},
  "geometry": {"coordinates":[27.18333,5.33333],"type":"Point"}
}