{
  "type": "Feature",
  "properties": {
    "gn:admin1_code":"2.0",
    "gn:admin2_code":"7731890.0",
    "gn:asciiname":"Oua",
    "gn:country_code":"CF",
    "gn:dem":400,
    "gn:feature_class":"P",
    "gn:feature_code":"PPL",
    "gn:name":"Oua",
    "gn:population":0,
    "gn:timezone":"Africa/Bangui",
    "iso:country":"CF",
    "name:ceb_x_preferred":[
        "Oua"
    ],
    "name:glg_x_preferred":[
        "Illote Oua"
    ],
    "name:jpn_x_preferred":[
        "\u30aa\u30a6\u30a2\u5cf6"
    ],
    "name:pol_x_preferred":[
        "Oua"
    ],
    "name:por_x_preferred":[
        "Oua"
    ],
    "wof:name":"Oua",
    "wof:placetype":"locality"
},
  "geometry": {"coordinates":[21.63333,4.31667],"type":"Point"}
}