{
  "type": "Feature",
  "properties": {
    "gn:admin1_code":"16.0",
    "gn:admin2_code":"9143473.0",
    "gn:asciiname":"Kambaoro",
    "gn:country_code":"CF",
    "gn:dem":510,
    "gn:feature_class":"P",
    "gn:feature_code":"PPL",
    "gn:name":"Kambaoro",
    "gn:population":0,
    "gn:timezone":"Africa/Bangui",
    "iso:country":"CF",
    "name:und_x_variant":[
        "Camba Oro Fortifi\u00e9",
        "Kambaoro"
    ],
    "wof:name":"Kambaoro",
    "wof:placetype":"locality"
},
  "geometry": {"coordinates":[16.78859,3.65939],"type":"Point"}
}