{
  "type": "Feature",
  "properties": {
    "gn:admin1_code":"17",
    "gn:admin2_code":"9143490.0",
    "gn:asciiname":"Bokpanemo",
    "gn:country_code":"CF",
    "gn:dem":625,
    "gn:feature_class":"P",
    "gn:feature_code":"PPL",
    "gn:name":"Bokpan\u00e9mo",
    "gn:population":0,
    "gn:timezone":"Africa/Bangui",
    "iso:country":"CF",
    "wof:name":"Bokpanemo",
    "wof:placetype":"locality"
},
  "geometry": {"coordinates":[18.27799,5.68246],"type":"Point"}
}