{
  "type": "Feature",
  "properties": {
    "gn:admin1_code":"13",
    "gn:admin2_code":"9143494.0",
    "gn:asciiname":"Bedoua II",
    "gn:country_code":"CF",
    "gn:dem":455,
    "gn:feature_class":"P",
    "gn:feature_code":"PPL",
    "gn:name":"B\u00e9doua II",
    "gn:population":0,
    "gn:timezone":"Africa/Bangui",
    "iso:country":"CF",
    "wof:name":"Bedoua II",
    "wof:placetype":"locality"
},
  "geometry": {"coordinates":[16.48279,7.71379],"type":"Point"}
}