{
  "type": "Feature",
  "properties": {
    "gn:admin1_code":"4.0",
    "gn:admin2_code":"7732916.0",
    "gn:asciiname":"Karidimbo",
    "gn:country_code":"CF",
    "gn:dem":630,
    "gn:feature_class":"P",
    "gn:feature_code":"PPL",
    "gn:name":"Karidimbo",
    "gn:population":0,
    "gn:timezone":"Africa/Bangui",
    "iso:country":"CF",
    "wof:name":"Karidimbo",
    "wof:placetype":"locality"
},
  "geometry": {"coordinates":[14.9639,4.45132],"type":"Point"}
}