{
  "type": "Feature",
  "properties": {
    "gn:admin1_code":"17",
    "gn:admin2_code":"7731895.0",
    "gn:asciiname":"Dombe",
    "gn:country_code":"CF",
    "gn:dem":395,
    "gn:feature_class":"P",
    "gn:feature_code":"PPL",
    "gn:name":"Domb\u00e9",
    "gn:population":0,
    "gn:timezone":"Africa/Bangui",
    "iso:country":"CF",
    "wof:name":"Dombe",
    "wof:placetype":"locality"
},
  "geometry": {"coordinates":[18.95897,5.25191],"type":"Point"}
}