{
  "type": "Feature",
  "properties": {
    "gn:admin1_code":"3.0",
    "gn:admin2_code":"9143465.0",
    "gn:asciiname":"Hyrra Banda",
    "gn:country_code":"CF",
    "gn:dem":600,
    "gn:feature_class":"P",
    "gn:feature_code":"PPL",
    "gn:name":"Hyrra Banda",
    "gn:population":0,
    "gn:timezone":"Africa/Bangui",
    "iso:country":"CF",
    "name:und_x_variant":[
        "Ira Banda",
        "Hirra Banda",
        "Hyrra Banda"
    ],
    "wof:name":"Hyrra Banda",
    "wof:placetype":"locality"
},
  "geometry": {"coordinates":[22.07052,5.95392],"type":"Point"}
}