{
  "type": "Feature",
  "properties": {
    "gn:admin1_code":"8.0",
    "gn:admin2_code":"7732690.0",
    "gn:asciiname":"Binga",
    "gn:country_code":"CF",
    "gn:dem":540,
    "gn:feature_class":"P",
    "gn:feature_code":"PPL",
    "gn:name":"Binga",
    "gn:population":0,
    "gn:timezone":"Africa/Bangui",
    "iso:country":"CF",
    "name:bar_x_preferred":[
        "Binga"
    ],
    "name:ceb_x_preferred":[
        "Binga"
    ],
    "name:fra_x_preferred":[
        "Binga"
    ],
    "name:ita_x_preferred":[
        "Binga"
    ],
    "name:nld_x_preferred":[
        "Binga"
    ],
    "name:por_x_preferred":[
        "Binga"
    ],
    "name:rus_x_preferred":[
        "\u0411\u0438\u043d\u0433\u0430"
    ],
    "name:swe_x_preferred":[
        "Binga"
    ],
    "name:tgl_x_preferred":[
        "Binga"
    ],
    "name:ukr_x_preferred":[
        "\u0411\u0456\u043d\u0433\u0430"
    ],
    "wof:name":"Binga",
    "wof:placetype":"locality"
},
  "geometry": {"coordinates":[22.40485,5.07115],"type":"Point"}
}