{
  "type": "Feature",
  "properties": {
    "gn:admin1_code":"4.0",
    "gn:admin2_code":"7732685.0",
    "gn:asciiname":"Zabo",
    "gn:country_code":"CF",
    "gn:dem":575,
    "gn:feature_class":"P",
    "gn:feature_code":"PPL",
    "gn:name":"Zabo",
    "gn:population":0,
    "gn:timezone":"Africa/Bangui",
    "iso:country":"CF",
    "name:fra_x_preferred":[
        "Zabo"
    ],
    "wof:name":"Zabo",
    "wof:placetype":"locality"
},
  "geometry": {"coordinates":[15.62914,4.10392],"type":"Point"}
}