{
  "type": "Feature",
  "properties": {
    "gn:admin1_code":"15",
    "gn:admin2_code":"9143469.0",
    "gn:asciiname":"Gribingui I",
    "gn:country_code":"CF",
    "gn:dem":441,
    "gn:feature_class":"P",
    "gn:feature_code":"PPL",
    "gn:name":"Gribingui I",
    "gn:population":0,
    "gn:timezone":"Africa/Bangui",
    "iso:country":"CF",
    "wof:name":"Gribingui I",
    "wof:placetype":"locality"
},
  "geometry": {"coordinates":[19.08388,7.07705],"type":"Point"}
}