{
  "type": "Feature",
  "properties": {
    "gn:admin1_code":"2.0",
    "gn:admin2_code":"7731891.0",
    "gn:asciiname":"Boulangba",
    "gn:country_code":"CF",
    "gn:dem":423,
    "gn:feature_class":"P",
    "gn:feature_code":"PPL",
    "gn:name":"Boulangba",
    "gn:population":0,
    "gn:timezone":"Africa/Bangui",
    "iso:country":"CF",
    "wof:name":"Boulangba",
    "wof:placetype":"locality"
},
  "geometry": {"coordinates":[21.13611,4.46571],"type":"Point"}
}