{
  "type": "Feature",
  "properties": {
    "gn:admin1_code":"12.0",
    "gn:admin2_code":"9143479.0",
    "gn:asciiname":"Kadanga",
    "gn:country_code":"CF",
    "gn:dem":480,
    "gn:feature_class":"P",
    "gn:feature_code":"PPL",
    "gn:name":"Kadanga",
    "gn:population":0,
    "gn:timezone":"Africa/Bangui",
    "iso:country":"CF",
    "wof:name":"Kadanga",
    "wof:placetype":"locality"
},
  "geometry": {"coordinates":[17.27925,7.22858],"type":"Point"}
}