{
  "type": "Feature",
  "properties": {
    "gn:admin1_code":"12",
    "gn:admin2_code":"9143479.0",
    "gn:asciiname":"Bele II",
    "gn:country_code":"CF",
    "gn:dem":426,
    "gn:feature_class":"P",
    "gn:feature_code":"PPL",
    "gn:name":"B\u00e9l\u00e9 II",
    "gn:population":0,
    "gn:timezone":"Africa/Bangui",
    "iso:country":"CF",
    "wof:name":"Bele II",
    "wof:placetype":"locality"
},
  "geometry": {"coordinates":[17.10431,7.65659],"type":"Point"}
}