{
  "type": "Feature",
  "properties": {
    "gn:admin1_code":"17",
    "gn:admin2_code":"8299285.0",
    "gn:asciiname":"Bogbayo",
    "gn:country_code":"CF",
    "gn:dem":395,
    "gn:feature_class":"P",
    "gn:feature_code":"PPL",
    "gn:name":"Bogbayo",
    "gn:population":0,
    "gn:timezone":"Africa/Bangui",
    "iso:country":"CF",
    "wof:name":"Bogbayo",
    "wof:placetype":"locality"
},
  "geometry": {"coordinates":[18.10292,4.79693],"type":"Point"}
}