{
  "type": "Feature",
  "properties": {
    "gn:admin1_code":"11.0",
    "gn:admin2_code":"7731893.0",
    "gn:asciiname":"Boundi",
    "gn:country_code":"CF",
    "gn:dem":431,
    "gn:feature_class":"P",
    "gn:feature_code":"PPL",
    "gn:name":"Boundi",
    "gn:population":0,
    "gn:timezone":"Africa/Bangui",
    "iso:country":"CF",
    "wof:name":"Boundi",
    "wof:placetype":"locality"
},
  "geometry": {"coordinates":[20.69316,5.30262],"type":"Point"}
}