{
  "type": "Feature",
  "properties": {
    "gn:admin1_code":"11.0",
    "gn:admin2_code":"7732062.0",
    "gn:asciiname":"Kea",
    "gn:country_code":"CF",
    "gn:dem":586,
    "gn:feature_class":"P",
    "gn:feature_code":"PPL",
    "gn:name":"K\u00e9a",
    "gn:population":0,
    "gn:timezone":"Africa/Bangui",
    "iso:country":"CF",
    "name:afr_x_preferred":[
        "Kea"
    ],
    "name:ang_x_preferred":[
        "Kea"
    ],
    "name:ara_x_preferred":[
        "\u0643\u064a\u0627"
    ],
    "name:arg_x_preferred":[
        "Nestor notabilis"
    ],
    "name:bre_x_preferred":[
        "Kea"
    ],
    "name:bul_x_preferred":[
        "\u041a\u0435\u0430"
    ],
    "name:cat_x_preferred":[
        "Kea"
    ],
    "name:ceb_x_preferred":[
        "Nestor notabilis"
    ],
    "name:ces_x_preferred":[
        "Nestor kea"
    ],
    "name:cym_x_preferred":[
        "Cea"
    ],
    "name:dan_x_preferred":[
        "Kea"
    ],
    "name:deu_x_preferred":[
        "Kea"
    ],
    "name:epo_x_preferred":[
        "Keo"
    ],
    "name:est_x_preferred":[
        "Kea"
    ],
    "name:eus_x_preferred":[
        "Nestor notabilis"
    ],
    "name:fas_x_preferred":[
        "\u06a9\u06cc\u0627"
    ],
    "name:fin_x_preferred":[
        "Kea"
    ],
    "name:fra_x_preferred":[
        "Nestor k\u00e9a"
    ],
    "name:heb_x_preferred":[
        "\u05e7\u05d9\u05d0\u05d4"
    ],
    "name:hun_x_preferred":[
        "Kea"
    ],
    "name:ind_x_preferred":[
        "Kea"
    ],
    "name:isl_x_preferred":[
        "Kea"
    ],
    "name:ita_x_preferred":[
        "Nestor notabilis"
    ],
    "name:jpn_x_preferred":[
        "\u30df\u30e4\u30de\u30aa\u30a6\u30e0"
    ],
    "name:kan_x_preferred":[
        "\u0c95\u0cbf\u0caf\u0cbe \u0c97\u0cbf\u0ca3\u0cbf"
    ],
    "name:kor_x_preferred":[
        "\ucf00\uc544\uc575\ubb34"
    ],
    "name:lav_x_preferred":[
        "Kea"
    ],
    "name:mkd_x_preferred":[
        "\u041a\u0435\u0430"
    ],
    "name:mri_x_preferred":[
        "Kea"
    ],
    "name:mrj_x_preferred":[
        "\u041a\u0435\u0430"
    ],
    "name:nld_x_preferred":[
        "Kea"
    ],
    "name:nno_x_preferred":[
        "Fuglen kea"
    ],
    "name:nor_x_preferred":[
        "Kea"
    ],
    "name:pnb_x_preferred":[
        "\u06a9\u06cc\u0627"
    ],
    "name:pol_x_preferred":[
        "Nestor kea"
    ],
    "name:por_x_preferred":[
        "Papagaio-da-Nova-Zel\u00e2ndia"
    ],
    "name:que_x_preferred":[
        "Kiya"
    ],
    "name:ron_x_preferred":[
        "Kea"
    ],
    "name:rus_x_preferred":[
        "\u041a\u0435\u0430"
    ],
    "name:slk_x_preferred":[
        "Nestor kea"
    ],
    "name:spa_x_preferred":[
        "Nestor notabilis"
    ],
    "name:srp_x_preferred":[
        "\u041a\u0435\u0430"
    ],
    "name:swe_x_preferred":[
        "Kea"
    ],
    "name:ukr_x_preferred":[
        "\u041a\u0435\u0430"
    ],
    "name:vie_x_preferred":[
        "V\u1eb9t kea"
    ],
    "name:war_x_preferred":[
        "Nestor notabilis"
    ],
    "name:zho_x_preferred":[
        "\u5544\u7f8a\u9e66\u9e49"
    ],
    "wof:name":"Kea",
    "wof:placetype":"locality"
},
  "geometry": {"coordinates":[21.38333,5.73333],"type":"Point"}
}