{
  "type": "Feature",
  "properties": {
    "gn:admin1_code":"5.0",
    "gn:admin2_code":"9143462.0",
    "gn:asciiname":"La Ouagou",
    "gn:country_code":"CF",
    "gn:dem":652,
    "gn:feature_class":"P",
    "gn:feature_code":"PPL",
    "gn:name":"La Ouagou",
    "gn:population":0,
    "gn:timezone":"Africa/Bangui",
    "iso:country":"CF",
    "wof:name":"La Ouagou",
    "wof:placetype":"locality"
},
  "geometry": {"coordinates":[25.96667,5.76463],"type":"Point"}
}