{
  "type": "Feature",
  "properties": {
    "gn:admin1_code":"15",
    "gn:admin2_code":"9143470.0",
    "gn:asciiname":"Gueme",
    "gn:country_code":"CF",
    "gn:dem":470,
    "gn:feature_class":"P",
    "gn:feature_code":"PPL",
    "gn:name":"Gu\u00e9m\u00e9",
    "gn:population":0,
    "gn:timezone":"Africa/Bangui",
    "iso:country":"CF",
    "name:fra_x_preferred":[
        "Gu\u00e9m\u00e9"
    ],
    "name:msa_x_preferred":[
        "Gueme"
    ],
    "wof:name":"Gueme",
    "wof:placetype":"locality"
},
  "geometry": {"coordinates":[19.95165,7.10527],"type":"Point"}
}