{
  "type": "Feature",
  "properties": {
    "gn:admin1_code":"0.0",
    "gn:asciiname":"Bangolo",
    "gn:country_code":"CF",
    "gn:dem":438,
    "gn:feature_class":"P",
    "gn:feature_code":"PPL",
    "gn:name":"Bangolo",
    "gn:population":0,
    "gn:timezone":"Africa/Bangui",
    "iso:country":"CF",
    "wof:name":"Bangolo",
    "wof:placetype":"locality"
},
  "geometry": {"coordinates":[20.11667000000001,4.53333],"type":"Point"}
}