{
  "type": "Feature",
  "properties": {
    "gn:admin1_code":"13.0",
    "gn:admin2_code":"9143491.0",
    "gn:asciiname":"Bam",
    "gn:country_code":"CF",
    "gn:dem":974,
    "gn:feature_class":"P",
    "gn:feature_code":"PPL",
    "gn:name":"Bam",
    "gn:population":0,
    "gn:timezone":"Africa/Bangui",
    "iso:country":"CF",
    "name:bos_x_preferred":[
        "Bam"
    ],
    "name:ceb_x_preferred":[
        "Bam"
    ],
    "name:ces_x_preferred":[
        "Bam"
    ],
    "name:deu_x_preferred":[
        "Bam"
    ],
    "name:fin_x_preferred":[
        "Bam"
    ],
    "name:mlg_x_preferred":[
        "Bam"
    ],
    "name:nld_x_preferred":[
        "Bam"
    ],
    "name:rus_x_preferred":[
        "\u0411\u0430\u043c"
    ],
    "name:slk_x_preferred":[
        "Bam"
    ],
    "name:swe_x_preferred":[
        "Bam"
    ],
    "name:ukr_x_preferred":[
        "\u0411\u0430\u043c"
    ],
    "name:uzb_x_preferred":[
        "Bam"
    ],
    "wof:name":"Bam",
    "wof:placetype":"locality"
},
  "geometry": {"coordinates":[15.89957,6.55866],"type":"Point"}
}