{
  "type": "Feature",
  "properties": {
    "gn:admin1_code":"17.0",
    "gn:admin2_code":"7731895.0",
    "gn:asciiname":"Gba",
    "gn:country_code":"CF",
    "gn:dem":469,
    "gn:feature_class":"P",
    "gn:feature_code":"PPL",
    "gn:name":"Gba",
    "gn:population":0,
    "gn:timezone":"Africa/Bangui",
    "iso:country":"CF",
    "wof:name":"Gba",
    "wof:placetype":"locality"
},
  "geometry": {"coordinates":[18.60447000000001,4.69906],"type":"Point"}
}