{
  "type": "Feature",
  "properties": {
    "gn:admin1_code":"2.0",
    "gn:admin2_code":"9143474.0",
    "gn:asciiname":"Ngbindjou",
    "gn:country_code":"CF",
    "gn:dem":563,
    "gn:feature_class":"P",
    "gn:feature_code":"PPL",
    "gn:name":"Ngbindjou",
    "gn:population":0,
    "gn:timezone":"Africa/Bangui",
    "iso:country":"CF",
    "wof:name":"Ngbindjou",
    "wof:placetype":"locality"
},
  "geometry": {"coordinates":[21.23333,4.81667],"type":"Point"}
}