{
  "type": "Feature",
  "properties": {
    "gn:admin1_code":"8.0",
    "gn:admin2_code":"7732690.0",
    "gn:asciiname":"Paouara",
    "gn:country_code":"CF",
    "gn:dem":554,
    "gn:feature_class":"P",
    "gn:feature_code":"PPL",
    "gn:name":"Paouara",
    "gn:population":0,
    "gn:timezone":"Africa/Bangui",
    "iso:country":"CF",
    "wof:name":"Paouara",
    "wof:placetype":"locality"
},
  "geometry": {"coordinates":[23.03667,5.38723],"type":"Point"}
}