{
  "type": "Feature",
  "properties": {
    "gn:admin1_code":"8.0",
    "gn:admin2_code":"9143468.0",
    "gn:asciiname":"Bawombo",
    "gn:cc2":"CF",
    "gn:country_code":"CF",
    "gn:dem":660,
    "gn:feature_class":"P",
    "gn:feature_code":"PPL",
    "gn:name":"Bawombo",
    "gn:population":0,
    "gn:timezone":"Africa/Bangui",
    "iso:country":"CF",
    "name:und_x_variant":[
        "Baouombo",
        "Bawombo"
    ],
    "wof:name":"Bawombo",
    "wof:placetype":"locality"
},
  "geometry": {"coordinates":[24.21667,5.26667],"type":"Point"}
}