{
  "type": "Feature",
  "properties": {
    "gn:admin1_code":"12.0",
    "gn:admin2_code":"7732115.0",
    "gn:asciiname":"Ouda-Kete",
    "gn:country_code":"CF",
    "gn:dem":600,
    "gn:feature_class":"P",
    "gn:feature_code":"PPL",
    "gn:name":"Ouda-K\u00e8te",
    "gn:population":0,
    "gn:timezone":"Africa/Bangui",
    "iso:country":"CF",
    "wof:name":"Ouda-Kete",
    "wof:placetype":"locality"
},
  "geometry": {"coordinates":[17.59098,5.78043],"type":"Point"}
}