{
  "type": "Feature",
  "properties": {
    "gn:admin1_code":"11.0",
    "gn:admin2_code":"7732377.0",
    "gn:asciiname":"Bareamba",
    "gn:country_code":"CF",
    "gn:dem":594,
    "gn:feature_class":"P",
    "gn:feature_code":"PPL",
    "gn:name":"Bar\u00e9amba",
    "gn:population":0,
    "gn:timezone":"Africa/Bangui",
    "iso:country":"CF",
    "wof:name":"Bareamba",
    "wof:placetype":"locality"
},
  "geometry": {"coordinates":[20.16667,5.96667],"type":"Point"}
}