{
  "type": "Feature",
  "properties": {
    "gn:admin1_code":"12.0",
    "gn:admin2_code":"9143479.0",
    "gn:asciiname":"Bili",
    "gn:country_code":"CF",
    "gn:dem":484,
    "gn:feature_class":"P",
    "gn:feature_code":"PPL",
    "gn:name":"Bili",
    "gn:population":0,
    "gn:timezone":"Africa/Bangui",
    "iso:country":"CF",
    "name:bre_x_preferred":[
        "Bili"
    ],
    "name:ceb_x_preferred":[
        "Bili"
    ],
    "name:fra_x_preferred":[
        "Bili"
    ],
    "name:kat_x_preferred":[
        "\u10d1\u10d8\u10da\u10d8"
    ],
    "name:swe_x_preferred":[
        "Bili"
    ],
    "wof:name":"Bili",
    "wof:placetype":"locality"
},
  "geometry": {"coordinates":[16.9936,7.29304],"type":"Point"}
}