{
  "type": "Feature",
  "properties": {
    "gn:admin1_code":"13.0",
    "gn:admin2_code":"9143493.0",
    "gn:asciiname":"Bene",
    "gn:country_code":"CF",
    "gn:dem":1080,
    "gn:feature_class":"P",
    "gn:feature_code":"PPL",
    "gn:name":"Ben\u00e9",
    "gn:population":0,
    "gn:timezone":"Africa/Bangui",
    "iso:country":"CF",
    "name:ceb_x_preferred":[
        "Bene"
    ],
    "name:deu_x_preferred":[
        "Bene"
    ],
    "name:fra_x_preferred":[
        "Bene"
    ],
    "name:ita_x_preferred":[
        "Bene"
    ],
    "name:rus_x_preferred":[
        "\u0411\u0435\u043d\u0435"
    ],
    "name:srp_x_preferred":[
        "\u0411\u0435\u043d\u0435"
    ],
    "name:swe_x_preferred":[
        "Bene"
    ],
    "name:ukr_x_preferred":[
        "\u0411\u0435\u043d\u0435"
    ],
    "wof:name":"Bene",
    "wof:placetype":"locality"
},
  "geometry": {"coordinates":[15.76667,7.31667],"type":"Point"}
}