{
  "type": "Feature",
  "properties": {
    "gn:admin1_code":"7.0",
    "gn:admin2_code":"9143487.0",
    "gn:asciiname":"Bougoin",
    "gn:country_code":"CF",
    "gn:dem":655,
    "gn:feature_class":"P",
    "gn:feature_code":"PPL",
    "gn:name":"Bougoin",
    "gn:population":0,
    "gn:timezone":"Africa/Bangui",
    "iso:country":"CF",
    "name:und_x_variant":[
        "Boungoy",
        "Bougouin",
        "Bougoin"
    ],
    "wof:name":"Bougoin",
    "wof:placetype":"locality"
},
  "geometry": {"coordinates":[17.32532999999999,4.55753],"type":"Point"}
}