{
  "type": "Feature",
  "properties": {
    "gn:admin1_code":"12",
    "gn:admin2_code":"9143477.0",
    "gn:asciiname":"Kotolinga",
    "gn:country_code":"CF",
    "gn:dem":535,
    "gn:feature_class":"P",
    "gn:feature_code":"PPL",
    "gn:name":"Kotolinga",
    "gn:population":0,
    "gn:timezone":"Africa/Bangui",
    "iso:country":"CF",
    "wof:name":"Kotolinga",
    "wof:placetype":"locality"
},
  "geometry": {"coordinates":[18.3654,5.92871],"type":"Point"}
}