{
  "type": "Feature",
  "properties": {
    "gn:admin1_code":"8.0",
    "gn:admin2_code":"7731888.0",
    "gn:asciiname":"Bozegi",
    "gn:country_code":"CF",
    "gn:dem":496,
    "gn:feature_class":"P",
    "gn:feature_code":"PPL",
    "gn:name":"Boz\u00e9gi",
    "gn:population":0,
    "gn:timezone":"Africa/Bangui",
    "iso:country":"CF",
    "name:und_x_variant":[
        "Bozegui",
        "Bos\u00e9gui",
        "Boz\u00e9gi"
    ],
    "wof:name":"Bozegi",
    "wof:placetype":"locality"
},
  "geometry": {"coordinates":[22.68632,4.50579],"type":"Point"}
}